Workbook

Sheet Guide
B1: Project Management KPI Tracker – User Guide
B2: Covers all 16 KPIs: target setting → data capture → automatic calculation → RAG monitoring → corrective actions → verified improvement.
B4: HOW IT WORKS – MONTHLY CYCLE
B5: 1. Set targets | C5: KPI_Targets: set Target, Amber limit, Direction and Owner for each KPI. Any later change → one row in Target_Revisions (date, old/new, reason, approver).
B6: 2. Capture data | C6: Fill the green-tab logs during the month (Projects, Cost_Schedule, Change_Log, Risk_Log, Issue_Log, Stakeholder_Survey, Resources, Milestones, Quality_Log, Benefits_Log, CI_Log). Only type in YELLOW cells; grey cells calculate.
B7: 3. Review | C7: KPI_Tracking calculates every KPI per month and colours it GREEN / AMBER / RED. Dashboard shows the selected month, trend vs previous month and the portfolio snapshot. Trends shows all 16 charts.
B8: 4. Act | C8: For every AMBER/RED KPI open a row in Action_Log: value before, root cause, action, owner, due date. Due status flags OVERDUE automatically.
B9: 5. Verify the change | C9: When implemented, enter the date and the KPI value after. 'Result' shows Improved / No change / Worse (direction-aware). Process improvements go to CI_Log with 'Benefit verified'.
B10: 6. Close the month | C10: Settings › Current reporting month defaults to today's month. Overwrite it with a fixed date to freeze a reported period.
B12: SHEET MAP
B13: Dashboard | C13: One-page view: RAG tiles, 16 KPI table (target, actual, previous, trend, status, actions), portfolio snapshot, 7 charts.
B14: KPI_Tracking | C14: Engine: monthly actuals (12 months) for all 16 KPIs, latest value, RAG grid, count of GREEN/AMBER/RED per month.
B15: Trends | C15: 16 charts – bars = actual, dashed red line = target.
B16: KPI_Targets | C16: Definitions, calculation method, unit, direction, target, amber limit, owner, watch-outs.
B17: Target_Revisions | C17: Audit trail of target changes.
B18: Action_Log | C18: Corrective actions / implemented changes with before–after effectiveness check.
B19: Projects | C19: Register → On-Time Delivery (#4) and Project Success Rate (#10).
B20: Cost_Schedule | C20: Monthly earned value per project → Schedule Variance (#1), Cost Variance (#2), Budget Utilization (#3).
B21: Change_Log | C21: Change requests → Scope Change Frequency (#5) and CR Approval Time (#13).
B22: Risk_Log | C22: Risk register → Risk Mitigation Effectiveness (#6).
B23: Issue_Log | C23: Issues → Issue Resolution Time (#7).
B24: Stakeholder_Survey | C24: Survey scores → Stakeholder Satisfaction (#8).
... B30: Settings | C30: Year start, current month, budget tolerance, and all drop-down lists.
B32: COLOUR CODE
B33: Yellow cell / blue text | C33: Input – type here.
B34: Grey cell / black text | C34: Formula – do not overwrite.
B35: Green text | C35: Value pulled from another sheet (e.g. targets in KPI_Tracking).
B36: GREEN / AMBER / RED | C36: Higher-is-better KPI: GREEN ≥ target, AMBER ≥ amber limit, else RED. Lower-is-better KPI: GREEN ≤ target, AMBER ≤ amber limit, else RED.
B38: BEFORE YOU USE IT FOR REAL
B39: Sample data | C39: All logs contain realistic sample data (Jan–Oct 2026) so you can see the dashboard working. Select the yellow cells in each log and press Delete – keep the grey formula columns.
B40: Dates | C40: Months in Cost_Schedule and Resources must be the 1st of the month. All logs accept ~500 rows (Projects 100).
B41: Missing data | C41: If a log has no entry for a month, that KPI shows blank (not zero) and is counted as NO DATA on the Dashboard.
B42: Charts | C42: Blank months show no bar. Add rows inside the existing ranges – formulas already cover them.
B44: KPI DESIGN CHALLENGES – read once
B45: Overlaps | C45: Budget Utilization alone is misleading: 100% of budget spent on 70% of the work looks 'perfect'. Always read it with Cost Variance (#2) – that is why both are calculated from the same EVM data.
B46: Schedule variance | C46: The picture says 'timelines'. Date-only variance hides partial progress; this workbook uses earned value (SV%) and keeps milestone dates in #11 and project finish dates in #4.
B47: Small samples | C47: On-Time Delivery and Success Rate run YTD because only a few projects finish per month. One late project can move the % by 20+ points – look at the count, not only the %.
B48: Utilisation | C48: Higher is not always better. Sustained >95% resource utilisation means no slack for breakdowns or learning; treat it as a warning, not a win.
B49: Productivity | C49: A 'Team Productivity Index' is only meaningful if each team defines one stable output unit (m drilled, t moved, WOs closed). Changing the unit mid-year breaks the trend.
B50: Continuous improvement | C50: Counting initiatives measures activity, not improvement. Use 'Benefit verified' in CI_Log and the before/after values in Action_Log to prove impact.
B51: Targets | C51: Set targets from your own baseline (last 6–12 months) before stretching them, and log every change – moving targets silently destroys trend credibility.

Sheet Dashboard
B1: PROJECT MANAGEMENT KPI DASHBOARD
B2: =Settings!B4 -> Mining Services – Project Portfolio
B4: Reporting month ▶ | C4: =MIN(Settings!$B$6,EDATE(Settings!$B$5,11)) -> 46296 | D4: ← select a month from the drop-down
B6: KPI status this month | C6: GREEN | E6: AMBER | G6: RED | I6: NO DATA
B7: =IF(SUM(C7:H7)=0,"",TEXT(C7/(C7+E7+G7),"0%")&" of measured KPIs on target") -> 44% of measured KPIs on target | C7: =COUNTIF($H$11:$H$26,"GREEN") -> 7 | E7: =COUNTIF($H$11:$H$26,"AMBER") -> 4 | G7: =COUNTIF($H$11:$H$26,"RED") -> 5 | I7: =COUNTBLANK($D$11:$D$26) -> 0
B10: KPI | C10: Target | D10: Actual | E10: Prev. month | F10: Change | G10: Trend | H10: Status | I10: Open actions | J10: Actions done | L10: PORTFOLIO SNAPSHOT (live)
B11: =KPI_Tracking!B5 -> Project Schedule Variance (SV%) | C11: =KPI_Tracking!E5 -> 0 | D11: =IFERROR(INDEX(KPI_Tracking!$G5:$R5,MATCH($C$4,KPI_Tracking!$G$4:$R$4,0)),"") -> -0.067027027 | E11: =IFERROR(IF(MATCH($C$4,KPI_Tracking!$G$4:$R$4,0)=1,"",INDEX(KPI_Tracking!$G5:$R5,MATCH($C$4,KPI_Tracking!$G$4:$R$4,0)-1)),"") -> -0.034266327 | F11: =IF(OR(D11="",E11=""),"",D11-E11) -> -0.0327607 | G11: =IF(F11="","",IF(F11=0,"► Stable",IF((F11>0)=(KPI_Tracking!$D5="Higher"),"▲ Better","▼ Worse"))) -> ▼ Worse | H11: =IF(D11="","",IF(KPI_Tracking!$D5="Higher",IF(D11>=KPI_Tracking!$E5,"GREEN",IF(D11>=KPI_Tracking!$F5,"AMBER","RED")),IF(D11<=KPI_Tracking!$E5,"GREEN",IF(D11<=KPI_Tracking!$F5,"AMBER","RED")))) -> RED | I11: =COUNTIFS(Action_Log!$C$5:$C$504,B11,Action_Log!$J$5:$J$504,"Open")+COUNTIFS(Action_Log!$C$5:$C$504,B11,Action_Log!$J$5:$J$504,"In progress") -> 0 | J11: =COUNTIFS(Action_Log!$C$5:$C$504,B11,Action_Log!$J$5:$J$504,"Implemented") -> 1 | L11: Projects registered | M11: =COUNTA(Projects!$A$5:$A$104) -> 8
B12: =KPI_Tracking!B6 -> Project Cost Variance (CV%) | C12: =KPI_Tracking!E6 -> 0 | D12: =IFERROR(INDEX(KPI_Tracking!$G6:$R6,MATCH($C$4,KPI_Tracking!$G$4:$R$4,0)),"") -> -0.037369641 | E12: =IFERROR(IF(MATCH($C$4,KPI_Tracking!$G$4:$R$4,0)=1,"",INDEX(KPI_Tracking!$G6:$R6,MATCH($C$4,KPI_Tracking!$G$4:$R$4,0)-1)),"") -> -0.01668716 | F12: =IF(OR(D12="",E12=""),"",D12-E12) -> -0.020682481 | G12: =IF(F12="","",IF(F12=0,"► Stable",IF((F12>0)=(KPI_Tracking!$D6="Higher"),"▲ Better","▼ Worse"))) -> ▼ Worse | H12: =IF(D12="","",IF(KPI_Tracking!$D6="Higher",IF(D12>=KPI_Tracking!$E6,"GREEN",IF(D12>=KPI_Tracking!$F6,"AMBER","RED")),IF(D12<=KPI_Tracking!$E6,"GREEN",IF(D12<=KPI_Tracking!$F6,"AMBER","RED")))) -> AMBER | I12: =COUNTIFS(Action_Log!$C$5:$C$504,B12,Action_Log!$J$5:$J$504,"Open")+COUNTIFS(Action_Log!$C$5:$C$504,B12,Action_Log!$J$5:$J$504,"In progress") -> 1 | J12: =COUNTIFS(Action_Log!$C$5:$C$504,B12,Action_Log!$J$5:$J$504,"Implemented") -> 1 | L12: Active projects | M12: =COUNTIF(Projects!$I$5:$I$104,"Active") -> 3
B13: =KPI_Tracking!B7 -> Budget Utilization | C13: =KPI_Tracking!E7 -> 1 | D13: =IFERROR(INDEX(KPI_Tracking!$G7:$R7,MATCH($C$4,KPI_Tracking!$G$4:$R$4,0)),"") -> 0.95493333 | E13: =IFERROR(IF(MATCH($C$4,KPI_Tracking!$G$4:$R$4,0)=1,"",INDEX(KPI_Tracking!$G7:$R7,MATCH($C$4,KPI_Tracking!$G$4:$R$4,0)-1)),"") -> 0.94420881 | F13: =IF(OR(D13="",E13=""),"",D13-E13) -> 0.010724524 | G13: =IF(F13="","",IF(F13=0,"► Stable",IF((F13>0)=(KPI_Tracking!$D7="Higher"),"▲ Better","▼ Worse"))) -> ▼ Worse | H13: =IF(D13="","",IF(KPI_Tracking!$D7="Higher",IF(D13>=KPI_Tracking!$E7,"GREEN",IF(D13>=KPI_Tracking!$F7,"AMBER","RED")),IF(D13<=KPI_Tracking!$E7,"GREEN",IF(D13<=KPI_Tracking!$F7,"AMBER","RED")))) -> GREEN | I13: =COUNTIFS(Action_Log!$C$5:$C$504,B13,Action_Log!$J$5:$J$504,"Open")+COUNTIFS(Action_Log!$C$5:$C$504,B13,Action_Log!$J$5:$J$504,"In progress") -> 0 | J13: =COUNTIFS(Action_Log!$C$5:$C$504,B13,Action_Log!$J$5:$J$504,"Implemented") -> 0 | L13: Completed projects | M13: =COUNTIF(Projects!$I$5:$I$104,"Completed") -> 5
B14: =KPI_Tracking!B8 -> On-Time Project Delivery | C14: =KPI_Tracking!E8 -> 0.9 | D14: =IFERROR(INDEX(KPI_Tracking!$G8:$R8,MATCH($C$4,KPI_Tracking!$G$4:$R$4,0)),"") -> 0.6 | E14: =IFERROR(IF(MATCH($C$4,KPI_Tracking!$G$4:$R$4,0)=1,"",INDEX(KPI_Tracking!$G8:$R8,MATCH($C$4,KPI_Tracking!$G$4:$R$4,0)-1)),"") -> 0.6 | F14: =IF(OR(D14="",E14=""),"",D14-E14) -> 0 | G14: =IF(F14="","",IF(F14=0,"► Stable",IF((F14>0)=(KPI_Tracking!$D8="Higher"),"▲ Better","▼ Worse"))) -> ► Stable | H14: =IF(D14="","",IF(KPI_Tracking!$D8="Higher",IF(D14>=KPI_Tracking!$E8,"GREEN",IF(D14>=KPI_Tracking!$F8,"AMBER","RED")),IF(D14<=KPI_Tracking!$E8,"GREEN",IF(D14<=KPI_Tracking!$F8,"AMBER","RED")))) -> RED | I14: =COUNTIFS(Action_Log!$C$5:$C$504,B14,Action_Log!$J$5:$J$504,"Open")+COUNTIFS(Action_Log!$C$5:$C$504,B14,Action_Log!$J$5:$J$504,"In progress") -> 0 | J14: =COUNTIFS(Action_Log!$C$5:$C$504,B14,Action_Log!$J$5:$J$504,"Implemented") -> 0 | L14: Total budget (BAC) | M14: =SUM(Projects!$J$5:$J$104) -> 13320000
B15: =KPI_Tracking!B9 -> Scope Change Frequency | C15: =KPI_Tracking!E9 -> 0.5 | D15: =IFERROR(INDEX(KPI_Tracking!$G9:$R9,MATCH($C$4,KPI_Tracking!$G$4:$R$4,0)),"") -> 0 | E15: =IFERROR(IF(MATCH($C$4,KPI_Tracking!$G$4:$R$4,0)=1,"",INDEX(KPI_Tracking!$G9:$R9,MATCH($C$4,KPI_Tracking!$G$4:$R$4,0)-1)),"") -> 0 | F15: =IF(OR(D15="",E15=""),"",D15-E15) -> 0 | G15: =IF(F15="","",IF(F15=0,"► Stable",IF((F15>0)=(KPI_Tracking!$D9="Higher"),"▲ Better","▼ Worse"))) -> ► Stable | H15: =IF(D15="","",IF(KPI_Tracking!$D9="Higher",IF(D15>=KPI_Tracking!$E9,"GREEN",IF(D15>=KPI_Tracking!$F9,"AMBER","RED")),IF(D15<=KPI_Tracking!$E9,"GREEN",IF(D15<=KPI_Tracking!$F9,"AMBER","RED")))) -> GREEN | I15: =COUNTIFS(Action_Log!$C$5:$C$504,B15,Action_Log!$J$5:$J$504,"Open")+COUNTIFS(Action_Log!$C$5:$C$504,B15,Action_Log!$J$5:$J$504,"In progress") -> 0 | J15: =COUNTIFS(Action_Log!$C$5:$C$504,B15,Action_Log!$J$5:$J$504,"Implemented") -> 1 | L15: Total forecast cost (EAC) | M15: =SUM(Projects!$K$5:$K$104) -> 13795000
B16: =KPI_Tracking!B10 -> Risk Mitigation Effectiveness | C16: =KPI_Tracking!E10 -> 0.85 | D16: =IFERROR(INDEX(KPI_Tracking!$G10:$R10,MATCH($C$4,KPI_Tracking!$G$4:$R$4,0)),"") -> 0.8125 | E16: =IFERROR(IF(MATCH($C$4,KPI_Tracking!$G$4:$R$4,0)=1,"",INDEX(KPI_Tracking!$G10:$R10,MATCH($C$4,KPI_Tracking!$G$4:$R$4,0)-1)),"") -> 0.76923077 | F16: =IF(OR(D16="",E16=""),"",D16-E16) -> 0.043269231 | G16: =IF(F16="","",IF(F16=0,"► Stable",IF((F16>0)=(KPI_Tracking!$D10="Higher"),"▲ Better","▼ Worse"))) -> ▲ Better | H16: =IF(D16="","",IF(KPI_Tracking!$D10="Higher",IF(D16>=KPI_Tracking!$E10,"GREEN",IF(D16>=KPI_Tracking!$F10,"AMBER","RED")),IF(D16<=KPI_Tracking!$E10,"GREEN",IF(D16<=KPI_Tracking!$F10,"AMBER","RED")))) -> AMBER | I16: =COUNTIFS(Action_Log!$C$5:$C$504,B16,Action_Log!$J$5:$J$504,"Open")+COUNTIFS(Action_Log!$C$5:$C$504,B16,Action_Log!$J$5:$J$504,"In progress") -> 0 | J16: =COUNTIFS(Action_Log!$C$5:$C$504,B16,Action_Log!$J$5:$J$504,"Implemented") -> 0 | L16: Forecast over(−)/under(+) budget | M16: =M14-M15 -> -475000
B17: =KPI_Tracking!B11 -> Issue Resolution Time | C17: =KPI_Tracking!E11 -> 7 | D17: =IFERROR(INDEX(KPI_Tracking!$G11:$R11,MATCH($C$4,KPI_Tracking!$G$4:$R$4,0)),"") -> 5 | E17: =IFERROR(IF(MATCH($C$4,KPI_Tracking!$G$4:$R$4,0)=1,"",INDEX(KPI_Tracking!$G11:$R11,MATCH($C$4,KPI_Tracking!$G$4:$R$4,0)-1)),"") -> 13 | F17: =IF(OR(D17="",E17=""),"",D17-E17) -> -8 | G17: =IF(F17="","",IF(F17=0,"► Stable",IF((F17>0)=(KPI_Tracking!$D11="Higher"),"▲ Better","▼ Worse"))) -> ▲ Better | H17: =IF(D17="","",IF(KPI_Tracking!$D11="Higher",IF(D17>=KPI_Tracking!$E11,"GREEN",IF(D17>=KPI_Tracking!$F11,"AMBER","RED")),IF(D17<=KPI_Tracking!$E11,"GREEN",IF(D17<=KPI_Tracking!$F11,"AMBER","RED")))) -> GREEN | I17: =COUNTIFS(Action_Log!$C$5:$C$504,B17,Action_Log!$J$5:$J$504,"Open")+COUNTIFS(Action_Log!$C$5:$C$504,B17,Action_Log!$J$5:$J$504,"In progress") -> 0 | J17: =COUNTIFS(Action_Log!$C$5:$C$504,B17,Action_Log!$J$5:$J$504,"Implemented") -> 1 | L17: Open risks | M17: =COUNTIF(Risk_Log!$L$5:$L$504,"Open") -> 12
B18: =KPI_Tracking!B12 -> Stakeholder Satisfaction | C18: =KPI_Tracking!E12 -> 4 | D18: =IFERROR(INDEX(KPI_Tracking!$G12:$R12,MATCH($C$4,KPI_Tracking!$G$4:$R$4,0)),"") -> 3.9166667 | E18: =IFERROR(IF(MATCH($C$4,KPI_Tracking!$G$4:$R$4,0)=1,"",INDEX(KPI_Tracking!$G12:$R12,MATCH($C$4,KPI_Tracking!$G$4:$R$4,0)-1)),"") -> 4.3333333 | F18: =IF(OR(D18="",E18=""),"",D18-E18) -> -0.41666667 | G18: =IF(F18="","",IF(F18=0,"► Stable",IF((F18>0)=(KPI_Tracking!$D12="Higher"),"▲ Better","▼ Worse"))) -> ▼ Worse | H18: =IF(D18="","",IF(KPI_Tracking!$D12="Higher",IF(D18>=KPI_Tracking!$E12,"GREEN",IF(D18>=KPI_Tracking!$F12,"AMBER","RED")),IF(D18<=KPI_Tracking!$E12,"GREEN",IF(D18<=KPI_Tracking!$F12,"AMBER","RED")))) -> AMBER | I18: =COUNTIFS(Action_Log!$C$5:$C$504,B18,Action_Log!$J$5:$J$504,"Open")+COUNTIFS(Action_Log!$C$5:$C$504,B18,Action_Log!$J$5:$J$504,"In progress") -> 0 | J18: =COUNTIFS(Action_Log!$C$5:$C$504,B18,Action_Log!$J$5:$J$504,"Implemented") -> 0 | L18: …of which HIGH | M18: =COUNTIFS(Risk_Log!$L$5:$L$504,"Open",Risk_Log!$I$5:$I$504,"High") -> 6
B19: =KPI_Tracking!B13 -> Resource Utilization Rate | C19: =KPI_Tracking!E13 -> 0.85 | D19: =IFERROR(INDEX(KPI_Tracking!$G13:$R13,MATCH($C$4,KPI_Tracking!$G$4:$R$4,0)),"") -> 0.86126374 | E19: =IFERROR(IF(MATCH($C$4,KPI_Tracking!$G$4:$R$4,0)=1,"",INDEX(KPI_Tracking!$G13:$R13,MATCH($C$4,KPI_Tracking!$G$4:$R$4,0)-1)),"") -> 0.84547872 | F19: =IF(OR(D19="",E19=""),"",D19-E19) -> 0.015785013 | G19: =IF(F19="","",IF(F19=0,"► Stable",IF((F19>0)=(KPI_Tracking!$D13="Higher"),"▲ Better","▼ Worse"))) -> ▲ Better | H19: =IF(D19="","",IF(KPI_Tracking!$D13="Higher",IF(D19>=KPI_Tracking!$E13,"GREEN",IF(D19>=KPI_Tracking!$F13,"AMBER","RED")),IF(D19<=KPI_Tracking!$E13,"GREEN",IF(D19<=KPI_Tracking!$F13,"AMBER","RED")))) -> GREEN | I19: =COUNTIFS(Action_Log!$C$5:$C$504,B19,Action_Log!$J$5:$J$504,"Open")+COUNTIFS(Action_Log!$C$5:$C$504,B19,Action_Log!$J$5:$J$504,"In progress") -> 1 | J19: =COUNTIFS(Action_Log!$C$5:$C$504,B19,Action_Log!$J$5:$J$504,"Implemented") -> 0 | L19: Open issues | M19: =COUNTIF(Issue_Log!$G$5:$G$504,"Open")+COUNTIF(Issue_Log!$G$5:$G$504,"In progress") -> 1
B20: =KPI_Tracking!B14 -> Project Success Rate | C20: =KPI_Tracking!E14 -> 0.8 | D20: =IFERROR(INDEX(KPI_Tracking!$G14:$R14,MATCH($C$4,KPI_Tracking!$G$4:$R$4,0)),"") -> 0.6 | E20: =IFERROR(IF(MATCH($C$4,KPI_Tracking!$G$4:$R$4,0)=1,"",INDEX(KPI_Tracking!$G14:$R14,MATCH($C$4,KPI_Tracking!$G$4:$R$4,0)-1)),"") -> 0.6 | F20: =IF(OR(D20="",E20=""),"",D20-E20) -> 0 | G20: =IF(F20="","",IF(F20=0,"► Stable",IF((F20>0)=(KPI_Tracking!$D14="Higher"),"▲ Better","▼ Worse"))) -> ► Stable | H20: =IF(D20="","",IF(KPI_Tracking!$D14="Higher",IF(D20>=KPI_Tracking!$E14,"GREEN",IF(D20>=KPI_Tracking!$F14,"AMBER","RED")),IF(D20<=KPI_Tracking!$E14,"GREEN",IF(D20<=KPI_Tracking!$F14,"AMBER","RED")))) -> RED | I20: =COUNTIFS(Action_Log!$C$5:$C$504,B20,Action_Log!$J$5:$J$504,"Open")+COUNTIFS(Action_Log!$C$5:$C$504,B20,Action_Log!$J$5:$J$504,"In progress") -> 0 | J20: =COUNTIFS(Action_Log!$C$5:$C$504,B20,Action_Log!$J$5:$J$504,"Implemented") -> 0 | L20: Issues open > 14 days | M20: =COUNTIF(Issue_Log!$J$5:$J$504,">14") -> 0
B21: =KPI_Tracking!B15 -> Milestone Completion Rate | C21: =KPI_Tracking!E15 -> 0.9 | D21: =IFERROR(INDEX(KPI_Tracking!$G15:$R15,MATCH($C$4,KPI_Tracking!$G$4:$R$4,0)),"") -> 0.25 | E21: =IFERROR(IF(MATCH($C$4,KPI_Tracking!$G$4:$R$4,0)=1,"",INDEX(KPI_Tracking!$G15:$R15,MATCH($C$4,KPI_Tracking!$G$4:$R$4,0)-1)),"") -> 1 | F21: =IF(OR(D21="",E21=""),"",D21-E21) -> -0.75 | G21: =IF(F21="","",IF(F21=0,"► Stable",IF((F21>0)=(KPI_Tracking!$D15="Higher"),"▲ Better","▼ Worse"))) -> ▼ Worse | H21: =IF(D21="","",IF(KPI_Tracking!$D15="Higher",IF(D21>=KPI_Tracking!$E15,"GREEN",IF(D21>=KPI_Tracking!$F15,"AMBER","RED")),IF(D21<=KPI_Tracking!$E15,"GREEN",IF(D21<=KPI_Tracking!$F15,"AMBER","RED")))) -> RED | I21: =COUNTIFS(Action_Log!$C$5:$C$504,B21,Action_Log!$J$5:$J$504,"Open")+COUNTIFS(Action_Log!$C$5:$C$504,B21,Action_Log!$J$5:$J$504,"In progress") -> 0 | J21: =COUNTIFS(Action_Log!$C$5:$C$504,B21,Action_Log!$J$5:$J$504,"Implemented") -> 1 | L21: Change requests pending | M21: =COUNTIF(Change_Log!$I$5:$I$504,"Pending") -> 1
B22: =KPI_Tracking!B16 -> Project Quality Index | C22: =KPI_Tracking!E16 -> 0.95 | D22: =IFERROR(INDEX(KPI_Tracking!$G16:$R16,MATCH($C$4,KPI_Tracking!$G$4:$R$4,0)),"") -> 1 | E22: =IFERROR(IF(MATCH($C$4,KPI_Tracking!$G$4:$R$4,0)=1,"",INDEX(KPI_Tracking!$G16:$R16,MATCH($C$4,KPI_Tracking!$G$4:$R$4,0)-1)),"") -> 1 | F22: =IF(OR(D22="",E22=""),"",D22-E22) -> 0 | G22: =IF(F22="","",IF(F22=0,"► Stable",IF((F22>0)=(KPI_Tracking!$D16="Higher"),"▲ Better","▼ Worse"))) -> ► Stable | H22: =IF(D22="","",IF(KPI_Tracking!$D16="Higher",IF(D22>=KPI_Tracking!$E16,"GREEN",IF(D22>=KPI_Tracking!$F16,"AMBER","RED")),IF(D22<=KPI_Tracking!$E16,"GREEN",IF(D22<=KPI_Tracking!$F16,"AMBER","RED")))) -> GREEN | I22: =COUNTIFS(Action_Log!$C$5:$C$504,B22,Action_Log!$J$5:$J$504,"Open")+COUNTIFS(Action_Log!$C$5:$C$504,B22,Action_Log!$J$5:$J$504,"In progress") -> 0 | J22: =COUNTIFS(Action_Log!$C$5:$C$504,B22,Action_Log!$J$5:$J$504,"Implemented") -> 1 | L22: Approved CR cost impact (YTD) | M22: =SUMIFS(Change_Log!$G$5:$G$504,Change_Log!$I$5:$I$504,"Approved") -> 449000
B23: =KPI_Tracking!B17 -> Change Request Approval Time | C23: =KPI_Tracking!E17 -> 5 | D23: =IFERROR(INDEX(KPI_Tracking!$G17:$R17,MATCH($C$4,KPI_Tracking!$G$4:$R$4,0)),"") -> 5 | E23: =IFERROR(IF(MATCH($C$4,KPI_Tracking!$G$4:$R$4,0)=1,"",INDEX(KPI_Tracking!$G17:$R17,MATCH($C$4,KPI_Tracking!$G$4:$R$4,0)-1)),"") -> 6.6666667 | F23: =IF(OR(D23="",E23=""),"",D23-E23) -> -1.6666667 | G23: =IF(F23="","",IF(F23=0,"► Stable",IF((F23>0)=(KPI_Tracking!$D17="Higher"),"▲ Better","▼ Worse"))) -> ▲ Better | H23: =IF(D23="","",IF(KPI_Tracking!$D17="Higher",IF(D23>=KPI_Tracking!$E17,"GREEN",IF(D23>=KPI_Tracking!$F17,"AMBER","RED")),IF(D23<=KPI_Tracking!$E17,"GREEN",IF(D23<=KPI_Tracking!$F17,"AMBER","RED")))) -> GREEN | I23: =COUNTIFS(Action_Log!$C$5:$C$504,B23,Action_Log!$J$5:$J$504,"Open")+COUNTIFS(Action_Log!$C$5:$C$504,B23,Action_Log!$J$5:$J$504,"In progress") -> 0 | J23: =COUNTIFS(Action_Log!$C$5:$C$504,B23,Action_Log!$J$5:$J$504,"Implemented") -> 1 | L23: Overdue milestones | M23: =COUNTIF(Milestones!$H$5:$H$504,"Overdue") -> 3
B24: =KPI_Tracking!B18 -> Team Productivity Index | C24: =KPI_Tracking!E18 -> 1 | D24: =IFERROR(INDEX(KPI_Tracking!$G18:$R18,MATCH($C$4,KPI_Tracking!$G$4:$R$4,0)),"") -> 0.95547917 | E24: =IFERROR(IF(MATCH($C$4,KPI_Tracking!$G$4:$R$4,0)=1,"",INDEX(KPI_Tracking!$G18:$R18,MATCH($C$4,KPI_Tracking!$G$4:$R$4,0)-1)),"") -> 0.97321528 | F24: =IF(OR(D24="",E24=""),"",D24-E24) -> -0.017736111 | G24: =IF(F24="","",IF(F24=0,"► Stable",IF((F24>0)=(KPI_Tracking!$D18="Higher"),"▲ Better","▼ Worse"))) -> ▼ Worse | H24: =IF(D24="","",IF(KPI_Tracking!$D18="Higher",IF(D24>=KPI_Tracking!$E18,"GREEN",IF(D24>=KPI_Tracking!$F18,"AMBER","RED")),IF(D24<=KPI_Tracking!$E18,"GREEN",IF(D24<=KPI_Tracking!$F18,"AMBER","RED")))) -> AMBER | I24: =COUNTIFS(Action_Log!$C$5:$C$504,B24,Action_Log!$J$5:$J$504,"Open")+COUNTIFS(Action_Log!$C$5:$C$504,B24,Action_Log!$J$5:$J$504,"In progress") -> 1 | J24: =COUNTIFS(Action_Log!$C$5:$C$504,B24,Action_Log!$J$5:$J$504,"Implemented") -> 0 | L24: Corrective actions open | M24: =COUNTIF(Action_Log!$N$5:$N$504,"On track")+COUNTIF(Action_Log!$N$5:$N$504,"OVERDUE") -> 3
B25: =KPI_Tracking!B19 -> Benefits Realization | C25: =KPI_Tracking!E19 -> 0.9 | D25: =IFERROR(INDEX(KPI_Tracking!$G19:$R19,MATCH($C$4,KPI_Tracking!$G$4:$R$4,0)),"") -> 0.92257418 | E25: =IFERROR(IF(MATCH($C$4,KPI_Tracking!$G$4:$R$4,0)=1,"",INDEX(KPI_Tracking!$G19:$R19,MATCH($C$4,KPI_Tracking!$G$4:$R$4,0)-1)),"") -> 0.86627371 | F25: =IF(OR(D25="",E25=""),"",D25-E25) -> 0.056300469 | G25: =IF(F25="","",IF(F25=0,"► Stable",IF((F25>0)=(KPI_Tracking!$D19="Higher"),"▲ Better","▼ Worse"))) -> ▲ Better | H25: =IF(D25="","",IF(KPI_Tracking!$D19="Higher",IF(D25>=KPI_Tracking!$E19,"GREEN",IF(D25>=KPI_Tracking!$F19,"AMBER","RED")),IF(D25<=KPI_Tracking!$E19,"GREEN",IF(D25<=KPI_Tracking!$F19,"AMBER","RED")))) -> GREEN | I25: =COUNTIFS(Action_Log!$C$5:$C$504,B25,Action_Log!$J$5:$J$504,"Open")+COUNTIFS(Action_Log!$C$5:$C$504,B25,Action_Log!$J$5:$J$504,"In progress") -> 0 | J25: =COUNTIFS(Action_Log!$C$5:$C$504,B25,Action_Log!$J$5:$J$504,"Implemented") -> 0 | L25: …of which OVERDUE | M25: =COUNTIF(Action_Log!$N$5:$N$504,"OVERDUE") -> 2
B26: =KPI_Tracking!B20 -> Continuous Improvement Initiatives | C26: =KPI_Tracking!E20 -> 2 | D26: =IFERROR(INDEX(KPI_Tracking!$G20:$R20,MATCH($C$4,KPI_Tracking!$G$4:$R$4,0)),"") -> 0 | E26: =IFERROR(IF(MATCH($C$4,KPI_Tracking!$G$4:$R$4,0)=1,"",INDEX(KPI_Tracking!$G20:$R20,MATCH($C$4,KPI_Tracking!$G$4:$R$4,0)-1)),"") -> 0 | F26: =IF(OR(D26="",E26=""),"",D26-E26) -> 0 | G26: =IF(F26="","",IF(F26=0,"► Stable",IF((F26>0)=(KPI_Tracking!$D20="Higher"),"▲ Better","▼ Worse"))) -> ► Stable | H26: =IF(D26="","",IF(KPI_Tracking!$D20="Higher",IF(D26>=KPI_Tracking!$E20,"GREEN",IF(D26>=KPI_Tracking!$F20,"AMBER","RED")),IF(D26<=KPI_Tracking!$E20,"GREEN",IF(D26<=KPI_Tracking!$F20,"AMBER","RED")))) -> RED | I26: =COUNTIFS(Action_Log!$C$5:$C$504,B26,Action_Log!$J$5:$J$504,"Open")+COUNTIFS(Action_Log!$C$5:$C$504,B26,Action_Log!$J$5:$J$504,"In progress") -> 0 | J26: =COUNTIFS(Action_Log!$C$5:$C$504,B26,Action_Log!$J$5:$J$504,"Implemented") -> 0 | L26: Actions that improved the KPI | M26: =IFERROR(COUNTIF(Action_Log!$M$5:$M$504,"Improved")/COUNTA(Action_Log!$L$5:$L$504),"") -> 1
L27: CI initiatives implemented (YTD) | M27: =COUNTIF(CI_Log!$F$5:$F$504,"Implemented") -> 11
L28: …with benefit verified | M28: =COUNTIFS(CI_Log!$F$5:$F$504,"Implemented",CI_Log!$I$5:$I$504,"Yes") -> 10
L29: Target revisions logged | M29: =COUNT(Target_Revisions!$B$5:$B$104) -> 2
B31: TRENDS – key KPIs (all 16 charts on the Trends sheet)

Sheet KPI_Tracking
A1: KPI Tracking – Monthly Actual vs Target
A2: Fully automatic: actuals are calculated from the logs. Months after the current reporting month (Settings) stay blank. Targets come from KPI_Targets.
A4: # | B4: KPI | C4: Unit | D4: Direction | E4: Target | F4: Amber limit | G4: =EDATE(Settings!$B$5,0) -> 46023 | H4: =EDATE(Settings!$B$5,1) -> 46054 | I4: =EDATE(Settings!$B$5,2) -> 46082 | J4: =EDATE(Settings!$B$5,3) -> 46113 | K4: =EDATE(Settings!$B$5,4) -> 46143 | L4: =EDATE(Settings!$B$5,5) -> 46174 | M4: =EDATE(Settings!$B$5,6) -> 46204 | N4: =EDATE(Settings!$B$5,7) -> 46235 | O4: =EDATE(Settings!$B$5,8) -> 46266 | P4: =EDATE(Settings!$B$5,9) -> 46296 | Q4: =EDATE(Settings!$B$5,10) -> 46327 | R4: =EDATE(Settings!$B$5,11) -> 46357 | S4: Latest actual | T4: Latest status | U4: Months GREEN | V4: Months RED
A5: 1 | B5: =KPI_Targets!B5 -> Project Schedule Variance (SV%) | C5: =KPI_Targets!E5 -> % | D5: =KPI_Targets!F5 -> Higher | E5: =KPI_Targets!G5 -> 0 | F5: =KPI_Targets!H5 -> -0.05 | G5: =IF(G$4>Settings!$B$6,"",IFERROR((SUMIFS(Cost_Schedule!$F$5:$F$504,Cost_Schedule!$A$5:$A$504,">="&G$4,Cost_Schedule!$A$5:$A$504,"<="&EOMONTH(G$4,0))-SUMIFS(Cost_Schedule!$E$5:$E$504,Cost_Schedule!$A$5:$A$504,">="&G$4,Cost_Schedule!$A$5:$A$504,"<="&EOMONTH(G$4,0)))/SUMIFS(Cost_Schedule!$E$5:$E$504,Cost_Schedule!$A$5:$A$504,">="&G$4,Cost_Schedule!$A$5:$A$504,"<="&EOMONTH(G$4,0)),"")) -> -0.053607374 | H5: =IF(H$4>Settings!$B$6,"",IFERROR((SUMIFS(Cost_Schedule!$F$5:$F$504,Cost_Schedule!$A$5:$A$504,">="&H$4,Cost_Schedule!$A$5:$A$504,"<="&EOMONTH(H$4,0))-SUMIFS(Cost_Schedule!$E$5:$E$504,Cost_Schedule!$A$5:$A$504,">="&H$4,Cost_Schedule!$A$5:$A$504,"<="&EOMONTH(H$4,0)))/SUMIFS(Cost_Schedule!$E$5:$E$504,Cost_Schedule!$A$5:$A$504,">="&H$4,Cost_Schedule!$A$5:$A$504,"<="&EOMONTH(H$4,0)),"")) -> -0.032187819 | I5: =IF(I$4>Settings!$B$6,"",IFERROR((SUMIFS(Cost_Schedule!$F$5:$F$504,Cost_Schedule!$A$5:$A$504,">="&I$4,Cost_Schedule!$A$5:$A$504,"<="&EOMONTH(I$4,0))-SUMIFS(Cost_Schedule!$E$5:$E$504,Cost_Schedule!$A$5:$A$504,">="&I$4,Cost_Schedule!$A$5:$A$504,"<="&EOMONTH(I$4,0)))/SUMIFS(Cost_Schedule!$E$5:$E$504,Cost_Schedule!$A$5:$A$504,">="&I$4,Cost_Schedule!$A$5:$A$504,"<="&EOMONTH(I$4,0)),"")) -> -0.046944949 | J5: =IF(J$4>Settings!$B$6,"",IFERROR((SUMIFS(Cost_Schedule!$F$5:$F$504,Cost_Schedule!$A$5:$A$504,">="&J$4,Cost_Schedule!$A$5:$A$504,"<="&EOMONTH(J$4,0))-SUMIFS(Cost_Schedule!$E$5:$E$504,Cost_Schedule!$A$5:$A$504,">="&J$4,Cost_Schedule!$A$5:$A$504,"<="&EOMONTH(J$4,0)))/SUMIFS(Cost_Schedule!$E$5:$E$504,Cost_Schedule!$A$5:$A$504,">="&J$4,Cost_Schedule!$A$5:$A$504,"<="&EOMONTH(J$4,0)),"")) -> -0.031599813 | K5: =IF(K$4>Settings!$B$6,"",IFERROR((SUMIFS(Cost_Schedule!$F$5:$F$504,Cost_Schedule!$A$5:$A$504,">="&K$4,Cost_Schedule!$A$5:$A$504,"<="&EOMONTH(K$4,0))-SUMIFS(Cost_Schedule!$E$5:$E$504,Cost_Schedule!$A$5:$A$504,">="&K$4,Cost_Schedule!$A$5:$A$504,"<="&EOMONTH(K$4,0)))/SUMIFS(Cost_Schedule!$E$5:$E$504,Cost_Schedule!$A$5:$A$504,">="&K$4,Cost_Schedule!$A$5:$A$504,"<="&EOMONTH(K$4,0)),"")) -> -0.040722517 | L5: =IF(L$4>Settings!$B$6,"",IFERROR((SUMIFS(Cost_Schedule!$F$5:$F$504,Cost_Schedule!$A$5:$A$504,">="&L$4,Cost_Schedule!$A$5:$A$504,"<="&EOMONTH(L$4,0))-SUMIFS(Cost_Schedule!$E$5:$E$504,Cost_Schedule!$A$5:$A$504,">="&L$4,Cost_Schedule!$A$5:$A$504,"<="&EOMONTH(L$4,0)))/SUMIFS(Cost_Schedule!$E$5:$E$504,Cost_Schedule!$A$5:$A$504,">="&L$4,Cost_Schedule!$A$5:$A$504,"<="&EOMONTH(L$4,0)),"")) -> -0.056735279 | M5: =IF(M$4>Settings!$B$6,"",IFERROR((SUMIFS(Cost_Schedule!$F$5:$F$504,Cost_Schedule!$A$5:$A$504,">="&M$4,Cost_Schedule!$A$5:$A$504,"<="&EOMONTH(M$4,0))-SUMIFS(Cost_Schedule!$E$5:$E$504,Cost_Schedule!$A$5:$A$504,">="&M$4,Cost_Schedule!$A$5:$A$504,"<="&EOMONTH(M$4,0)))/SUMIFS(Cost_Schedule!$E$5:$E$504,Cost_Schedule!$A$5:$A$504,">="&M$4,Cost_Schedule!$A$5:$A$504,"<="&EOMONTH(M$4,0)),"")) -> -0.053169038 | N5: =IF(N$4>Settings!$B$6,"",IFERROR((SUMIFS(Cost_Schedule!$F$5:$F$504,Cost_Schedule!$A$5:$A$504,">="&N$4,Cost_Schedule!$A$5:$A$504,"<="&EOMONTH(N$4,0))-SUMIFS(Cost_Schedule!$E$5:$E$504,Cost_Schedule!$A$5:$A$504,">="&N$4,Cost_Schedule!$A$5:$A$504,"<="&EOMONTH(N$4,0)))/SUMIFS(Cost_Schedule!$E$5:$E$504,Cost_Schedule!$A$5:$A$504,">="&N$4,Cost_Schedule!$A$5:$A$504,"<="&EOMONTH(N$4,0)),"")) -> -0.038984384 | ... R5: =IF(R$4>Settings!$B$6,"",IFERROR((SUMIFS(Cost_Schedule!$F$5:$F$504,Cost_Schedule!$A$5:$A$504,">="&R$4,Cost_Schedule!$A$5:$A$504,"<="&EOMONTH(R$4,0))-SUMIFS(Cost_Schedule!$E$5:$E$504,Cost_Schedule!$A$5:$A$504,">="&R$4,Cost_Schedule!$A$5:$A$504,"<="&EOMONTH(R$4,0)))/SUMIFS(Cost_Schedule!$E$5:$E$504,Cost_Schedule!$A$5:$A$504,">="&R$4,Cost_Schedule!$A$5:$A$504,"<="&EOMONTH(R$4,0)),"")) | S5: =IFERROR(LOOKUP(2,1/(G5:R5<>""),G5:R5),"") -> -0.067027027 | T5: =IF(S5="","",IF($D5="Higher",IF(S5>=$E5,"GREEN",IF(S5>=$F5,"AMBER","RED")),IF(S5<=$E5,"GREEN",IF(S5<=$F5,"AMBER","RED")))) -> RED | U5: =COUNTIF(G24:R24,"GREEN") -> 0 | V5: =COUNTIF(G24:R24,"RED") -> 4
A6: 2 | B6: =KPI_Targets!B6 -> Project Cost Variance (CV%) | C6: =KPI_Targets!E6 -> % | D6: =KPI_Targets!F6 -> Higher | E6: =KPI_Targets!G6 -> 0 | F6: =KPI_Targets!H6 -> -0.05 | G6: =IF(G$4>Settings!$B$6,"",IFERROR((SUMIFS(Cost_Schedule!$F$5:$F$504,Cost_Schedule!$A$5:$A$504,">="&G$4,Cost_Schedule!$A$5:$A$504,"<="&EOMONTH(G$4,0))-SUMIFS(Cost_Schedule!$G$5:$G$504,Cost_Schedule!$A$5:$A$504,">="&G$4,Cost_Schedule!$A$5:$A$504,"<="&EOMONTH(G$4,0)))/SUMIFS(Cost_Schedule!$F$5:$F$504,Cost_Schedule!$A$5:$A$504,">="&G$4,Cost_Schedule!$A$5:$A$504,"<="&EOMONTH(G$4,0)),"")) -> -0.024291951 | H6: =IF(H$4>Settings!$B$6,"",IFERROR((SUMIFS(Cost_Schedule!$F$5:$F$504,Cost_Schedule!$A$5:$A$504,">="&H$4,Cost_Schedule!$A$5:$A$504,"<="&EOMONTH(H$4,0))-SUMIFS(Cost_Schedule!$G$5:$G$504,Cost_Schedule!$A$5:$A$504,">="&H$4,Cost_Schedule!$A$5:$A$504,"<="&EOMONTH(H$4,0)))/SUMIFS(Cost_Schedule!$F$5:$F$504,Cost_Schedule!$A$5:$A$504,">="&H$4,Cost_Schedule!$A$5:$A$504,"<="&EOMONTH(H$4,0)),"")) -> -0.0088595134 | I6: =IF(I$4>Settings!$B$6,"",IFERROR((SUMIFS(Cost_Schedule!$F$5:$F$504,Cost_Schedule!$A$5:$A$504,">="&I$4,Cost_Schedule!$A$5:$A$504,"<="&EOMONTH(I$4,0))-SUMIFS(Cost_Schedule!$G$5:$G$504,Cost_Schedule!$A$5:$A$504,">="&I$4,Cost_Schedule!$A$5:$A$504,"<="&EOMONTH(I$4,0)))/SUMIFS(Cost_Schedule!$F$5:$F$504,Cost_Schedule!$A$5:$A$504,">="&I$4,Cost_Schedule!$A$5:$A$504,"<="&EOMONTH(I$4,0)),"")) -> -0.017963692 | J6: =IF(J$4>Settings!$B$6,"",IFERROR((SUMIFS(Cost_Schedule!$F$5:$F$504,Cost_Schedule!$A$5:$A$504,">="&J$4,Cost_Schedule!$A$5:$A$504,"<="&EOMONTH(J$4,0))-SUMIFS(Cost_Schedule!$G$5:$G$504,Cost_Schedule!$A$5:$A$504,">="&J$4,Cost_Schedule!$A$5:$A$504,"<="&EOMONTH(J$4,0)))/SUMIFS(Cost_Schedule!$F$5:$F$504,Cost_Schedule!$A$5:$A$504,">="&J$4,Cost_Schedule!$A$5:$A$504,"<="&EOMONTH(J$4,0)),"")) -> -0.02667068 | K6: =IF(K$4>Settings!$B$6,"",IFERROR((SUMIFS(Cost_Schedule!$F$5:$F$504,Cost_Schedule!$A$5:$A$504,">="&K$4,Cost_Schedule!$A$5:$A$504,"<="&EOMONTH(K$4,0))-SUMIFS(Cost_Schedule!$G$5:$G$504,Cost_Schedule!$A$5:$A$504,">="&K$4,Cost_Schedule!$A$5:$A$504,"<="&EOMONTH(K$4,0)))/SUMIFS(Cost_Schedule!$F$5:$F$504,Cost_Schedule!$A$5:$A$504,">="&K$4,Cost_Schedule!$A$5:$A$504,"<="&EOMONTH(K$4,0)),"")) -> -0.040696497 | L6: =IF(L$4>Settings!$B$6,"",IFERROR((SUMIFS(Cost_Schedule!$F$5:$F$504,Cost_Schedule!$A$5:$A$504,">="&L$4,Cost_Schedule!$A$5:$A$504,"<="&EOMONTH(L$4,0))-SUMIFS(Cost_Schedule!$G$5:$G$504,Cost_Schedule!$A$5:$A$504,">="&L$4,Cost_Schedule!$A$5:$A$504,"<="&EOMONTH(L$4,0)))/SUMIFS(Cost_Schedule!$F$5:$F$504,Cost_Schedule!$A$5:$A$504,">="&L$4,Cost_Schedule!$A$5:$A$504,"<="&EOMONTH(L$4,0)),"")) -> -0.034804226 | M6: =IF(M$4>Settings!$B$6,"",IFERROR((SUMIFS(Cost_Schedule!$F$5:$F$504,Cost_Schedule!$A$5:$A$504,">="&M$4,Cost_Schedule!$A$5:$A$504,"<="&EOMONTH(M$4,0))-SUMIFS(Cost_Schedule!$G$5:$G$504,Cost_Schedule!$A$5:$A$504,">="&M$4,Cost_Schedule!$A$5:$A$504,"<="&EOMONTH(M$4,0)))/SUMIFS(Cost_Schedule!$F$5:$F$504,Cost_Schedule!$A$5:$A$504,">="&M$4,Cost_Schedule!$A$5:$A$504,"<="&EOMONTH(M$4,0)),"")) -> -0.044434858 | N6: =IF(N$4>Settings!$B$6,"",IFERROR((SUMIFS(Cost_Schedule!$F$5:$F$504,Cost_Schedule!$A$5:$A$504,">="&N$4,Cost_Schedule!$A$5:$A$504,"<="&EOMONTH(N$4,0))-SUMIFS(Cost_Schedule!$G$5:$G$504,Cost_Schedule!$A$5:$A$504,">="&N$4,Cost_Schedule!$A$5:$A$504,"<="&EOMONTH(N$4,0)))/SUMIFS(Cost_Schedule!$F$5:$F$504,Cost_Schedule!$A$5:$A$504,">="&N$4,Cost_Schedule!$A$5:$A$504,"<="&EOMONTH(N$4,0)),"")) -> -0.0060790274 | ... R6: =IF(R$4>Settings!$B$6,"",IFERROR((SUMIFS(Cost_Schedule!$F$5:$F$504,Cost_Schedule!$A$5:$A$504,">="&R$4,Cost_Schedule!$A$5:$A$504,"<="&EOMONTH(R$4,0))-SUMIFS(Cost_Schedule!$G$5:$G$504,Cost_Schedule!$A$5:$A$504,">="&R$4,Cost_Schedule!$A$5:$A$504,"<="&EOMONTH(R$4,0)))/SUMIFS(Cost_Schedule!$F$5:$F$504,Cost_Schedule!$A$5:$A$504,">="&R$4,Cost_Schedule!$A$5:$A$504,"<="&EOMONTH(R$4,0)),"")) | S6: =IFERROR(LOOKUP(2,1/(G6:R6<>""),G6:R6),"") -> -0.037369641 | T6: =IF(S6="","",IF($D6="Higher",IF(S6>=$E6,"GREEN",IF(S6>=$F6,"AMBER","RED")),IF(S6<=$E6,"GREEN",IF(S6<=$F6,"AMBER","RED")))) -> AMBER | U6: =COUNTIF(G25:R25,"GREEN") -> 0 | V6: =COUNTIF(G25:R25,"RED") -> 0
A7: 3 | B7: =KPI_Targets!B7 -> Budget Utilization | C7: =KPI_Targets!E7 -> % | D7: =KPI_Targets!F7 -> Lower | E7: =KPI_Targets!G7 -> 1 | F7: =KPI_Targets!H7 -> 1.05 | G7: =IF(G$4>Settings!$B$6,"",IFERROR(SUMIFS(Cost_Schedule!$G$5:$G$504,Cost_Schedule!$A$5:$A$504,">="&G$4,Cost_Schedule!$A$5:$A$504,"<="&EOMONTH(G$4,0))/SUMIFS(Cost_Schedule!$D$5:$D$504,Cost_Schedule!$A$5:$A$504,">="&G$4,Cost_Schedule!$A$5:$A$504,"<="&EOMONTH(G$4,0)),"")) -> 0.93177189 | H7: =IF(H$4>Settings!$B$6,"",IFERROR(SUMIFS(Cost_Schedule!$G$5:$G$504,Cost_Schedule!$A$5:$A$504,">="&H$4,Cost_Schedule!$A$5:$A$504,"<="&EOMONTH(H$4,0))/SUMIFS(Cost_Schedule!$D$5:$D$504,Cost_Schedule!$A$5:$A$504,">="&H$4,Cost_Schedule!$A$5:$A$504,"<="&EOMONTH(H$4,0)),"")) -> 0.94394737 | I7: =IF(I$4>Settings!$B$6,"",IFERROR(SUMIFS(Cost_Schedule!$G$5:$G$504,Cost_Schedule!$A$5:$A$504,">="&I$4,Cost_Schedule!$A$5:$A$504,"<="&EOMONTH(I$4,0))/SUMIFS(Cost_Schedule!$D$5:$D$504,Cost_Schedule!$A$5:$A$504,">="&I$4,Cost_Schedule!$A$5:$A$504,"<="&EOMONTH(I$4,0)),"")) -> 0.94446408 | J7: =IF(J$4>Settings!$B$6,"",IFERROR(SUMIFS(Cost_Schedule!$G$5:$G$504,Cost_Schedule!$A$5:$A$504,">="&J$4,Cost_Schedule!$A$5:$A$504,"<="&EOMONTH(J$4,0))/SUMIFS(Cost_Schedule!$D$5:$D$504,Cost_Schedule!$A$5:$A$504,">="&J$4,Cost_Schedule!$A$5:$A$504,"<="&EOMONTH(J$4,0)),"")) -> 0.97724928 | K7: =IF(K$4>Settings!$B$6,"",IFERROR(SUMIFS(Cost_Schedule!$G$5:$G$504,Cost_Schedule!$A$5:$A$504,">="&K$4,Cost_Schedule!$A$5:$A$504,"<="&EOMONTH(K$4,0))/SUMIFS(Cost_Schedule!$D$5:$D$504,Cost_Schedule!$A$5:$A$504,">="&K$4,Cost_Schedule!$A$5:$A$504,"<="&EOMONTH(K$4,0)),"")) -> 0.97409981 | L7: =IF(L$4>Settings!$B$6,"",IFERROR(SUMIFS(Cost_Schedule!$G$5:$G$504,Cost_Schedule!$A$5:$A$504,">="&L$4,Cost_Schedule!$A$5:$A$504,"<="&EOMONTH(L$4,0))/SUMIFS(Cost_Schedule!$D$5:$D$504,Cost_Schedule!$A$5:$A$504,">="&L$4,Cost_Schedule!$A$5:$A$504,"<="&EOMONTH(L$4,0)),"")) -> 0.94662034 | M7: =IF(M$4>Settings!$B$6,"",IFERROR(SUMIFS(Cost_Schedule!$G$5:$G$504,Cost_Schedule!$A$5:$A$504,">="&M$4,Cost_Schedule!$A$5:$A$504,"<="&EOMONTH(M$4,0))/SUMIFS(Cost_Schedule!$D$5:$D$504,Cost_Schedule!$A$5:$A$504,">="&M$4,Cost_Schedule!$A$5:$A$504,"<="&EOMONTH(M$4,0)),"")) -> 0.96007931 | N7: =IF(N$4>Settings!$B$6,"",IFERROR(SUMIFS(Cost_Schedule!$G$5:$G$504,Cost_Schedule!$A$5:$A$504,">="&N$4,Cost_Schedule!$A$5:$A$504,"<="&EOMONTH(N$4,0))/SUMIFS(Cost_Schedule!$D$5:$D$504,Cost_Schedule!$A$5:$A$504,">="&N$4,Cost_Schedule!$A$5:$A$504,"<="&EOMONTH(N$4,0)),"")) -> 0.94260679 | ... R7: =IF(R$4>Settings!$B$6,"",IFERROR(SUMIFS(Cost_Schedule!$G$5:$G$504,Cost_Schedule!$A$5:$A$504,">="&R$4,Cost_Schedule!$A$5:$A$504,"<="&EOMONTH(R$4,0))/SUMIFS(Cost_Schedule!$D$5:$D$504,Cost_Schedule!$A$5:$A$504,">="&R$4,Cost_Schedule!$A$5:$A$504,"<="&EOMONTH(R$4,0)),"")) | S7: =IFERROR(LOOKUP(2,1/(G7:R7<>""),G7:R7),"") -> 0.95493333 | T7: =IF(S7="","",IF($D7="Higher",IF(S7>=$E7,"GREEN",IF(S7>=$F7,"AMBER","RED")),IF(S7<=$E7,"GREEN",IF(S7<=$F7,"AMBER","RED")))) -> GREEN | U7: =COUNTIF(G26:R26,"GREEN") -> 10 | V7: =COUNTIF(G26:R26,"RED") -> 0
A8: 4 | B8: =KPI_Targets!B8 -> On-Time Project Delivery | C8: =KPI_Targets!E8 -> % | D8: =KPI_Targets!F8 -> Higher | E8: =KPI_Targets!G8 -> 0.9 | F8: =KPI_Targets!H8 -> 0.8 | G8: =IF(G$4>Settings!$B$6,"",IFERROR(COUNTIFS(Projects!$I$5:$I$104,"Completed",Projects!$H$5:$H$104,">="&Settings!$B$5,Projects!$H$5:$H$104,"<="&EOMONTH(G$4,0),Projects!$N$5:$N$104,"Yes")/COUNTIFS(Projects!$I$5:$I$104,"Completed",Projects!$H$5:$H$104,">="&Settings!$B$5,Projects!$H$5:$H$104,"<="&EOMONTH(G$4,0)),"")) | H8: =IF(H$4>Settings!$B$6,"",IFERROR(COUNTIFS(Projects!$I$5:$I$104,"Completed",Projects!$H$5:$H$104,">="&Settings!$B$5,Projects!$H$5:$H$104,"<="&EOMONTH(H$4,0),Projects!$N$5:$N$104,"Yes")/COUNTIFS(Projects!$I$5:$I$104,"Completed",Projects!$H$5:$H$104,">="&Settings!$B$5,Projects!$H$5:$H$104,"<="&EOMONTH(H$4,0)),"")) | I8: =IF(I$4>Settings!$B$6,"",IFERROR(COUNTIFS(Projects!$I$5:$I$104,"Completed",Projects!$H$5:$H$104,">="&Settings!$B$5,Projects!$H$5:$H$104,"<="&EOMONTH(I$4,0),Projects!$N$5:$N$104,"Yes")/COUNTIFS(Projects!$I$5:$I$104,"Completed",Projects!$H$5:$H$104,">="&Settings!$B$5,Projects!$H$5:$H$104,"<="&EOMONTH(I$4,0)),"")) | J8: =IF(J$4>Settings!$B$6,"",IFERROR(COUNTIFS(Projects!$I$5:$I$104,"Completed",Projects!$H$5:$H$104,">="&Settings!$B$5,Projects!$H$5:$H$104,"<="&EOMONTH(J$4,0),Projects!$N$5:$N$104,"Yes")/COUNTIFS(Projects!$I$5:$I$104,"Completed",Projects!$H$5:$H$104,">="&Settings!$B$5,Projects!$H$5:$H$104,"<="&EOMONTH(J$4,0)),"")) -> 1 | K8: =IF(K$4>Settings!$B$6,"",IFERROR(COUNTIFS(Projects!$I$5:$I$104,"Completed",Projects!$H$5:$H$104,">="&Settings!$B$5,Projects!$H$5:$H$104,"<="&EOMONTH(K$4,0),Projects!$N$5:$N$104,"Yes")/COUNTIFS(Projects!$I$5:$I$104,"Completed",Projects!$H$5:$H$104,">="&Settings!$B$5,Projects!$H$5:$H$104,"<="&EOMONTH(K$4,0)),"")) -> 1 | L8: =IF(L$4>Settings!$B$6,"",IFERROR(COUNTIFS(Projects!$I$5:$I$104,"Completed",Projects!$H$5:$H$104,">="&Settings!$B$5,Projects!$H$5:$H$104,"<="&EOMONTH(L$4,0),Projects!$N$5:$N$104,"Yes")/COUNTIFS(Projects!$I$5:$I$104,"Completed",Projects!$H$5:$H$104,">="&Settings!$B$5,Projects!$H$5:$H$104,"<="&EOMONTH(L$4,0)),"")) -> 0.5 | M8: =IF(M$4>Settings!$B$6,"",IFERROR(COUNTIFS(Projects!$I$5:$I$104,"Completed",Projects!$H$5:$H$104,">="&Settings!$B$5,Projects!$H$5:$H$104,"<="&EOMONTH(M$4,0),Projects!$N$5:$N$104,"Yes")/COUNTIFS(Projects!$I$5:$I$104,"Completed",Projects!$H$5:$H$104,">="&Settings!$B$5,Projects!$H$5:$H$104,"<="&EOMONTH(M$4,0)),"")) -> 0.33333333 | N8: =IF(N$4>Settings!$B$6,"",IFERROR(COUNTIFS(Projects!$I$5:$I$104,"Completed",Projects!$H$5:$H$104,">="&Settings!$B$5,Projects!$H$5:$H$104,"<="&EOMONTH(N$4,0),Projects!$N$5:$N$104,"Yes")/COUNTIFS(Projects!$I$5:$I$104,"Completed",Projects!$H$5:$H$104,">="&Settings!$B$5,Projects!$H$5:$H$104,"<="&EOMONTH(N$4,0)),"")) -> 0.5 | ... R8: =IF(R$4>Settings!$B$6,"",IFERROR(COUNTIFS(Projects!$I$5:$I$104,"Completed",Projects!$H$5:$H$104,">="&Settings!$B$5,Projects!$H$5:$H$104,"<="&EOMONTH(R$4,0),Projects!$N$5:$N$104,"Yes")/COUNTIFS(Projects!$I$5:$I$104,"Completed",Projects!$H$5:$H$104,">="&Settings!$B$5,Projects!$H$5:$H$104,"<="&EOMONTH(R$4,0)),"")) | S8: =IFERROR(LOOKUP(2,1/(G8:R8<>""),G8:R8),"") -> 0.6 | T8: =IF(S8="","",IF($D8="Higher",IF(S8>=$E8,"GREEN",IF(S8>=$F8,"AMBER","RED")),IF(S8<=$E8,"GREEN",IF(S8<=$F8,"AMBER","RED")))) -> RED | U8: =COUNTIF(G27:R27,"GREEN") -> 2 | V8: =COUNTIF(G27:R27,"RED") -> 5
A9: 5 | B9: =KPI_Targets!B9 -> Scope Change Frequency | C9: =KPI_Targets!E9 -> CRs / project | D9: =KPI_Targets!F9 -> Lower | E9: =KPI_Targets!G9 -> 0.5 | F9: =KPI_Targets!H9 -> 1 | G9: =IF(G$4>Settings!$B$6,"",IFERROR(COUNTIFS(Change_Log!$E$5:$E$504,"Scope",Change_Log!$C$5:$C$504,">="&G$4,Change_Log!$C$5:$C$504,"<="&EOMONTH(G$4,0))/COUNTIFS(Projects!$F$5:$F$104,"<="&EOMONTH(G$4,0),Projects!$H$5:$H$104,">="&G$4),"")) -> 1 | H9: =IF(H$4>Settings!$B$6,"",IFERROR(COUNTIFS(Change_Log!$E$5:$E$504,"Scope",Change_Log!$C$5:$C$504,">="&H$4,Change_Log!$C$5:$C$504,"<="&EOMONTH(H$4,0))/COUNTIFS(Projects!$F$5:$F$104,"<="&EOMONTH(H$4,0),Projects!$H$5:$H$104,">="&H$4),"")) -> 0.4 | I9: =IF(I$4>Settings!$B$6,"",IFERROR(COUNTIFS(Change_Log!$E$5:$E$504,"Scope",Change_Log!$C$5:$C$504,">="&I$4,Change_Log!$C$5:$C$504,"<="&EOMONTH(I$4,0))/COUNTIFS(Projects!$F$5:$F$104,"<="&EOMONTH(I$4,0),Projects!$H$5:$H$104,">="&I$4),"")) -> 0 | J9: =IF(J$4>Settings!$B$6,"",IFERROR(COUNTIFS(Change_Log!$E$5:$E$504,"Scope",Change_Log!$C$5:$C$504,">="&J$4,Change_Log!$C$5:$C$504,"<="&EOMONTH(J$4,0))/COUNTIFS(Projects!$F$5:$F$104,"<="&EOMONTH(J$4,0),Projects!$H$5:$H$104,">="&J$4),"")) -> 0.28571429 | K9: =IF(K$4>Settings!$B$6,"",IFERROR(COUNTIFS(Change_Log!$E$5:$E$504,"Scope",Change_Log!$C$5:$C$504,">="&K$4,Change_Log!$C$5:$C$504,"<="&EOMONTH(K$4,0))/COUNTIFS(Projects!$F$5:$F$104,"<="&EOMONTH(K$4,0),Projects!$H$5:$H$104,">="&K$4),"")) -> 0.42857143 | L9: =IF(L$4>Settings!$B$6,"",IFERROR(COUNTIFS(Change_Log!$E$5:$E$504,"Scope",Change_Log!$C$5:$C$504,">="&L$4,Change_Log!$C$5:$C$504,"<="&EOMONTH(L$4,0))/COUNTIFS(Projects!$F$5:$F$104,"<="&EOMONTH(L$4,0),Projects!$H$5:$H$104,">="&L$4),"")) -> 0.14285714 | M9: =IF(M$4>Settings!$B$6,"",IFERROR(COUNTIFS(Change_Log!$E$5:$E$504,"Scope",Change_Log!$C$5:$C$504,">="&M$4,Change_Log!$C$5:$C$504,"<="&EOMONTH(M$4,0))/COUNTIFS(Projects!$F$5:$F$104,"<="&EOMONTH(M$4,0),Projects!$H$5:$H$104,">="&M$4),"")) -> 0.16666667 | N9: =IF(N$4>Settings!$B$6,"",IFERROR(COUNTIFS(Change_Log!$E$5:$E$504,"Scope",Change_Log!$C$5:$C$504,">="&N$4,Change_Log!$C$5:$C$504,"<="&EOMONTH(N$4,0))/COUNTIFS(Projects!$F$5:$F$104,"<="&EOMONTH(N$4,0),Projects!$H$5:$H$104,">="&N$4),"")) -> 0 | ... R9: =IF(R$4>Settings!$B$6,"",IFERROR(COUNTIFS(Change_Log!$E$5:$E$504,"Scope",Change_Log!$C$5:$C$504,">="&R$4,Change_Log!$C$5:$C$504,"<="&EOMONTH(R$4,0))/COUNTIFS(Projects!$F$5:$F$104,"<="&EOMONTH(R$4,0),Projects!$H$5:$H$104,">="&R$4),"")) | S9: =IFERROR(LOOKUP(2,1/(G9:R9<>""),G9:R9),"") -> 0 | T9: =IF(S9="","",IF($D9="Higher",IF(S9>=$E9,"GREEN",IF(S9>=$F9,"AMBER","RED")),IF(S9<=$E9,"GREEN",IF(S9<=$F9,"AMBER","RED")))) -> GREEN | U9: =COUNTIF(G28:R28,"GREEN") -> 9 | V9: =COUNTIF(G28:R28,"RED") -> 0
A10: 6 | B10: =KPI_Targets!B10 -> Risk Mitigation Effectiveness | C10: =KPI_Targets!E10 -> % | D10: =KPI_Targets!F10 -> Higher | E10: =KPI_Targets!G10 -> 0.85 | F10: =KPI_Targets!H10 -> 0.7 | G10: =IF(G$4>Settings!$B$6,"",IFERROR(COUNTIFS(Risk_Log!$M$5:$M$504,">="&Settings!$B$5,Risk_Log!$M$5:$M$504,"<="&EOMONTH(G$4,0),Risk_Log!$N$5:$N$504,"No")/COUNTIFS(Risk_Log!$M$5:$M$504,">="&Settings!$B$5,Risk_Log!$M$5:$M$504,"<="&EOMONTH(G$4,0)),"")) | H10: =IF(H$4>Settings!$B$6,"",IFERROR(COUNTIFS(Risk_Log!$M$5:$M$504,">="&Settings!$B$5,Risk_Log!$M$5:$M$504,"<="&EOMONTH(H$4,0),Risk_Log!$N$5:$N$504,"No")/COUNTIFS(Risk_Log!$M$5:$M$504,">="&Settings!$B$5,Risk_Log!$M$5:$M$504,"<="&EOMONTH(H$4,0)),"")) | I10: =IF(I$4>Settings!$B$6,"",IFERROR(COUNTIFS(Risk_Log!$M$5:$M$504,">="&Settings!$B$5,Risk_Log!$M$5:$M$504,"<="&EOMONTH(I$4,0),Risk_Log!$N$5:$N$504,"No")/COUNTIFS(Risk_Log!$M$5:$M$504,">="&Settings!$B$5,Risk_Log!$M$5:$M$504,"<="&EOMONTH(I$4,0)),"")) -> 1 | J10: =IF(J$4>Settings!$B$6,"",IFERROR(COUNTIFS(Risk_Log!$M$5:$M$504,">="&Settings!$B$5,Risk_Log!$M$5:$M$504,"<="&EOMONTH(J$4,0),Risk_Log!$N$5:$N$504,"No")/COUNTIFS(Risk_Log!$M$5:$M$504,">="&Settings!$B$5,Risk_Log!$M$5:$M$504,"<="&EOMONTH(J$4,0)),"")) -> 1 | K10: =IF(K$4>Settings!$B$6,"",IFERROR(COUNTIFS(Risk_Log!$M$5:$M$504,">="&Settings!$B$5,Risk_Log!$M$5:$M$504,"<="&EOMONTH(K$4,0),Risk_Log!$N$5:$N$504,"No")/COUNTIFS(Risk_Log!$M$5:$M$504,">="&Settings!$B$5,Risk_Log!$M$5:$M$504,"<="&EOMONTH(K$4,0)),"")) -> 1 | L10: =IF(L$4>Settings!$B$6,"",IFERROR(COUNTIFS(Risk_Log!$M$5:$M$504,">="&Settings!$B$5,Risk_Log!$M$5:$M$504,"<="&EOMONTH(L$4,0),Risk_Log!$N$5:$N$504,"No")/COUNTIFS(Risk_Log!$M$5:$M$504,">="&Settings!$B$5,Risk_Log!$M$5:$M$504,"<="&EOMONTH(L$4,0)),"")) -> 0.77777778 | M10: =IF(M$4>Settings!$B$6,"",IFERROR(COUNTIFS(Risk_Log!$M$5:$M$504,">="&Settings!$B$5,Risk_Log!$M$5:$M$504,"<="&EOMONTH(M$4,0),Risk_Log!$N$5:$N$504,"No")/COUNTIFS(Risk_Log!$M$5:$M$504,">="&Settings!$B$5,Risk_Log!$M$5:$M$504,"<="&EOMONTH(M$4,0)),"")) -> 0.8 | N10: =IF(N$4>Settings!$B$6,"",IFERROR(COUNTIFS(Risk_Log!$M$5:$M$504,">="&Settings!$B$5,Risk_Log!$M$5:$M$504,"<="&EOMONTH(N$4,0),Risk_Log!$N$5:$N$504,"No")/COUNTIFS(Risk_Log!$M$5:$M$504,">="&Settings!$B$5,Risk_Log!$M$5:$M$504,"<="&EOMONTH(N$4,0)),"")) -> 0.8 | ... R10: =IF(R$4>Settings!$B$6,"",IFERROR(COUNTIFS(Risk_Log!$M$5:$M$504,">="&Settings!$B$5,Risk_Log!$M$5:$M$504,"<="&EOMONTH(R$4,0),Risk_Log!$N$5:$N$504,"No")/COUNTIFS(Risk_Log!$M$5:$M$504,">="&Settings!$B$5,Risk_Log!$M$5:$M$504,"<="&EOMONTH(R$4,0)),"")) | S10: =IFERROR(LOOKUP(2,1/(G10:R10<>""),G10:R10),"") -> 0.8125 | T10: =IF(S10="","",IF($D10="Higher",IF(S10>=$E10,"GREEN",IF(S10>=$F10,"AMBER","RED")),IF(S10<=$E10,"GREEN",IF(S10<=$F10,"AMBER","RED")))) -> AMBER | U10: =COUNTIF(G29:R29,"GREEN") -> 3 | V10: =COUNTIF(G29:R29,"RED") -> 0
A11: 7 | B11: =KPI_Targets!B11 -> Issue Resolution Time | C11: =KPI_Targets!E11 -> days | D11: =KPI_Targets!F11 -> Lower | E11: =KPI_Targets!G11 -> 7 | F11: =KPI_Targets!H11 -> 14 | G11: =IF(G$4>Settings!$B$6,"",IFERROR(AVERAGEIFS(Issue_Log!$I$5:$I$504,Issue_Log!$H$5:$H$504,">="&G$4,Issue_Log!$H$5:$H$504,"<="&EOMONTH(G$4,0)),"")) -> 9.25 | H11: =IF(H$4>Settings!$B$6,"",IFERROR(AVERAGEIFS(Issue_Log!$I$5:$I$504,Issue_Log!$H$5:$H$504,">="&H$4,Issue_Log!$H$5:$H$504,"<="&EOMONTH(H$4,0)),"")) -> 15 | I11: =IF(I$4>Settings!$B$6,"",IFERROR(AVERAGEIFS(Issue_Log!$I$5:$I$504,Issue_Log!$H$5:$H$504,">="&I$4,Issue_Log!$H$5:$H$504,"<="&EOMONTH(I$4,0)),"")) -> 9.5714286 | J11: =IF(J$4>Settings!$B$6,"",IFERROR(AVERAGEIFS(Issue_Log!$I$5:$I$504,Issue_Log!$H$5:$H$504,">="&J$4,Issue_Log!$H$5:$H$504,"<="&EOMONTH(J$4,0)),"")) -> 4.3333333 | K11: =IF(K$4>Settings!$B$6,"",IFERROR(AVERAGEIFS(Issue_Log!$I$5:$I$504,Issue_Log!$H$5:$H$504,">="&K$4,Issue_Log!$H$5:$H$504,"<="&EOMONTH(K$4,0)),"")) -> 8 | L11: =IF(L$4>Settings!$B$6,"",IFERROR(AVERAGEIFS(Issue_Log!$I$5:$I$504,Issue_Log!$H$5:$H$504,">="&L$4,Issue_Log!$H$5:$H$504,"<="&EOMONTH(L$4,0)),"")) -> 4.4285714 | M11: =IF(M$4>Settings!$B$6,"",IFERROR(AVERAGEIFS(Issue_Log!$I$5:$I$504,Issue_Log!$H$5:$H$504,">="&M$4,Issue_Log!$H$5:$H$504,"<="&EOMONTH(M$4,0)),"")) -> 10.428571 | N11: =IF(N$4>Settings!$B$6,"",IFERROR(AVERAGEIFS(Issue_Log!$I$5:$I$504,Issue_Log!$H$5:$H$504,">="&N$4,Issue_Log!$H$5:$H$504,"<="&EOMONTH(N$4,0)),"")) -> 7.4 | ... R11: =IF(R$4>Settings!$B$6,"",IFERROR(AVERAGEIFS(Issue_Log!$I$5:$I$504,Issue_Log!$H$5:$H$504,">="&R$4,Issue_Log!$H$5:$H$504,"<="&EOMONTH(R$4,0)),"")) | S11: =IFERROR(LOOKUP(2,1/(G11:R11<>""),G11:R11),"") -> 5 | T11: =IF(S11="","",IF($D11="Higher",IF(S11>=$E11,"GREEN",IF(S11>=$F11,"AMBER","RED")),IF(S11<=$E11,"GREEN",IF(S11<=$F11,"AMBER","RED")))) -> GREEN | U11: =COUNTIF(G30:R30,"GREEN") -> 3 | V11: =COUNTIF(G30:R30,"RED") -> 1
A12: 8 | B12: =KPI_Targets!B12 -> Stakeholder Satisfaction | C12: =KPI_Targets!E12 -> score /5 | D12: =KPI_Targets!F12 -> Higher | E12: =KPI_Targets!G12 -> 4 | F12: =KPI_Targets!H12 -> 3.5 | G12: =IF(G$4>Settings!$B$6,"",IFERROR(AVERAGEIFS(Stakeholder_Survey!$I$5:$I$504,Stakeholder_Survey!$A$5:$A$504,">="&G$4,Stakeholder_Survey!$A$5:$A$504,"<="&EOMONTH(G$4,0)),"")) -> 3.3125 | H12: =IF(H$4>Settings!$B$6,"",IFERROR(AVERAGEIFS(Stakeholder_Survey!$I$5:$I$504,Stakeholder_Survey!$A$5:$A$504,">="&H$4,Stakeholder_Survey!$A$5:$A$504,"<="&EOMONTH(H$4,0)),"")) -> 3.3125 | I12: =IF(I$4>Settings!$B$6,"",IFERROR(AVERAGEIFS(Stakeholder_Survey!$I$5:$I$504,Stakeholder_Survey!$A$5:$A$504,">="&I$4,Stakeholder_Survey!$A$5:$A$504,"<="&EOMONTH(I$4,0)),"")) -> 3.625 | J12: =IF(J$4>Settings!$B$6,"",IFERROR(AVERAGEIFS(Stakeholder_Survey!$I$5:$I$504,Stakeholder_Survey!$A$5:$A$504,">="&J$4,Stakeholder_Survey!$A$5:$A$504,"<="&EOMONTH(J$4,0)),"")) -> 3.5 | K12: =IF(K$4>Settings!$B$6,"",IFERROR(AVERAGEIFS(Stakeholder_Survey!$I$5:$I$504,Stakeholder_Survey!$A$5:$A$504,">="&K$4,Stakeholder_Survey!$A$5:$A$504,"<="&EOMONTH(K$4,0)),"")) -> 3.875 | L12: =IF(L$4>Settings!$B$6,"",IFERROR(AVERAGEIFS(Stakeholder_Survey!$I$5:$I$504,Stakeholder_Survey!$A$5:$A$504,">="&L$4,Stakeholder_Survey!$A$5:$A$504,"<="&EOMONTH(L$4,0)),"")) -> 3.6875 | M12: =IF(M$4>Settings!$B$6,"",IFERROR(AVERAGEIFS(Stakeholder_Survey!$I$5:$I$504,Stakeholder_Survey!$A$5:$A$504,">="&M$4,Stakeholder_Survey!$A$5:$A$504,"<="&EOMONTH(M$4,0)),"")) -> 3.9166667 | N12: =IF(N$4>Settings!$B$6,"",IFERROR(AVERAGEIFS(Stakeholder_Survey!$I$5:$I$504,Stakeholder_Survey!$A$5:$A$504,">="&N$4,Stakeholder_Survey!$A$5:$A$504,"<="&EOMONTH(N$4,0)),"")) -> 4.1666667 | ... R12: =IF(R$4>Settings!$B$6,"",IFERROR(AVERAGEIFS(Stakeholder_Survey!$I$5:$I$504,Stakeholder_Survey!$A$5:$A$504,">="&R$4,Stakeholder_Survey!$A$5:$A$504,"<="&EOMONTH(R$4,0)),"")) | S12: =IFERROR(LOOKUP(2,1/(G12:R12<>""),G12:R12),"") -> 3.9166667 | T12: =IF(S12="","",IF($D12="Higher",IF(S12>=$E12,"GREEN",IF(S12>=$F12,"AMBER","RED")),IF(S12<=$E12,"GREEN",IF(S12<=$F12,"AMBER","RED")))) -> AMBER | U12: =COUNTIF(G31:R31,"GREEN") -> 2 | V12: =COUNTIF(G31:R31,"RED") -> 2
A13: 9 | B13: =KPI_Targets!B13 -> Resource Utilization Rate | C13: =KPI_Targets!E13 -> % | D13: =KPI_Targets!F13 -> Higher | E13: =KPI_Targets!G13 -> 0.85 | F13: =KPI_Targets!H13 -> 0.75 | G13: =IF(G$4>Settings!$B$6,"",IFERROR(SUMIFS(Resources!$E$5:$E$504,Resources!$A$5:$A$504,">="&G$4,Resources!$A$5:$A$504,"<="&EOMONTH(G$4,0))/SUMIFS(Resources!$D$5:$D$504,Resources!$A$5:$A$504,">="&G$4,Resources!$A$5:$A$504,"<="&EOMONTH(G$4,0)),"")) -> 0.84760638 | H13: =IF(H$4>Settings!$B$6,"",IFERROR(SUMIFS(Resources!$E$5:$E$504,Resources!$A$5:$A$504,">="&H$4,Resources!$A$5:$A$504,"<="&EOMONTH(H$4,0))/SUMIFS(Resources!$D$5:$D$504,Resources!$A$5:$A$504,">="&H$4,Resources!$A$5:$A$504,"<="&EOMONTH(H$4,0)),"")) -> 0.84244505 | I13: =IF(I$4>Settings!$B$6,"",IFERROR(SUMIFS(Resources!$E$5:$E$504,Resources!$A$5:$A$504,">="&I$4,Resources!$A$5:$A$504,"<="&EOMONTH(I$4,0))/SUMIFS(Resources!$D$5:$D$504,Resources!$A$5:$A$504,">="&I$4,Resources!$A$5:$A$504,"<="&EOMONTH(I$4,0)),"")) -> 0.82739362 | J13: =IF(J$4>Settings!$B$6,"",IFERROR(SUMIFS(Resources!$E$5:$E$504,Resources!$A$5:$A$504,">="&J$4,Resources!$A$5:$A$504,"<="&EOMONTH(J$4,0))/SUMIFS(Resources!$D$5:$D$504,Resources!$A$5:$A$504,">="&J$4,Resources!$A$5:$A$504,"<="&EOMONTH(J$4,0)),"")) -> 0.81758242 | K13: =IF(K$4>Settings!$B$6,"",IFERROR(SUMIFS(Resources!$E$5:$E$504,Resources!$A$5:$A$504,">="&K$4,Resources!$A$5:$A$504,"<="&EOMONTH(K$4,0))/SUMIFS(Resources!$D$5:$D$504,Resources!$A$5:$A$504,">="&K$4,Resources!$A$5:$A$504,"<="&EOMONTH(K$4,0)),"")) -> 0.82181122 | L13: =IF(L$4>Settings!$B$6,"",IFERROR(SUMIFS(Resources!$E$5:$E$504,Resources!$A$5:$A$504,">="&L$4,Resources!$A$5:$A$504,"<="&EOMONTH(L$4,0))/SUMIFS(Resources!$D$5:$D$504,Resources!$A$5:$A$504,">="&L$4,Resources!$A$5:$A$504,"<="&EOMONTH(L$4,0)),"")) -> 0.83489011 | M13: =IF(M$4>Settings!$B$6,"",IFERROR(SUMIFS(Resources!$E$5:$E$504,Resources!$A$5:$A$504,">="&M$4,Resources!$A$5:$A$504,"<="&EOMONTH(M$4,0))/SUMIFS(Resources!$D$5:$D$504,Resources!$A$5:$A$504,">="&M$4,Resources!$A$5:$A$504,"<="&EOMONTH(M$4,0)),"")) -> 0.81868557 | N13: =IF(N$4>Settings!$B$6,"",IFERROR(SUMIFS(Resources!$E$5:$E$504,Resources!$A$5:$A$504,">="&N$4,Resources!$A$5:$A$504,"<="&EOMONTH(N$4,0))/SUMIFS(Resources!$D$5:$D$504,Resources!$A$5:$A$504,">="&N$4,Resources!$A$5:$A$504,"<="&EOMONTH(N$4,0)),"")) -> 0.84076087 | ... R13: =IF(R$4>Settings!$B$6,"",IFERROR(SUMIFS(Resources!$E$5:$E$504,Resources!$A$5:$A$504,">="&R$4,Resources!$A$5:$A$504,"<="&EOMONTH(R$4,0))/SUMIFS(Resources!$D$5:$D$504,Resources!$A$5:$A$504,">="&R$4,Resources!$A$5:$A$504,"<="&EOMONTH(R$4,0)),"")) | S13: =IFERROR(LOOKUP(2,1/(G13:R13<>""),G13:R13),"") -> 0.86126374 | T13: =IF(S13="","",IF($D13="Higher",IF(S13>=$E13,"GREEN",IF(S13>=$F13,"AMBER","RED")),IF(S13<=$E13,"GREEN",IF(S13<=$F13,"AMBER","RED")))) -> GREEN | U13: =COUNTIF(G32:R32,"GREEN") -> 1 | V13: =COUNTIF(G32:R32,"RED") -> 0
A14: 10 | B14: =KPI_Targets!B14 -> Project Success Rate | C14: =KPI_Targets!E14 -> % | D14: =KPI_Targets!F14 -> Higher | E14: =KPI_Targets!G14 -> 0.8 | F14: =KPI_Targets!H14 -> 0.65 | G14: =IF(G$4>Settings!$B$6,"",IFERROR(COUNTIFS(Projects!$I$5:$I$104,"Completed",Projects!$H$5:$H$104,">="&Settings!$B$5,Projects!$H$5:$H$104,"<="&EOMONTH(G$4,0),Projects!$P$5:$P$104,"Yes")/COUNTIFS(Projects!$I$5:$I$104,"Completed",Projects!$H$5:$H$104,">="&Settings!$B$5,Projects!$H$5:$H$104,"<="&EOMONTH(G$4,0)),"")) | H14: =IF(H$4>Settings!$B$6,"",IFERROR(COUNTIFS(Projects!$I$5:$I$104,"Completed",Projects!$H$5:$H$104,">="&Settings!$B$5,Projects!$H$5:$H$104,"<="&EOMONTH(H$4,0),Projects!$P$5:$P$104,"Yes")/COUNTIFS(Projects!$I$5:$I$104,"Completed",Projects!$H$5:$H$104,">="&Settings!$B$5,Projects!$H$5:$H$104,"<="&EOMONTH(H$4,0)),"")) | I14: =IF(I$4>Settings!$B$6,"",IFERROR(COUNTIFS(Projects!$I$5:$I$104,"Completed",Projects!$H$5:$H$104,">="&Settings!$B$5,Projects!$H$5:$H$104,"<="&EOMONTH(I$4,0),Projects!$P$5:$P$104,"Yes")/COUNTIFS(Projects!$I$5:$I$104,"Completed",Projects!$H$5:$H$104,">="&Settings!$B$5,Projects!$H$5:$H$104,"<="&EOMONTH(I$4,0)),"")) | J14: =IF(J$4>Settings!$B$6,"",IFERROR(COUNTIFS(Projects!$I$5:$I$104,"Completed",Projects!$H$5:$H$104,">="&Settings!$B$5,Projects!$H$5:$H$104,"<="&EOMONTH(J$4,0),Projects!$P$5:$P$104,"Yes")/COUNTIFS(Projects!$I$5:$I$104,"Completed",Projects!$H$5:$H$104,">="&Settings!$B$5,Projects!$H$5:$H$104,"<="&EOMONTH(J$4,0)),"")) -> 1 | K14: =IF(K$4>Settings!$B$6,"",IFERROR(COUNTIFS(Projects!$I$5:$I$104,"Completed",Projects!$H$5:$H$104,">="&Settings!$B$5,Projects!$H$5:$H$104,"<="&EOMONTH(K$4,0),Projects!$P$5:$P$104,"Yes")/COUNTIFS(Projects!$I$5:$I$104,"Completed",Projects!$H$5:$H$104,">="&Settings!$B$5,Projects!$H$5:$H$104,"<="&EOMONTH(K$4,0)),"")) -> 1 | L14: =IF(L$4>Settings!$B$6,"",IFERROR(COUNTIFS(Projects!$I$5:$I$104,"Completed",Projects!$H$5:$H$104,">="&Settings!$B$5,Projects!$H$5:$H$104,"<="&EOMONTH(L$4,0),Projects!$P$5:$P$104,"Yes")/COUNTIFS(Projects!$I$5:$I$104,"Completed",Projects!$H$5:$H$104,">="&Settings!$B$5,Projects!$H$5:$H$104,"<="&EOMONTH(L$4,0)),"")) -> 0.5 | M14: =IF(M$4>Settings!$B$6,"",IFERROR(COUNTIFS(Projects!$I$5:$I$104,"Completed",Projects!$H$5:$H$104,">="&Settings!$B$5,Projects!$H$5:$H$104,"<="&EOMONTH(M$4,0),Projects!$P$5:$P$104,"Yes")/COUNTIFS(Projects!$I$5:$I$104,"Completed",Projects!$H$5:$H$104,">="&Settings!$B$5,Projects!$H$5:$H$104,"<="&EOMONTH(M$4,0)),"")) -> 0.33333333 | N14: =IF(N$4>Settings!$B$6,"",IFERROR(COUNTIFS(Projects!$I$5:$I$104,"Completed",Projects!$H$5:$H$104,">="&Settings!$B$5,Projects!$H$5:$H$104,"<="&EOMONTH(N$4,0),Projects!$P$5:$P$104,"Yes")/COUNTIFS(Projects!$I$5:$I$104,"Completed",Projects!$H$5:$H$104,">="&Settings!$B$5,Projects!$H$5:$H$104,"<="&EOMONTH(N$4,0)),"")) -> 0.5 | ... R14: =IF(R$4>Settings!$B$6,"",IFERROR(COUNTIFS(Projects!$I$5:$I$104,"Completed",Projects!$H$5:$H$104,">="&Settings!$B$5,Projects!$H$5:$H$104,"<="&EOMONTH(R$4,0),Projects!$P$5:$P$104,"Yes")/COUNTIFS(Projects!$I$5:$I$104,"Completed",Projects!$H$5:$H$104,">="&Settings!$B$5,Projects!$H$5:$H$104,"<="&EOMONTH(R$4,0)),"")) | S14: =IFERROR(LOOKUP(2,1/(G14:R14<>""),G14:R14),"") -> 0.6 | T14: =IF(S14="","",IF($D14="Higher",IF(S14>=$E14,"GREEN",IF(S14>=$F14,"AMBER","RED")),IF(S14<=$E14,"GREEN",IF(S14<=$F14,"AMBER","RED")))) -> RED | U14: =COUNTIF(G33:R33,"GREEN") -> 2 | V14: =COUNTIF(G33:R33,"RED") -> 5
A15: 11 | B15: =KPI_Targets!B15 -> Milestone Completion Rate | C15: =KPI_Targets!E15 -> % | D15: =KPI_Targets!F15 -> Higher | E15: =KPI_Targets!G15 -> 0.9 | F15: =KPI_Targets!H15 -> 0.8 | G15: =IF(G$4>Settings!$B$6,"",IFERROR(COUNTIFS(Milestones!$E$5:$E$504,">="&G$4,Milestones!$E$5:$E$504,"<="&EOMONTH(G$4,0),Milestones!$H$5:$H$504,"Yes")/COUNTIFS(Milestones!$E$5:$E$504,">="&G$4,Milestones!$E$5:$E$504,"<="&EOMONTH(G$4,0)),"")) -> 0.4 | H15: =IF(H$4>Settings!$B$6,"",IFERROR(COUNTIFS(Milestones!$E$5:$E$504,">="&H$4,Milestones!$E$5:$E$504,"<="&EOMONTH(H$4,0),Milestones!$H$5:$H$504,"Yes")/COUNTIFS(Milestones!$E$5:$E$504,">="&H$4,Milestones!$E$5:$E$504,"<="&EOMONTH(H$4,0)),"")) -> 0.6 | I15: =IF(I$4>Settings!$B$6,"",IFERROR(COUNTIFS(Milestones!$E$5:$E$504,">="&I$4,Milestones!$E$5:$E$504,"<="&EOMONTH(I$4,0),Milestones!$H$5:$H$504,"Yes")/COUNTIFS(Milestones!$E$5:$E$504,">="&I$4,Milestones!$E$5:$E$504,"<="&EOMONTH(I$4,0)),"")) -> 1 | J15: =IF(J$4>Settings!$B$6,"",IFERROR(COUNTIFS(Milestones!$E$5:$E$504,">="&J$4,Milestones!$E$5:$E$504,"<="&EOMONTH(J$4,0),Milestones!$H$5:$H$504,"Yes")/COUNTIFS(Milestones!$E$5:$E$504,">="&J$4,Milestones!$E$5:$E$504,"<="&EOMONTH(J$4,0)),"")) -> 0.8 | K15: =IF(K$4>Settings!$B$6,"",IFERROR(COUNTIFS(Milestones!$E$5:$E$504,">="&K$4,Milestones!$E$5:$E$504,"<="&EOMONTH(K$4,0),Milestones!$H$5:$H$504,"Yes")/COUNTIFS(Milestones!$E$5:$E$504,">="&K$4,Milestones!$E$5:$E$504,"<="&EOMONTH(K$4,0)),"")) -> 0.4 | L15: =IF(L$4>Settings!$B$6,"",IFERROR(COUNTIFS(Milestones!$E$5:$E$504,">="&L$4,Milestones!$E$5:$E$504,"<="&EOMONTH(L$4,0),Milestones!$H$5:$H$504,"Yes")/COUNTIFS(Milestones!$E$5:$E$504,">="&L$4,Milestones!$E$5:$E$504,"<="&EOMONTH(L$4,0)),"")) -> 0.4 | M15: =IF(M$4>Settings!$B$6,"",IFERROR(COUNTIFS(Milestones!$E$5:$E$504,">="&M$4,Milestones!$E$5:$E$504,"<="&EOMONTH(M$4,0),Milestones!$H$5:$H$504,"Yes")/COUNTIFS(Milestones!$E$5:$E$504,">="&M$4,Milestones!$E$5:$E$504,"<="&EOMONTH(M$4,0)),"")) -> 0.5 | N15: =IF(N$4>Settings!$B$6,"",IFERROR(COUNTIFS(Milestones!$E$5:$E$504,">="&N$4,Milestones!$E$5:$E$504,"<="&EOMONTH(N$4,0),Milestones!$H$5:$H$504,"Yes")/COUNTIFS(Milestones!$E$5:$E$504,">="&N$4,Milestones!$E$5:$E$504,"<="&EOMONTH(N$4,0)),"")) -> 0.5 | ... R15: =IF(R$4>Settings!$B$6,"",IFERROR(COUNTIFS(Milestones!$E$5:$E$504,">="&R$4,Milestones!$E$5:$E$504,"<="&EOMONTH(R$4,0),Milestones!$H$5:$H$504,"Yes")/COUNTIFS(Milestones!$E$5:$E$504,">="&R$4,Milestones!$E$5:$E$504,"<="&EOMONTH(R$4,0)),"")) | S15: =IFERROR(LOOKUP(2,1/(G15:R15<>""),G15:R15),"") -> 0.25 | T15: =IF(S15="","",IF($D15="Higher",IF(S15>=$E15,"GREEN",IF(S15>=$F15,"AMBER","RED")),IF(S15<=$E15,"GREEN",IF(S15<=$F15,"AMBER","RED")))) -> RED | U15: =COUNTIF(G34:R34,"GREEN") -> 2 | V15: =COUNTIF(G34:R34,"RED") -> 7
A16: 12 | B16: =KPI_Targets!B16 -> Project Quality Index | C16: =KPI_Targets!E16 -> % | D16: =KPI_Targets!F16 -> Higher | E16: =KPI_Targets!G16 -> 0.95 | F16: =KPI_Targets!H16 -> 0.85 | G16: =IF(G$4>Settings!$B$6,"",IFERROR(COUNTIFS(Quality_Log!$D$5:$D$504,">="&G$4,Quality_Log!$D$5:$D$504,"<="&EOMONTH(G$4,0),Quality_Log!$G$5:$G$504,"Yes")/COUNTIFS(Quality_Log!$D$5:$D$504,">="&G$4,Quality_Log!$D$5:$D$504,"<="&EOMONTH(G$4,0)),"")) -> 1 | H16: =IF(H$4>Settings!$B$6,"",IFERROR(COUNTIFS(Quality_Log!$D$5:$D$504,">="&H$4,Quality_Log!$D$5:$D$504,"<="&EOMONTH(H$4,0),Quality_Log!$G$5:$G$504,"Yes")/COUNTIFS(Quality_Log!$D$5:$D$504,">="&H$4,Quality_Log!$D$5:$D$504,"<="&EOMONTH(H$4,0)),"")) -> 0.8 | I16: =IF(I$4>Settings!$B$6,"",IFERROR(COUNTIFS(Quality_Log!$D$5:$D$504,">="&I$4,Quality_Log!$D$5:$D$504,"<="&EOMONTH(I$4,0),Quality_Log!$G$5:$G$504,"Yes")/COUNTIFS(Quality_Log!$D$5:$D$504,">="&I$4,Quality_Log!$D$5:$D$504,"<="&EOMONTH(I$4,0)),"")) -> 1 | J16: =IF(J$4>Settings!$B$6,"",IFERROR(COUNTIFS(Quality_Log!$D$5:$D$504,">="&J$4,Quality_Log!$D$5:$D$504,"<="&EOMONTH(J$4,0),Quality_Log!$G$5:$G$504,"Yes")/COUNTIFS(Quality_Log!$D$5:$D$504,">="&J$4,Quality_Log!$D$5:$D$504,"<="&EOMONTH(J$4,0)),"")) -> 0.6 | K16: =IF(K$4>Settings!$B$6,"",IFERROR(COUNTIFS(Quality_Log!$D$5:$D$504,">="&K$4,Quality_Log!$D$5:$D$504,"<="&EOMONTH(K$4,0),Quality_Log!$G$5:$G$504,"Yes")/COUNTIFS(Quality_Log!$D$5:$D$504,">="&K$4,Quality_Log!$D$5:$D$504,"<="&EOMONTH(K$4,0)),"")) -> 0.8 | L16: =IF(L$4>Settings!$B$6,"",IFERROR(COUNTIFS(Quality_Log!$D$5:$D$504,">="&L$4,Quality_Log!$D$5:$D$504,"<="&EOMONTH(L$4,0),Quality_Log!$G$5:$G$504,"Yes")/COUNTIFS(Quality_Log!$D$5:$D$504,">="&L$4,Quality_Log!$D$5:$D$504,"<="&EOMONTH(L$4,0)),"")) -> 1 | M16: =IF(M$4>Settings!$B$6,"",IFERROR(COUNTIFS(Quality_Log!$D$5:$D$504,">="&M$4,Quality_Log!$D$5:$D$504,"<="&EOMONTH(M$4,0),Quality_Log!$G$5:$G$504,"Yes")/COUNTIFS(Quality_Log!$D$5:$D$504,">="&M$4,Quality_Log!$D$5:$D$504,"<="&EOMONTH(M$4,0)),"")) -> 0.8 | N16: =IF(N$4>Settings!$B$6,"",IFERROR(COUNTIFS(Quality_Log!$D$5:$D$504,">="&N$4,Quality_Log!$D$5:$D$504,"<="&EOMONTH(N$4,0),Quality_Log!$G$5:$G$504,"Yes")/COUNTIFS(Quality_Log!$D$5:$D$504,">="&N$4,Quality_Log!$D$5:$D$504,"<="&EOMONTH(N$4,0)),"")) -> 1 | ... R16: =IF(R$4>Settings!$B$6,"",IFERROR(COUNTIFS(Quality_Log!$D$5:$D$504,">="&R$4,Quality_Log!$D$5:$D$504,"<="&EOMONTH(R$4,0),Quality_Log!$G$5:$G$504,"Yes")/COUNTIFS(Quality_Log!$D$5:$D$504,">="&R$4,Quality_Log!$D$5:$D$504,"<="&EOMONTH(R$4,0)),"")) | S16: =IFERROR(LOOKUP(2,1/(G16:R16<>""),G16:R16),"") -> 1 | T16: =IF(S16="","",IF($D16="Higher",IF(S16>=$E16,"GREEN",IF(S16>=$F16,"AMBER","RED")),IF(S16<=$E16,"GREEN",IF(S16<=$F16,"AMBER","RED")))) -> GREEN | U16: =COUNTIF(G35:R35,"GREEN") -> 6 | V16: =COUNTIF(G35:R35,"RED") -> 4
A17: 13 | B17: =KPI_Targets!B17 -> Change Request Approval Time | C17: =KPI_Targets!E17 -> days | D17: =KPI_Targets!F17 -> Lower | E17: =KPI_Targets!G17 -> 5 | F17: =KPI_Targets!H17 -> 10 | G17: =IF(G$4>Settings!$B$6,"",IFERROR(AVERAGEIFS(Change_Log!$K$5:$K$504,Change_Log!$J$5:$J$504,">="&G$4,Change_Log!$J$5:$J$504,"<="&EOMONTH(G$4,0)),"")) -> 8.6666667 | H17: =IF(H$4>Settings!$B$6,"",IFERROR(AVERAGEIFS(Change_Log!$K$5:$K$504,Change_Log!$J$5:$J$504,">="&H$4,Change_Log!$J$5:$J$504,"<="&EOMONTH(H$4,0)),"")) -> 9 | I17: =IF(I$4>Settings!$B$6,"",IFERROR(AVERAGEIFS(Change_Log!$K$5:$K$504,Change_Log!$J$5:$J$504,">="&I$4,Change_Log!$J$5:$J$504,"<="&EOMONTH(I$4,0)),"")) -> 7.6 | J17: =IF(J$4>Settings!$B$6,"",IFERROR(AVERAGEIFS(Change_Log!$K$5:$K$504,Change_Log!$J$5:$J$504,">="&J$4,Change_Log!$J$5:$J$504,"<="&EOMONTH(J$4,0)),"")) -> 7 | K17: =IF(K$4>Settings!$B$6,"",IFERROR(AVERAGEIFS(Change_Log!$K$5:$K$504,Change_Log!$J$5:$J$504,">="&K$4,Change_Log!$J$5:$J$504,"<="&EOMONTH(K$4,0)),"")) -> 5.3333333 | L17: =IF(L$4>Settings!$B$6,"",IFERROR(AVERAGEIFS(Change_Log!$K$5:$K$504,Change_Log!$J$5:$J$504,">="&L$4,Change_Log!$J$5:$J$504,"<="&EOMONTH(L$4,0)),"")) -> 4 | M17: =IF(M$4>Settings!$B$6,"",IFERROR(AVERAGEIFS(Change_Log!$K$5:$K$504,Change_Log!$J$5:$J$504,">="&M$4,Change_Log!$J$5:$J$504,"<="&EOMONTH(M$4,0)),"")) -> 5 | N17: =IF(N$4>Settings!$B$6,"",IFERROR(AVERAGEIFS(Change_Log!$K$5:$K$504,Change_Log!$J$5:$J$504,">="&N$4,Change_Log!$J$5:$J$504,"<="&EOMONTH(N$4,0)),"")) -> 6 | ... R17: =IF(R$4>Settings!$B$6,"",IFERROR(AVERAGEIFS(Change_Log!$K$5:$K$504,Change_Log!$J$5:$J$504,">="&R$4,Change_Log!$J$5:$J$504,"<="&EOMONTH(R$4,0)),"")) | S17: =IFERROR(LOOKUP(2,1/(G17:R17<>""),G17:R17),"") -> 5 | T17: =IF(S17="","",IF($D17="Higher",IF(S17>=$E17,"GREEN",IF(S17>=$F17,"AMBER","RED")),IF(S17<=$E17,"GREEN",IF(S17<=$F17,"AMBER","RED")))) -> GREEN | U17: =COUNTIF(G36:R36,"GREEN") -> 3 | V17: =COUNTIF(G36:R36,"RED") -> 0
A18: 14 | B18: =KPI_Targets!B18 -> Team Productivity Index | C18: =KPI_Targets!E18 -> index | D18: =KPI_Targets!F18 -> Higher | E18: =KPI_Targets!G18 -> 1 | F18: =KPI_Targets!H18 -> 0.9 | G18: =IF(G$4>Settings!$B$6,"",IFERROR(AVERAGEIFS(Resources!$J$5:$J$504,Resources!$A$5:$A$504,">="&G$4,Resources!$A$5:$A$504,"<="&EOMONTH(G$4,0)),"")) -> 0.96216667 | H18: =IF(H$4>Settings!$B$6,"",IFERROR(AVERAGEIFS(Resources!$J$5:$J$504,Resources!$A$5:$A$504,">="&H$4,Resources!$A$5:$A$504,"<="&EOMONTH(H$4,0)),"")) -> 0.90721528 | I18: =IF(I$4>Settings!$B$6,"",IFERROR(AVERAGEIFS(Resources!$J$5:$J$504,Resources!$A$5:$A$504,">="&I$4,Resources!$A$5:$A$504,"<="&EOMONTH(I$4,0)),"")) -> 0.96729861 | J18: =IF(J$4>Settings!$B$6,"",IFERROR(AVERAGEIFS(Resources!$J$5:$J$504,Resources!$A$5:$A$504,">="&J$4,Resources!$A$5:$A$504,"<="&EOMONTH(J$4,0)),"")) -> 0.96393056 | K18: =IF(K$4>Settings!$B$6,"",IFERROR(AVERAGEIFS(Resources!$J$5:$J$504,Resources!$A$5:$A$504,">="&K$4,Resources!$A$5:$A$504,"<="&EOMONTH(K$4,0)),"")) -> 0.98034722 | L18: =IF(L$4>Settings!$B$6,"",IFERROR(AVERAGEIFS(Resources!$J$5:$J$504,Resources!$A$5:$A$504,">="&L$4,Resources!$A$5:$A$504,"<="&EOMONTH(L$4,0)),"")) -> 0.94514583 | M18: =IF(M$4>Settings!$B$6,"",IFERROR(AVERAGEIFS(Resources!$J$5:$J$504,Resources!$A$5:$A$504,">="&M$4,Resources!$A$5:$A$504,"<="&EOMONTH(M$4,0)),"")) -> 1.0134514 | N18: =IF(N$4>Settings!$B$6,"",IFERROR(AVERAGEIFS(Resources!$J$5:$J$504,Resources!$A$5:$A$504,">="&N$4,Resources!$A$5:$A$504,"<="&EOMONTH(N$4,0)),"")) -> 0.96982639 | ... R18: =IF(R$4>Settings!$B$6,"",IFERROR(AVERAGEIFS(Resources!$J$5:$J$504,Resources!$A$5:$A$504,">="&R$4,Resources!$A$5:$A$504,"<="&EOMONTH(R$4,0)),"")) | S18: =IFERROR(LOOKUP(2,1/(G18:R18<>""),G18:R18),"") -> 0.95547917 | T18: =IF(S18="","",IF($D18="Higher",IF(S18>=$E18,"GREEN",IF(S18>=$F18,"AMBER","RED")),IF(S18<=$E18,"GREEN",IF(S18<=$F18,"AMBER","RED")))) -> AMBER | U18: =COUNTIF(G37:R37,"GREEN") -> 1 | V18: =COUNTIF(G37:R37,"RED") -> 0
A19: 15 | B19: =KPI_Targets!B19 -> Benefits Realization | C19: =KPI_Targets!E19 -> % | D19: =KPI_Targets!F19 -> Higher | E19: =KPI_Targets!G19 -> 0.9 | F19: =KPI_Targets!H19 -> 0.75 | G19: =IF(G$4>Settings!$B$6,"",IFERROR(SUMIFS(Benefits_Log!$G$5:$G$504,Benefits_Log!$E$5:$E$504,">="&G$4,Benefits_Log!$E$5:$E$504,"<="&EOMONTH(G$4,0))/SUMIFS(Benefits_Log!$F$5:$F$504,Benefits_Log!$E$5:$E$504,">="&G$4,Benefits_Log!$E$5:$E$504,"<="&EOMONTH(G$4,0)),"")) | H19: =IF(H$4>Settings!$B$6,"",IFERROR(SUMIFS(Benefits_Log!$G$5:$G$504,Benefits_Log!$E$5:$E$504,">="&H$4,Benefits_Log!$E$5:$E$504,"<="&EOMONTH(H$4,0))/SUMIFS(Benefits_Log!$F$5:$F$504,Benefits_Log!$E$5:$E$504,">="&H$4,Benefits_Log!$E$5:$E$504,"<="&EOMONTH(H$4,0)),"")) | I19: =IF(I$4>Settings!$B$6,"",IFERROR(SUMIFS(Benefits_Log!$G$5:$G$504,Benefits_Log!$E$5:$E$504,">="&I$4,Benefits_Log!$E$5:$E$504,"<="&EOMONTH(I$4,0))/SUMIFS(Benefits_Log!$F$5:$F$504,Benefits_Log!$E$5:$E$504,">="&I$4,Benefits_Log!$E$5:$E$504,"<="&EOMONTH(I$4,0)),"")) | J19: =IF(J$4>Settings!$B$6,"",IFERROR(SUMIFS(Benefits_Log!$G$5:$G$504,Benefits_Log!$E$5:$E$504,">="&J$4,Benefits_Log!$E$5:$E$504,"<="&EOMONTH(J$4,0))/SUMIFS(Benefits_Log!$F$5:$F$504,Benefits_Log!$E$5:$E$504,">="&J$4,Benefits_Log!$E$5:$E$504,"<="&EOMONTH(J$4,0)),"")) -> 0.9166 | K19: =IF(K$4>Settings!$B$6,"",IFERROR(SUMIFS(Benefits_Log!$G$5:$G$504,Benefits_Log!$E$5:$E$504,">="&K$4,Benefits_Log!$E$5:$E$504,"<="&EOMONTH(K$4,0))/SUMIFS(Benefits_Log!$F$5:$F$504,Benefits_Log!$E$5:$E$504,">="&K$4,Benefits_Log!$E$5:$E$504,"<="&EOMONTH(K$4,0)),"")) -> 0.88562 | L19: =IF(L$4>Settings!$B$6,"",IFERROR(SUMIFS(Benefits_Log!$G$5:$G$504,Benefits_Log!$E$5:$E$504,">="&L$4,Benefits_Log!$E$5:$E$504,"<="&EOMONTH(L$4,0))/SUMIFS(Benefits_Log!$F$5:$F$504,Benefits_Log!$E$5:$E$504,">="&L$4,Benefits_Log!$E$5:$E$504,"<="&EOMONTH(L$4,0)),"")) -> 0.94735484 | M19: =IF(M$4>Settings!$B$6,"",IFERROR(SUMIFS(Benefits_Log!$G$5:$G$504,Benefits_Log!$E$5:$E$504,">="&M$4,Benefits_Log!$E$5:$E$504,"<="&EOMONTH(M$4,0))/SUMIFS(Benefits_Log!$F$5:$F$504,Benefits_Log!$E$5:$E$504,">="&M$4,Benefits_Log!$E$5:$E$504,"<="&EOMONTH(M$4,0)),"")) -> 0.89497794 | N19: =IF(N$4>Settings!$B$6,"",IFERROR(SUMIFS(Benefits_Log!$G$5:$G$504,Benefits_Log!$E$5:$E$504,">="&N$4,Benefits_Log!$E$5:$E$504,"<="&EOMONTH(N$4,0))/SUMIFS(Benefits_Log!$F$5:$F$504,Benefits_Log!$E$5:$E$504,">="&N$4,Benefits_Log!$E$5:$E$504,"<="&EOMONTH(N$4,0)),"")) -> 0.86095164 | ... R19: =IF(R$4>Settings!$B$6,"",IFERROR(SUMIFS(Benefits_Log!$G$5:$G$504,Benefits_Log!$E$5:$E$504,">="&R$4,Benefits_Log!$E$5:$E$504,"<="&EOMONTH(R$4,0))/SUMIFS(Benefits_Log!$F$5:$F$504,Benefits_Log!$E$5:$E$504,">="&R$4,Benefits_Log!$E$5:$E$504,"<="&EOMONTH(R$4,0)),"")) | S19: =IFERROR(LOOKUP(2,1/(G19:R19<>""),G19:R19),"") -> 0.92257418 | T19: =IF(S19="","",IF($D19="Higher",IF(S19>=$E19,"GREEN",IF(S19>=$F19,"AMBER","RED")),IF(S19<=$E19,"GREEN",IF(S19<=$F19,"AMBER","RED")))) -> GREEN | U19: =COUNTIF(G38:R38,"GREEN") -> 3 | V19: =COUNTIF(G38:R38,"RED") -> 0
A20: 16 | B20: =KPI_Targets!B20 -> Continuous Improvement Initiatives | C20: =KPI_Targets!E20 -> count | D20: =KPI_Targets!F20 -> Higher | E20: =KPI_Targets!G20 -> 2 | F20: =KPI_Targets!H20 -> 1 | G20: =IF(G$4>Settings!$B$6,"",IFERROR(COUNTIFS(CI_Log!$G$5:$G$504,">="&G$4,CI_Log!$G$5:$G$504,"<="&EOMONTH(G$4,0),CI_Log!$F$5:$F$504,"Implemented"),"")) -> 1 | H20: =IF(H$4>Settings!$B$6,"",IFERROR(COUNTIFS(CI_Log!$G$5:$G$504,">="&H$4,CI_Log!$G$5:$G$504,"<="&EOMONTH(H$4,0),CI_Log!$F$5:$F$504,"Implemented"),"")) -> 2 | I20: =IF(I$4>Settings!$B$6,"",IFERROR(COUNTIFS(CI_Log!$G$5:$G$504,">="&I$4,CI_Log!$G$5:$G$504,"<="&EOMONTH(I$4,0),CI_Log!$F$5:$F$504,"Implemented"),"")) -> 0 | J20: =IF(J$4>Settings!$B$6,"",IFERROR(COUNTIFS(CI_Log!$G$5:$G$504,">="&J$4,CI_Log!$G$5:$G$504,"<="&EOMONTH(J$4,0),CI_Log!$F$5:$F$504,"Implemented"),"")) -> 3 | K20: =IF(K$4>Settings!$B$6,"",IFERROR(COUNTIFS(CI_Log!$G$5:$G$504,">="&K$4,CI_Log!$G$5:$G$504,"<="&EOMONTH(K$4,0),CI_Log!$F$5:$F$504,"Implemented"),"")) -> 1 | L20: =IF(L$4>Settings!$B$6,"",IFERROR(COUNTIFS(CI_Log!$G$5:$G$504,">="&L$4,CI_Log!$G$5:$G$504,"<="&EOMONTH(L$4,0),CI_Log!$F$5:$F$504,"Implemented"),"")) -> 1 | M20: =IF(M$4>Settings!$B$6,"",IFERROR(COUNTIFS(CI_Log!$G$5:$G$504,">="&M$4,CI_Log!$G$5:$G$504,"<="&EOMONTH(M$4,0),CI_Log!$F$5:$F$504,"Implemented"),"")) -> 2 | N20: =IF(N$4>Settings!$B$6,"",IFERROR(COUNTIFS(CI_Log!$G$5:$G$504,">="&N$4,CI_Log!$G$5:$G$504,"<="&EOMONTH(N$4,0),CI_Log!$F$5:$F$504,"Implemented"),"")) -> 1 | ... R20: =IF(R$4>Settings!$B$6,"",IFERROR(COUNTIFS(CI_Log!$G$5:$G$504,">="&R$4,CI_Log!$G$5:$G$504,"<="&EOMONTH(R$4,0),CI_Log!$F$5:$F$504,"Implemented"),"")) | S20: =IFERROR(LOOKUP(2,1/(G20:R20<>""),G20:R20),"") -> 0 | T20: =IF(S20="","",IF($D20="Higher",IF(S20>=$E20,"GREEN",IF(S20>=$F20,"AMBER","RED")),IF(S20<=$E20,"GREEN",IF(S20<=$F20,"AMBER","RED")))) -> RED | U20: =COUNTIF(G39:R39,"GREEN") -> 3 | V20: =COUNTIF(G39:R39,"RED") -> 3
B22: Monthly RAG status (automatic)
A23: # | B23: KPI | G23: =G4 -> 46023 | H23: =H4 -> 46054 | I23: =I4 -> 46082 | J23: =J4 -> 46113 | K23: =K4 -> 46143 | L23: =L4 -> 46174 | M23: =M4 -> 46204 | N23: =N4 -> 46235 | ... R23: =R4 -> 46357
A24: 1 | B24: =B5 -> Project Schedule Variance (SV%) | G24: =IF(G5="","",IF($D5="Higher",IF(G5>=$E5,"GREEN",IF(G5>=$F5,"AMBER","RED")),IF(G5<=$E5,"GREEN",IF(G5<=$F5,"AMBER","RED")))) -> RED | H24: =IF(H5="","",IF($D5="Higher",IF(H5>=$E5,"GREEN",IF(H5>=$F5,"AMBER","RED")),IF(H5<=$E5,"GREEN",IF(H5<=$F5,"AMBER","RED")))) -> AMBER | I24: =IF(I5="","",IF($D5="Higher",IF(I5>=$E5,"GREEN",IF(I5>=$F5,"AMBER","RED")),IF(I5<=$E5,"GREEN",IF(I5<=$F5,"AMBER","RED")))) -> AMBER | J24: =IF(J5="","",IF($D5="Higher",IF(J5>=$E5,"GREEN",IF(J5>=$F5,"AMBER","RED")),IF(J5<=$E5,"GREEN",IF(J5<=$F5,"AMBER","RED")))) -> AMBER | K24: =IF(K5="","",IF($D5="Higher",IF(K5>=$E5,"GREEN",IF(K5>=$F5,"AMBER","RED")),IF(K5<=$E5,"GREEN",IF(K5<=$F5,"AMBER","RED")))) -> AMBER | L24: =IF(L5="","",IF($D5="Higher",IF(L5>=$E5,"GREEN",IF(L5>=$F5,"AMBER","RED")),IF(L5<=$E5,"GREEN",IF(L5<=$F5,"AMBER","RED")))) -> RED | M24: =IF(M5="","",IF($D5="Higher",IF(M5>=$E5,"GREEN",IF(M5>=$F5,"AMBER","RED")),IF(M5<=$E5,"GREEN",IF(M5<=$F5,"AMBER","RED")))) -> RED | N24: =IF(N5="","",IF($D5="Higher",IF(N5>=$E5,"GREEN",IF(N5>=$F5,"AMBER","RED")),IF(N5<=$E5,"GREEN",IF(N5<=$F5,"AMBER","RED")))) -> AMBER | ... R24: =IF(R5="","",IF($D5="Higher",IF(R5>=$E5,"GREEN",IF(R5>=$F5,"AMBER","RED")),IF(R5<=$E5,"GREEN",IF(R5<=$F5,"AMBER","RED"))))
A25: 2 | B25: =B6 -> Project Cost Variance (CV%) | G25: =IF(G6="","",IF($D6="Higher",IF(G6>=$E6,"GREEN",IF(G6>=$F6,"AMBER","RED")),IF(G6<=$E6,"GREEN",IF(G6<=$F6,"AMBER","RED")))) -> AMBER | H25: =IF(H6="","",IF($D6="Higher",IF(H6>=$E6,"GREEN",IF(H6>=$F6,"AMBER","RED")),IF(H6<=$E6,"GREEN",IF(H6<=$F6,"AMBER","RED")))) -> AMBER | I25: =IF(I6="","",IF($D6="Higher",IF(I6>=$E6,"GREEN",IF(I6>=$F6,"AMBER","RED")),IF(I6<=$E6,"GREEN",IF(I6<=$F6,"AMBER","RED")))) -> AMBER | J25: =IF(J6="","",IF($D6="Higher",IF(J6>=$E6,"GREEN",IF(J6>=$F6,"AMBER","RED")),IF(J6<=$E6,"GREEN",IF(J6<=$F6,"AMBER","RED")))) -> AMBER | K25: =IF(K6="","",IF($D6="Higher",IF(K6>=$E6,"GREEN",IF(K6>=$F6,"AMBER","RED")),IF(K6<=$E6,"GREEN",IF(K6<=$F6,"AMBER","RED")))) -> AMBER | L25: =IF(L6="","",IF($D6="Higher",IF(L6>=$E6,"GREEN",IF(L6>=$F6,"AMBER","RED")),IF(L6<=$E6,"GREEN",IF(L6<=$F6,"AMBER","RED")))) -> AMBER | M25: =IF(M6="","",IF($D6="Higher",IF(M6>=$E6,"GREEN",IF(M6>=$F6,"AMBER","RED")),IF(M6<=$E6,"GREEN",IF(M6<=$F6,"AMBER","RED")))) -> AMBER | N25: =IF(N6="","",IF($D6="Higher",IF(N6>=$E6,"GREEN",IF(N6>=$F6,"AMBER","RED")),IF(N6<=$E6,"GREEN",IF(N6<=$F6,"AMBER","RED")))) -> AMBER | ... R25: =IF(R6="","",IF($D6="Higher",IF(R6>=$E6,"GREEN",IF(R6>=$F6,"AMBER","RED")),IF(R6<=$E6,"GREEN",IF(R6<=$F6,"AMBER","RED"))))
A26: 3 | B26: =B7 -> Budget Utilization | G26: =IF(G7="","",IF($D7="Higher",IF(G7>=$E7,"GREEN",IF(G7>=$F7,"AMBER","RED")),IF(G7<=$E7,"GREEN",IF(G7<=$F7,"AMBER","RED")))) -> GREEN | H26: =IF(H7="","",IF($D7="Higher",IF(H7>=$E7,"GREEN",IF(H7>=$F7,"AMBER","RED")),IF(H7<=$E7,"GREEN",IF(H7<=$F7,"AMBER","RED")))) -> GREEN | I26: =IF(I7="","",IF($D7="Higher",IF(I7>=$E7,"GREEN",IF(I7>=$F7,"AMBER","RED")),IF(I7<=$E7,"GREEN",IF(I7<=$F7,"AMBER","RED")))) -> GREEN | J26: =IF(J7="","",IF($D7="Higher",IF(J7>=$E7,"GREEN",IF(J7>=$F7,"AMBER","RED")),IF(J7<=$E7,"GREEN",IF(J7<=$F7,"AMBER","RED")))) -> GREEN | K26: =IF(K7="","",IF($D7="Higher",IF(K7>=$E7,"GREEN",IF(K7>=$F7,"AMBER","RED")),IF(K7<=$E7,"GREEN",IF(K7<=$F7,"AMBER","RED")))) -> GREEN | L26: =IF(L7="","",IF($D7="Higher",IF(L7>=$E7,"GREEN",IF(L7>=$F7,"AMBER","RED")),IF(L7<=$E7,"GREEN",IF(L7<=$F7,"AMBER","RED")))) -> GREEN | M26: =IF(M7="","",IF($D7="Higher",IF(M7>=$E7,"GREEN",IF(M7>=$F7,"AMBER","RED")),IF(M7<=$E7,"GREEN",IF(M7<=$F7,"AMBER","RED")))) -> GREEN | N26: =IF(N7="","",IF($D7="Higher",IF(N7>=$E7,"GREEN",IF(N7>=$F7,"AMBER","RED")),IF(N7<=$E7,"GREEN",IF(N7<=$F7,"AMBER","RED")))) -> GREEN | ... R26: =IF(R7="","",IF($D7="Higher",IF(R7>=$E7,"GREEN",IF(R7>=$F7,"AMBER","RED")),IF(R7<=$E7,"GREEN",IF(R7<=$F7,"AMBER","RED"))))
A27: 4 | B27: =B8 -> On-Time Project Delivery | G27: =IF(G8="","",IF($D8="Higher",IF(G8>=$E8,"GREEN",IF(G8>=$F8,"AMBER","RED")),IF(G8<=$E8,"GREEN",IF(G8<=$F8,"AMBER","RED")))) | H27: =IF(H8="","",IF($D8="Higher",IF(H8>=$E8,"GREEN",IF(H8>=$F8,"AMBER","RED")),IF(H8<=$E8,"GREEN",IF(H8<=$F8,"AMBER","RED")))) | I27: =IF(I8="","",IF($D8="Higher",IF(I8>=$E8,"GREEN",IF(I8>=$F8,"AMBER","RED")),IF(I8<=$E8,"GREEN",IF(I8<=$F8,"AMBER","RED")))) | J27: =IF(J8="","",IF($D8="Higher",IF(J8>=$E8,"GREEN",IF(J8>=$F8,"AMBER","RED")),IF(J8<=$E8,"GREEN",IF(J8<=$F8,"AMBER","RED")))) -> GREEN | K27: =IF(K8="","",IF($D8="Higher",IF(K8>=$E8,"GREEN",IF(K8>=$F8,"AMBER","RED")),IF(K8<=$E8,"GREEN",IF(K8<=$F8,"AMBER","RED")))) -> GREEN | L27: =IF(L8="","",IF($D8="Higher",IF(L8>=$E8,"GREEN",IF(L8>=$F8,"AMBER","RED")),IF(L8<=$E8,"GREEN",IF(L8<=$F8,"AMBER","RED")))) -> RED | M27: =IF(M8="","",IF($D8="Higher",IF(M8>=$E8,"GREEN",IF(M8>=$F8,"AMBER","RED")),IF(M8<=$E8,"GREEN",IF(M8<=$F8,"AMBER","RED")))) -> RED | N27: =IF(N8="","",IF($D8="Higher",IF(N8>=$E8,"GREEN",IF(N8>=$F8,"AMBER","RED")),IF(N8<=$E8,"GREEN",IF(N8<=$F8,"AMBER","RED")))) -> RED | ... R27: =IF(R8="","",IF($D8="Higher",IF(R8>=$E8,"GREEN",IF(R8>=$F8,"AMBER","RED")),IF(R8<=$E8,"GREEN",IF(R8<=$F8,"AMBER","RED"))))
A28: 5 | B28: =B9 -> Scope Change Frequency | G28: =IF(G9="","",IF($D9="Higher",IF(G9>=$E9,"GREEN",IF(G9>=$F9,"AMBER","RED")),IF(G9<=$E9,"GREEN",IF(G9<=$F9,"AMBER","RED")))) -> AMBER | H28: =IF(H9="","",IF($D9="Higher",IF(H9>=$E9,"GREEN",IF(H9>=$F9,"AMBER","RED")),IF(H9<=$E9,"GREEN",IF(H9<=$F9,"AMBER","RED")))) -> GREEN | I28: =IF(I9="","",IF($D9="Higher",IF(I9>=$E9,"GREEN",IF(I9>=$F9,"AMBER","RED")),IF(I9<=$E9,"GREEN",IF(I9<=$F9,"AMBER","RED")))) -> GREEN | J28: =IF(J9="","",IF($D9="Higher",IF(J9>=$E9,"GREEN",IF(J9>=$F9,"AMBER","RED")),IF(J9<=$E9,"GREEN",IF(J9<=$F9,"AMBER","RED")))) -> GREEN | K28: =IF(K9="","",IF($D9="Higher",IF(K9>=$E9,"GREEN",IF(K9>=$F9,"AMBER","RED")),IF(K9<=$E9,"GREEN",IF(K9<=$F9,"AMBER","RED")))) -> GREEN | L28: =IF(L9="","",IF($D9="Higher",IF(L9>=$E9,"GREEN",IF(L9>=$F9,"AMBER","RED")),IF(L9<=$E9,"GREEN",IF(L9<=$F9,"AMBER","RED")))) -> GREEN | M28: =IF(M9="","",IF($D9="Higher",IF(M9>=$E9,"GREEN",IF(M9>=$F9,"AMBER","RED")),IF(M9<=$E9,"GREEN",IF(M9<=$F9,"AMBER","RED")))) -> GREEN | N28: =IF(N9="","",IF($D9="Higher",IF(N9>=$E9,"GREEN",IF(N9>=$F9,"AMBER","RED")),IF(N9<=$E9,"GREEN",IF(N9<=$F9,"AMBER","RED")))) -> GREEN | ... R28: =IF(R9="","",IF($D9="Higher",IF(R9>=$E9,"GREEN",IF(R9>=$F9,"AMBER","RED")),IF(R9<=$E9,"GREEN",IF(R9<=$F9,"AMBER","RED"))))
A29: 6 | B29: =B10 -> Risk Mitigation Effectiveness | G29: =IF(G10="","",IF($D10="Higher",IF(G10>=$E10,"GREEN",IF(G10>=$F10,"AMBER","RED")),IF(G10<=$E10,"GREEN",IF(G10<=$F10,"AMBER","RED")))) | H29: =IF(H10="","",IF($D10="Higher",IF(H10>=$E10,"GREEN",IF(H10>=$F10,"AMBER","RED")),IF(H10<=$E10,"GREEN",IF(H10<=$F10,"AMBER","RED")))) | I29: =IF(I10="","",IF($D10="Higher",IF(I10>=$E10,"GREEN",IF(I10>=$F10,"AMBER","RED")),IF(I10<=$E10,"GREEN",IF(I10<=$F10,"AMBER","RED")))) -> GREEN | J29: =IF(J10="","",IF($D10="Higher",IF(J10>=$E10,"GREEN",IF(J10>=$F10,"AMBER","RED")),IF(J10<=$E10,"GREEN",IF(J10<=$F10,"AMBER","RED")))) -> GREEN | K29: =IF(K10="","",IF($D10="Higher",IF(K10>=$E10,"GREEN",IF(K10>=$F10,"AMBER","RED")),IF(K10<=$E10,"GREEN",IF(K10<=$F10,"AMBER","RED")))) -> GREEN | L29: =IF(L10="","",IF($D10="Higher",IF(L10>=$E10,"GREEN",IF(L10>=$F10,"AMBER","RED")),IF(L10<=$E10,"GREEN",IF(L10<=$F10,"AMBER","RED")))) -> AMBER | M29: =IF(M10="","",IF($D10="Higher",IF(M10>=$E10,"GREEN",IF(M10>=$F10,"AMBER","RED")),IF(M10<=$E10,"GREEN",IF(M10<=$F10,"AMBER","RED")))) -> AMBER | N29: =IF(N10="","",IF($D10="Higher",IF(N10>=$E10,"GREEN",IF(N10>=$F10,"AMBER","RED")),IF(N10<=$E10,"GREEN",IF(N10<=$F10,"AMBER","RED")))) -> AMBER | ... R29: =IF(R10="","",IF($D10="Higher",IF(R10>=$E10,"GREEN",IF(R10>=$F10,"AMBER","RED")),IF(R10<=$E10,"GREEN",IF(R10<=$F10,"AMBER","RED"))))
A30: 7 | B30: =B11 -> Issue Resolution Time | G30: =IF(G11="","",IF($D11="Higher",IF(G11>=$E11,"GREEN",IF(G11>=$F11,"AMBER","RED")),IF(G11<=$E11,"GREEN",IF(G11<=$F11,"AMBER","RED")))) -> AMBER | H30: =IF(H11="","",IF($D11="Higher",IF(H11>=$E11,"GREEN",IF(H11>=$F11,"AMBER","RED")),IF(H11<=$E11,"GREEN",IF(H11<=$F11,"AMBER","RED")))) -> RED | I30: =IF(I11="","",IF($D11="Higher",IF(I11>=$E11,"GREEN",IF(I11>=$F11,"AMBER","RED")),IF(I11<=$E11,"GREEN",IF(I11<=$F11,"AMBER","RED")))) -> AMBER | J30: =IF(J11="","",IF($D11="Higher",IF(J11>=$E11,"GREEN",IF(J11>=$F11,"AMBER","RED")),IF(J11<=$E11,"GREEN",IF(J11<=$F11,"AMBER","RED")))) -> GREEN | K30: =IF(K11="","",IF($D11="Higher",IF(K11>=$E11,"GREEN",IF(K11>=$F11,"AMBER","RED")),IF(K11<=$E11,"GREEN",IF(K11<=$F11,"AMBER","RED")))) -> AMBER | L30: =IF(L11="","",IF($D11="Higher",IF(L11>=$E11,"GREEN",IF(L11>=$F11,"AMBER","RED")),IF(L11<=$E11,"GREEN",IF(L11<=$F11,"AMBER","RED")))) -> GREEN | M30: =IF(M11="","",IF($D11="Higher",IF(M11>=$E11,"GREEN",IF(M11>=$F11,"AMBER","RED")),IF(M11<=$E11,"GREEN",IF(M11<=$F11,"AMBER","RED")))) -> AMBER | N30: =IF(N11="","",IF($D11="Higher",IF(N11>=$E11,"GREEN",IF(N11>=$F11,"AMBER","RED")),IF(N11<=$E11,"GREEN",IF(N11<=$F11,"AMBER","RED")))) -> AMBER | ... R30: =IF(R11="","",IF($D11="Higher",IF(R11>=$E11,"GREEN",IF(R11>=$F11,"AMBER","RED")),IF(R11<=$E11,"GREEN",IF(R11<=$F11,"AMBER","RED"))))
A31: 8 | B31: =B12 -> Stakeholder Satisfaction | G31: =IF(G12="","",IF($D12="Higher",IF(G12>=$E12,"GREEN",IF(G12>=$F12,"AMBER","RED")),IF(G12<=$E12,"GREEN",IF(G12<=$F12,"AMBER","RED")))) -> RED | H31: =IF(H12="","",IF($D12="Higher",IF(H12>=$E12,"GREEN",IF(H12>=$F12,"AMBER","RED")),IF(H12<=$E12,"GREEN",IF(H12<=$F12,"AMBER","RED")))) -> RED | I31: =IF(I12="","",IF($D12="Higher",IF(I12>=$E12,"GREEN",IF(I12>=$F12,"AMBER","RED")),IF(I12<=$E12,"GREEN",IF(I12<=$F12,"AMBER","RED")))) -> AMBER | J31: =IF(J12="","",IF($D12="Higher",IF(J12>=$E12,"GREEN",IF(J12>=$F12,"AMBER","RED")),IF(J12<=$E12,"GREEN",IF(J12<=$F12,"AMBER","RED")))) -> AMBER | K31: =IF(K12="","",IF($D12="Higher",IF(K12>=$E12,"GREEN",IF(K12>=$F12,"AMBER","RED")),IF(K12<=$E12,"GREEN",IF(K12<=$F12,"AMBER","RED")))) -> AMBER | L31: =IF(L12="","",IF($D12="Higher",IF(L12>=$E12,"GREEN",IF(L12>=$F12,"AMBER","RED")),IF(L12<=$E12,"GREEN",IF(L12<=$F12,"AMBER","RED")))) -> AMBER | M31: =IF(M12="","",IF($D12="Higher",IF(M12>=$E12,"GREEN",IF(M12>=$F12,"AMBER","RED")),IF(M12<=$E12,"GREEN",IF(M12<=$F12,"AMBER","RED")))) -> AMBER | N31: =IF(N12="","",IF($D12="Higher",IF(N12>=$E12,"GREEN",IF(N12>=$F12,"AMBER","RED")),IF(N12<=$E12,"GREEN",IF(N12<=$F12,"AMBER","RED")))) -> GREEN | ... R31: =IF(R12="","",IF($D12="Higher",IF(R12>=$E12,"GREEN",IF(R12>=$F12,"AMBER","RED")),IF(R12<=$E12,"GREEN",IF(R12<=$F12,"AMBER","RED"))))
A32: 9 | B32: =B13 -> Resource Utilization Rate | G32: =IF(G13="","",IF($D13="Higher",IF(G13>=$E13,"GREEN",IF(G13>=$F13,"AMBER","RED")),IF(G13<=$E13,"GREEN",IF(G13<=$F13,"AMBER","RED")))) -> AMBER | H32: =IF(H13="","",IF($D13="Higher",IF(H13>=$E13,"GREEN",IF(H13>=$F13,"AMBER","RED")),IF(H13<=$E13,"GREEN",IF(H13<=$F13,"AMBER","RED")))) -> AMBER | I32: =IF(I13="","",IF($D13="Higher",IF(I13>=$E13,"GREEN",IF(I13>=$F13,"AMBER","RED")),IF(I13<=$E13,"GREEN",IF(I13<=$F13,"AMBER","RED")))) -> AMBER | J32: =IF(J13="","",IF($D13="Higher",IF(J13>=$E13,"GREEN",IF(J13>=$F13,"AMBER","RED")),IF(J13<=$E13,"GREEN",IF(J13<=$F13,"AMBER","RED")))) -> AMBER | K32: =IF(K13="","",IF($D13="Higher",IF(K13>=$E13,"GREEN",IF(K13>=$F13,"AMBER","RED")),IF(K13<=$E13,"GREEN",IF(K13<=$F13,"AMBER","RED")))) -> AMBER | L32: =IF(L13="","",IF($D13="Higher",IF(L13>=$E13,"GREEN",IF(L13>=$F13,"AMBER","RED")),IF(L13<=$E13,"GREEN",IF(L13<=$F13,"AMBER","RED")))) -> AMBER | M32: =IF(M13="","",IF($D13="Higher",IF(M13>=$E13,"GREEN",IF(M13>=$F13,"AMBER","RED")),IF(M13<=$E13,"GREEN",IF(M13<=$F13,"AMBER","RED")))) -> AMBER | N32: =IF(N13="","",IF($D13="Higher",IF(N13>=$E13,"GREEN",IF(N13>=$F13,"AMBER","RED")),IF(N13<=$E13,"GREEN",IF(N13<=$F13,"AMBER","RED")))) -> AMBER | ... R32: =IF(R13="","",IF($D13="Higher",IF(R13>=$E13,"GREEN",IF(R13>=$F13,"AMBER","RED")),IF(R13<=$E13,"GREEN",IF(R13<=$F13,"AMBER","RED"))))
A33: 10 | B33: =B14 -> Project Success Rate | G33: =IF(G14="","",IF($D14="Higher",IF(G14>=$E14,"GREEN",IF(G14>=$F14,"AMBER","RED")),IF(G14<=$E14,"GREEN",IF(G14<=$F14,"AMBER","RED")))) | H33: =IF(H14="","",IF($D14="Higher",IF(H14>=$E14,"GREEN",IF(H14>=$F14,"AMBER","RED")),IF(H14<=$E14,"GREEN",IF(H14<=$F14,"AMBER","RED")))) | I33: =IF(I14="","",IF($D14="Higher",IF(I14>=$E14,"GREEN",IF(I14>=$F14,"AMBER","RED")),IF(I14<=$E14,"GREEN",IF(I14<=$F14,"AMBER","RED")))) | J33: =IF(J14="","",IF($D14="Higher",IF(J14>=$E14,"GREEN",IF(J14>=$F14,"AMBER","RED")),IF(J14<=$E14,"GREEN",IF(J14<=$F14,"AMBER","RED")))) -> GREEN | K33: =IF(K14="","",IF($D14="Higher",IF(K14>=$E14,"GREEN",IF(K14>=$F14,"AMBER","RED")),IF(K14<=$E14,"GREEN",IF(K14<=$F14,"AMBER","RED")))) -> GREEN | L33: =IF(L14="","",IF($D14="Higher",IF(L14>=$E14,"GREEN",IF(L14>=$F14,"AMBER","RED")),IF(L14<=$E14,"GREEN",IF(L14<=$F14,"AMBER","RED")))) -> RED | M33: =IF(M14="","",IF($D14="Higher",IF(M14>=$E14,"GREEN",IF(M14>=$F14,"AMBER","RED")),IF(M14<=$E14,"GREEN",IF(M14<=$F14,"AMBER","RED")))) -> RED | N33: =IF(N14="","",IF($D14="Higher",IF(N14>=$E14,"GREEN",IF(N14>=$F14,"AMBER","RED")),IF(N14<=$E14,"GREEN",IF(N14<=$F14,"AMBER","RED")))) -> RED | ... R33: =IF(R14="","",IF($D14="Higher",IF(R14>=$E14,"GREEN",IF(R14>=$F14,"AMBER","RED")),IF(R14<=$E14,"GREEN",IF(R14<=$F14,"AMBER","RED"))))
A34: 11 | B34: =B15 -> Milestone Completion Rate | G34: =IF(G15="","",IF($D15="Higher",IF(G15>=$E15,"GREEN",IF(G15>=$F15,"AMBER","RED")),IF(G15<=$E15,"GREEN",IF(G15<=$F15,"AMBER","RED")))) -> RED | H34: =IF(H15="","",IF($D15="Higher",IF(H15>=$E15,"GREEN",IF(H15>=$F15,"AMBER","RED")),IF(H15<=$E15,"GREEN",IF(H15<=$F15,"AMBER","RED")))) -> RED | I34: =IF(I15="","",IF($D15="Higher",IF(I15>=$E15,"GREEN",IF(I15>=$F15,"AMBER","RED")),IF(I15<=$E15,"GREEN",IF(I15<=$F15,"AMBER","RED")))) -> GREEN | J34: =IF(J15="","",IF($D15="Higher",IF(J15>=$E15,"GREEN",IF(J15>=$F15,"AMBER","RED")),IF(J15<=$E15,"GREEN",IF(J15<=$F15,"AMBER","RED")))) -> AMBER | K34: =IF(K15="","",IF($D15="Higher",IF(K15>=$E15,"GREEN",IF(K15>=$F15,"AMBER","RED")),IF(K15<=$E15,"GREEN",IF(K15<=$F15,"AMBER","RED")))) -> RED | L34: =IF(L15="","",IF($D15="Higher",IF(L15>=$E15,"GREEN",IF(L15>=$F15,"AMBER","RED")),IF(L15<=$E15,"GREEN",IF(L15<=$F15,"AMBER","RED")))) -> RED | M34: =IF(M15="","",IF($D15="Higher",IF(M15>=$E15,"GREEN",IF(M15>=$F15,"AMBER","RED")),IF(M15<=$E15,"GREEN",IF(M15<=$F15,"AMBER","RED")))) -> RED | N34: =IF(N15="","",IF($D15="Higher",IF(N15>=$E15,"GREEN",IF(N15>=$F15,"AMBER","RED")),IF(N15<=$E15,"GREEN",IF(N15<=$F15,"AMBER","RED")))) -> RED | ... R34: =IF(R15="","",IF($D15="Higher",IF(R15>=$E15,"GREEN",IF(R15>=$F15,"AMBER","RED")),IF(R15<=$E15,"GREEN",IF(R15<=$F15,"AMBER","RED"))))
A35: 12 | B35: =B16 -> Project Quality Index | G35: =IF(G16="","",IF($D16="Higher",IF(G16>=$E16,"GREEN",IF(G16>=$F16,"AMBER","RED")),IF(G16<=$E16,"GREEN",IF(G16<=$F16,"AMBER","RED")))) -> GREEN | H35: =IF(H16="","",IF($D16="Higher",IF(H16>=$E16,"GREEN",IF(H16>=$F16,"AMBER","RED")),IF(H16<=$E16,"GREEN",IF(H16<=$F16,"AMBER","RED")))) -> RED | I35: =IF(I16="","",IF($D16="Higher",IF(I16>=$E16,"GREEN",IF(I16>=$F16,"AMBER","RED")),IF(I16<=$E16,"GREEN",IF(I16<=$F16,"AMBER","RED")))) -> GREEN | J35: =IF(J16="","",IF($D16="Higher",IF(J16>=$E16,"GREEN",IF(J16>=$F16,"AMBER","RED")),IF(J16<=$E16,"GREEN",IF(J16<=$F16,"AMBER","RED")))) -> RED | K35: =IF(K16="","",IF($D16="Higher",IF(K16>=$E16,"GREEN",IF(K16>=$F16,"AMBER","RED")),IF(K16<=$E16,"GREEN",IF(K16<=$F16,"AMBER","RED")))) -> RED | L35: =IF(L16="","",IF($D16="Higher",IF(L16>=$E16,"GREEN",IF(L16>=$F16,"AMBER","RED")),IF(L16<=$E16,"GREEN",IF(L16<=$F16,"AMBER","RED")))) -> GREEN | M35: =IF(M16="","",IF($D16="Higher",IF(M16>=$E16,"GREEN",IF(M16>=$F16,"AMBER","RED")),IF(M16<=$E16,"GREEN",IF(M16<=$F16,"AMBER","RED")))) -> RED | N35: =IF(N16="","",IF($D16="Higher",IF(N16>=$E16,"GREEN",IF(N16>=$F16,"AMBER","RED")),IF(N16<=$E16,"GREEN",IF(N16<=$F16,"AMBER","RED")))) -> GREEN | ... R35: =IF(R16="","",IF($D16="Higher",IF(R16>=$E16,"GREEN",IF(R16>=$F16,"AMBER","RED")),IF(R16<=$E16,"GREEN",IF(R16<=$F16,"AMBER","RED"))))
... A39: 16 | B39: =B20 -> Continuous Improvement Initiatives | G39: =IF(G20="","",IF($D20="Higher",IF(G20>=$E20,"GREEN",IF(G20>=$F20,"AMBER","RED")),IF(G20<=$E20,"GREEN",IF(G20<=$F20,"AMBER","RED")))) -> AMBER | H39: =IF(H20="","",IF($D20="Higher",IF(H20>=$E20,"GREEN",IF(H20>=$F20,"AMBER","RED")),IF(H20<=$E20,"GREEN",IF(H20<=$F20,"AMBER","RED")))) -> GREEN | I39: =IF(I20="","",IF($D20="Higher",IF(I20>=$E20,"GREEN",IF(I20>=$F20,"AMBER","RED")),IF(I20<=$E20,"GREEN",IF(I20<=$F20,"AMBER","RED")))) -> RED | J39: =IF(J20="","",IF($D20="Higher",IF(J20>=$E20,"GREEN",IF(J20>=$F20,"AMBER","RED")),IF(J20<=$E20,"GREEN",IF(J20<=$F20,"AMBER","RED")))) -> GREEN | K39: =IF(K20="","",IF($D20="Higher",IF(K20>=$E20,"GREEN",IF(K20>=$F20,"AMBER","RED")),IF(K20<=$E20,"GREEN",IF(K20<=$F20,"AMBER","RED")))) -> AMBER | L39: =IF(L20="","",IF($D20="Higher",IF(L20>=$E20,"GREEN",IF(L20>=$F20,"AMBER","RED")),IF(L20<=$E20,"GREEN",IF(L20<=$F20,"AMBER","RED")))) -> AMBER | M39: =IF(M20="","",IF($D20="Higher",IF(M20>=$E20,"GREEN",IF(M20>=$F20,"AMBER","RED")),IF(M20<=$E20,"GREEN",IF(M20<=$F20,"AMBER","RED")))) -> GREEN | N39: =IF(N20="","",IF($D20="Higher",IF(N20>=$E20,"GREEN",IF(N20>=$F20,"AMBER","RED")),IF(N20<=$E20,"GREEN",IF(N20<=$F20,"AMBER","RED")))) -> AMBER | ... R39: =IF(R20="","",IF($D20="Higher",IF(R20>=$E20,"GREEN",IF(R20>=$F20,"AMBER","RED")),IF(R20<=$E20,"GREEN",IF(R20<=$F20,"AMBER","RED"))))
B41: KPIs GREEN | G41: =COUNTIF(G24:G39,"GREEN") -> 2 | H41: =COUNTIF(H24:H39,"GREEN") -> 3 | I41: =COUNTIF(I24:I39,"GREEN") -> 5 | J41: =COUNTIF(J24:J39,"GREEN") -> 8 | K41: =COUNTIF(K24:K39,"GREEN") -> 5 | L41: =COUNTIF(L24:L39,"GREEN") -> 6 | M41: =COUNTIF(M24:M39,"GREEN") -> 5 | N41: =COUNTIF(N24:N39,"GREEN") -> 4 | ... R41: =COUNTIF(R24:R39,"GREEN") -> 0
B42: KPIs AMBER | G42: =COUNTIF(G24:G39,"AMBER") -> 7 | H42: =COUNTIF(H24:H39,"AMBER") -> 5 | I42: =COUNTIF(I24:I39,"AMBER") -> 7 | J42: =COUNTIF(J24:J39,"AMBER") -> 7 | K42: =COUNTIF(K24:K39,"AMBER") -> 9 | L42: =COUNTIF(L24:L39,"AMBER") -> 6 | M42: =COUNTIF(M24:M39,"AMBER") -> 6 | N42: =COUNTIF(N24:N39,"AMBER") -> 9 | ... R42: =COUNTIF(R24:R39,"AMBER") -> 0
B43: KPIs RED | G43: =COUNTIF(G24:G39,"RED") -> 3 | H43: =COUNTIF(H24:H39,"RED") -> 4 | I43: =COUNTIF(I24:I39,"RED") -> 1 | J43: =COUNTIF(J24:J39,"RED") -> 1 | K43: =COUNTIF(K24:K39,"RED") -> 2 | L43: =COUNTIF(L24:L39,"RED") -> 4 | M43: =COUNTIF(M24:M39,"RED") -> 5 | N43: =COUNTIF(N24:N39,"RED") -> 3 | ... R43: =COUNTIF(R24:R39,"RED") -> 0
B44: % KPIs on target | G44: =IF(SUM(G41:G43)=0,"",G41/SUM(G41:G43)) -> 0.16666667 | H44: =IF(SUM(H41:H43)=0,"",H41/SUM(H41:H43)) -> 0.25 | I44: =IF(SUM(I41:I43)=0,"",I41/SUM(I41:I43)) -> 0.38461538 | J44: =IF(SUM(J41:J43)=0,"",J41/SUM(J41:J43)) -> 0.5 | K44: =IF(SUM(K41:K43)=0,"",K41/SUM(K41:K43)) -> 0.3125 | L44: =IF(SUM(L41:L43)=0,"",L41/SUM(L41:L43)) -> 0.375 | M44: =IF(SUM(M41:M43)=0,"",M41/SUM(M41:M43)) -> 0.3125 | N44: =IF(SUM(N41:N43)=0,"",N41/SUM(N41:N43)) -> 0.25 | ... R44: =IF(SUM(R41:R43)=0,"",R41/SUM(R41:R43))

Sheet Trends
A1: KPI Trend Charts
A2: Bars = monthly actual · Line = target. Charts update automatically from KPI_Tracking.
A148: Rows below hold the target line series used by the charts – do not delete.
A149: Target series (chart helper – do not delete)
A150: =KPI_Tracking!B5 -> Project Schedule Variance (SV%) | B150: =KPI_Tracking!$E5 -> 0 | C150: =KPI_Tracking!$E5 -> 0 | D150: =KPI_Tracking!$E5 -> 0 | E150: =KPI_Tracking!$E5 -> 0 | F150: =KPI_Tracking!$E5 -> 0 | G150: =KPI_Tracking!$E5 -> 0 | H150: =KPI_Tracking!$E5 -> 0 | I150: =KPI_Tracking!$E5 -> 0 | ... M150: =KPI_Tracking!$E5 -> 0
A151: =KPI_Tracking!B6 -> Project Cost Variance (CV%) | B151: =KPI_Tracking!$E6 -> 0 | C151: =KPI_Tracking!$E6 -> 0 | D151: =KPI_Tracking!$E6 -> 0 | E151: =KPI_Tracking!$E6 -> 0 | F151: =KPI_Tracking!$E6 -> 0 | G151: =KPI_Tracking!$E6 -> 0 | H151: =KPI_Tracking!$E6 -> 0 | I151: =KPI_Tracking!$E6 -> 0 | ... M151: =KPI_Tracking!$E6 -> 0
A152: =KPI_Tracking!B7 -> Budget Utilization | B152: =KPI_Tracking!$E7 -> 1 | C152: =KPI_Tracking!$E7 -> 1 | D152: =KPI_Tracking!$E7 -> 1 | E152: =KPI_Tracking!$E7 -> 1 | F152: =KPI_Tracking!$E7 -> 1 | G152: =KPI_Tracking!$E7 -> 1 | H152: =KPI_Tracking!$E7 -> 1 | I152: =KPI_Tracking!$E7 -> 1 | ... M152: =KPI_Tracking!$E7 -> 1
A153: =KPI_Tracking!B8 -> On-Time Project Delivery | B153: =KPI_Tracking!$E8 -> 0.9 | C153: =KPI_Tracking!$E8 -> 0.9 | D153: =KPI_Tracking!$E8 -> 0.9 | E153: =KPI_Tracking!$E8 -> 0.9 | F153: =KPI_Tracking!$E8 -> 0.9 | G153: =KPI_Tracking!$E8 -> 0.9 | H153: =KPI_Tracking!$E8 -> 0.9 | I153: =KPI_Tracking!$E8 -> 0.9 | ... M153: =KPI_Tracking!$E8 -> 0.9
A154: =KPI_Tracking!B9 -> Scope Change Frequency | B154: =KPI_Tracking!$E9 -> 0.5 | C154: =KPI_Tracking!$E9 -> 0.5 | D154: =KPI_Tracking!$E9 -> 0.5 | E154: =KPI_Tracking!$E9 -> 0.5 | F154: =KPI_Tracking!$E9 -> 0.5 | G154: =KPI_Tracking!$E9 -> 0.5 | H154: =KPI_Tracking!$E9 -> 0.5 | I154: =KPI_Tracking!$E9 -> 0.5 | ... M154: =KPI_Tracking!$E9 -> 0.5
A155: =KPI_Tracking!B10 -> Risk Mitigation Effectiveness | B155: =KPI_Tracking!$E10 -> 0.85 | C155: =KPI_Tracking!$E10 -> 0.85 | D155: =KPI_Tracking!$E10 -> 0.85 | E155: =KPI_Tracking!$E10 -> 0.85 | F155: =KPI_Tracking!$E10 -> 0.85 | G155: =KPI_Tracking!$E10 -> 0.85 | H155: =KPI_Tracking!$E10 -> 0.85 | I155: =KPI_Tracking!$E10 -> 0.85 | ... M155: =KPI_Tracking!$E10 -> 0.85
A156: =KPI_Tracking!B11 -> Issue Resolution Time | B156: =KPI_Tracking!$E11 -> 7 | C156: =KPI_Tracking!$E11 -> 7 | D156: =KPI_Tracking!$E11 -> 7 | E156: =KPI_Tracking!$E11 -> 7 | F156: =KPI_Tracking!$E11 -> 7 | G156: =KPI_Tracking!$E11 -> 7 | H156: =KPI_Tracking!$E11 -> 7 | I156: =KPI_Tracking!$E11 -> 7 | ... M156: =KPI_Tracking!$E11 -> 7
A157: =KPI_Tracking!B12 -> Stakeholder Satisfaction | B157: =KPI_Tracking!$E12 -> 4 | C157: =KPI_Tracking!$E12 -> 4 | D157: =KPI_Tracking!$E12 -> 4 | E157: =KPI_Tracking!$E12 -> 4 | F157: =KPI_Tracking!$E12 -> 4 | G157: =KPI_Tracking!$E12 -> 4 | H157: =KPI_Tracking!$E12 -> 4 | I157: =KPI_Tracking!$E12 -> 4 | ... M157: =KPI_Tracking!$E12 -> 4
A158: =KPI_Tracking!B13 -> Resource Utilization Rate | B158: =KPI_Tracking!$E13 -> 0.85 | C158: =KPI_Tracking!$E13 -> 0.85 | D158: =KPI_Tracking!$E13 -> 0.85 | E158: =KPI_Tracking!$E13 -> 0.85 | F158: =KPI_Tracking!$E13 -> 0.85 | G158: =KPI_Tracking!$E13 -> 0.85 | H158: =KPI_Tracking!$E13 -> 0.85 | I158: =KPI_Tracking!$E13 -> 0.85 | ... M158: =KPI_Tracking!$E13 -> 0.85
A159: =KPI_Tracking!B14 -> Project Success Rate | B159: =KPI_Tracking!$E14 -> 0.8 | C159: =KPI_Tracking!$E14 -> 0.8 | D159: =KPI_Tracking!$E14 -> 0.8 | E159: =KPI_Tracking!$E14 -> 0.8 | F159: =KPI_Tracking!$E14 -> 0.8 | G159: =KPI_Tracking!$E14 -> 0.8 | H159: =KPI_Tracking!$E14 -> 0.8 | I159: =KPI_Tracking!$E14 -> 0.8 | ... M159: =KPI_Tracking!$E14 -> 0.8
A160: =KPI_Tracking!B15 -> Milestone Completion Rate | B160: =KPI_Tracking!$E15 -> 0.9 | C160: =KPI_Tracking!$E15 -> 0.9 | D160: =KPI_Tracking!$E15 -> 0.9 | E160: =KPI_Tracking!$E15 -> 0.9 | F160: =KPI_Tracking!$E15 -> 0.9 | G160: =KPI_Tracking!$E15 -> 0.9 | H160: =KPI_Tracking!$E15 -> 0.9 | I160: =KPI_Tracking!$E15 -> 0.9 | ... M160: =KPI_Tracking!$E15 -> 0.9
A161: =KPI_Tracking!B16 -> Project Quality Index | B161: =KPI_Tracking!$E16 -> 0.95 | C161: =KPI_Tracking!$E16 -> 0.95 | D161: =KPI_Tracking!$E16 -> 0.95 | E161: =KPI_Tracking!$E16 -> 0.95 | F161: =KPI_Tracking!$E16 -> 0.95 | G161: =KPI_Tracking!$E16 -> 0.95 | H161: =KPI_Tracking!$E16 -> 0.95 | I161: =KPI_Tracking!$E16 -> 0.95 | ... M161: =KPI_Tracking!$E16 -> 0.95
... A165: =KPI_Tracking!B20 -> Continuous Improvement Initiatives | B165: =KPI_Tracking!$E20 -> 2 | C165: =KPI_Tracking!$E20 -> 2 | D165: =KPI_Tracking!$E20 -> 2 | E165: =KPI_Tracking!$E20 -> 2 | F165: =KPI_Tracking!$E20 -> 2 | G165: =KPI_Tracking!$E20 -> 2 | H165: =KPI_Tracking!$E20 -> 2 | I165: =KPI_Tracking!$E20 -> 2 | ... M165: =KPI_Tracking!$E20 -> 2

Sheet KPI_Targets
A1: KPI Targets & Definitions
A2: Set the TARGET and AMBER LIMIT per KPI (yellow). Direction: Higher = bigger is better, Lower = smaller is better. Any change → log it in Target_Revisions.
A4: # | B4: KPI | C4: What it measures | D4: Calculation used in this workbook | E4: Unit | F4: Direction | G4: Target (Green) | H4: Amber limit | I4: Frequency | J4: Data source sheet | K4: Basis | L4: Owner | M4: Notes / watch-outs
A5: 1 | B5: Project Schedule Variance (SV%) | C5: Deviation between planned and actual project progress/timeline. | D5: (EV − PV) ÷ PV for the month, all projects. Negative = behind schedule. SPI = EV ÷ PV shown in Cost_Schedule. | E5: % | F5: Higher | G5: 0 | H5: -0.05 | I5: Monthly | J5: Cost_Schedule | K5: Month | L5: A. Camara | M5: Earned-value based – measures work done vs plan, not just dates.
A6: 2 | B6: Project Cost Variance (CV%) | C6: Difference between planned (earned) and actual project costs. | D6: (EV − AC) ÷ EV for the month. Negative = over cost. CPI = EV ÷ AC shown in Cost_Schedule. | E6: % | F6: Higher | G6: 0 | H6: -0.05 | I6: Monthly | J6: Cost_Schedule | K6: Month | L6: M. Diallo | M6: Compares cost against value earned – the honest cost KPI.
A7: 3 | B7: Budget Utilization | C7: How efficiently approved budgets are being consumed. | D7: Actual spend (AC) ÷ approved period budget. | E7: % | F7: Lower | G7: 1 | H7: 1.05 | I7: Monthly | J7: Cost_Schedule | K7: Month | L7: S. Keita | M7: Read with CV%: 100% spend on 70% of work is NOT good. Big under-spend usually means slippage.
A8: 4 | B8: On-Time Project Delivery | C8: % of projects delivered within schedule. | D8: Completed projects with Actual finish ≤ Baseline finish ÷ Completed projects (YTD). | E8: % | F8: Higher | G8: 0.9 | H8: 0.8 | I8: Monthly | J8: Projects | K8: YTD | L8: F. Bah | M8: Small sample sizes swing this – check the count of completed projects.
A9: 5 | B9: Scope Change Frequency | C9: How often project scope changes occur. | D9: Scope change requests submitted in month ÷ active projects in month. | E9: CRs / project | F9: Lower | G9: 0.5 | H9: 1 | I9: Monthly | J9: Change_Log + Projects | K9: Month | L9: I. Sylla | M9: Normalised per active project so a bigger portfolio isn't penalised.
A10: 6 | B10: Risk Mitigation Effectiveness | C10: How well project risks are managed and reduced. | D10: Risks closed YTD that did NOT materialise ÷ all risks closed YTD. | E10: % | F10: Higher | G10: 0.85 | H10: 0.7 | I10: Monthly | J10: Risk_Log | K10: YTD | L10: K. Conde | M10: Residual score columns in Risk_Log show the reduction achieved per risk.
A11: 7 | B11: Issue Resolution Time | C11: How quickly project issues are resolved. | D11: Average days from Date raised to Date resolved, issues resolved in month. | E11: days | F11: Lower | G11: 7 | H11: 14 | I11: Monthly | J11: Issue_Log | K11: Month | L11: O. Traore | M11: Ageing of still-open issues is visible in Issue_Log (days open).
A12: 8 | B12: Stakeholder Satisfaction | C12: Stakeholder perception of project outcomes. | D12: Average overall survey score (1–5) of surveys dated in month. | E12: score /5 | F12: Higher | G12: 4 | H12: 3.5 | I12: Monthly / per survey | J12: Stakeholder_Survey | K12: Month | L12: B. Toure | M12: Overall = average of 4 criteria. Track response count too – 2 surveys is not a trend.
A13: 9 | B13: Resource Utilization Rate | C13: Efficiency of project resource allocation. | D13: Hours allocated to project work ÷ hours available, all teams. | E13: % | F13: Higher | G13: 0.85 | H13: 0.75 | I13: Monthly | J13: Resources | K13: Month | L13: A. Camara | M13: Above ~95% for long periods = burnout/no slack. Watch it, don't just maximise it.
A14: 10 | B14: Project Success Rate | C14: % of projects meeting scope, cost and schedule goals. | D14: Completed projects that are On time AND Within budget AND Scope delivered ÷ completed projects (YTD). | E14: % | F14: Higher | G14: 0.8 | H14: 0.65 | I14: Monthly | J14: Projects | K14: YTD | L14: M. Diallo | M14: All three criteria must be met – stricter than On-Time Delivery.
A15: 11 | B15: Milestone Completion Rate | C15: Timely completion of key project milestones. | D15: Milestones due in month completed on/before baseline date ÷ milestones due in month. | E15: % | F15: Higher | G15: 0.9 | H15: 0.8 | I15: Monthly | J15: Milestones | K15: Month | L15: S. Keita | M15: Use baseline dates – re-baselining hides slippage.
A16: 12 | B16: Project Quality Index | C16: Quality of project deliverables. | D16: Deliverables accepted first time (no rework) ÷ deliverables inspected in month. | E16: % | F16: Higher | G16: 0.95 | H16: 0.85 | I16: Monthly | J16: Quality_Log | K16: Month | L16: F. Bah | M16: First-pass yield. Defects & rework hours are logged for root-cause analysis.
... A20: 16 | B20: Continuous Improvement Initiatives | C20: Ongoing improvements in project delivery processes. | D20: Number of improvement initiatives implemented in month. | E20: count | F20: Higher | G20: 2 | H20: 1 | I20: Monthly | J20: CI_Log | K20: Month | L20: B. Toure | M20: Count is the activity; 'Benefit verified' in CI_Log shows whether it actually worked.
B22: RAG rule – Direction = Higher: GREEN if Actual ≥ Target · AMBER if Actual ≥ Amber limit · else RED.
B23: RAG rule – Direction = Lower: GREEN if Actual ≤ Target · AMBER if Actual ≤ Amber limit · else RED.
B24: So for 'Higher' KPIs the amber limit sits BELOW the target; for 'Lower' KPIs it sits ABOVE the target.

Sheet Target_Revisions
A1: Target Revision Log
A2: Every change to a target or amber limit, with the reason and approver – the audit trail for target setting.
A4: Rev # | B4: Date | C4: KPI | D4: Old target | E4: New target | F4: Old amber | G4: New amber | H4: Reason for change | I4: Proposed by | J4: Approved by
A5: =IF(B5="","",ROW()-4) -> 1 | B5: 46027 | C5: On-Time Project Delivery | D5: 0.85 | E5: 0.9 | F5: 0.75 | G5: 0.8 | H5: Annual target setting – raised after 2025 actual of 88%. | I5: A. Camara | J5: B. Toure
A6: =IF(B6="","",ROW()-4) -> 2 | B6: 46114 | C6: Issue Resolution Time | D6: 10 | E6: 7 | F6: 20 | G6: 14 | H6: Issue triage process introduced (CI-003); faster target now achievable. | I6: M. Diallo | J6: B. Toure
A7: =IF(B7="","",ROW()-4)
A8: =IF(B8="","",ROW()-4)
A9: =IF(B9="","",ROW()-4)
A10: =IF(B10="","",ROW()-4)
A11: =IF(B11="","",ROW()-4)
A12: =IF(B12="","",ROW()-4)
A13: =IF(B13="","",ROW()-4)
A14: =IF(B14="","",ROW()-4)
A15: =IF(B15="","",ROW()-4)
A16: =IF(B16="","",ROW()-4)
A17: =IF(B17="","",ROW()-4)
A18: =IF(B18="","",ROW()-4)
... A104: =IF(B104="","",ROW()-4)

Sheet Action_Log
A1: Corrective Action & Change Implementation Log
A2: When a KPI goes AMBER/RED: record the root cause, the action, who/when, and the KPI value before and after. Result is calculated automatically.
E3: Enter KPI values as decimals for % KPIs (e.g. 0.82 = 82%).
A4: Action ID | B4: Date raised | C4: KPI concerned | D4: Project ID (optional) | E4: KPI value before | F4: Problem / root cause | G4: Corrective action / change | H4: Owner | I4: Due date | J4: Status | K4: Date implemented | L4: KPI value after | M4: Result | N4: Due status | O4: Remarks
A5: A-001 | B5: 46056 | C5: Project Schedule Variance (SV%) | D5: P01 | E5: -0.08 | F5: Pushback behind plan – one excavator down 3 weeks | G5: Hire-in excavator + double-shift loading | H5: A. Camara | I5: 46081 | J5: Implemented | K5: 46073 | L5: -0.03 | M5: =IF(OR(C5="",E5="",L5=""),"",IF(INDEX(KPI_Targets!$F$5:$F$20,MATCH(C5,KPI_Targets!$B$5:$B$20,0))="Higher",IF(L5>E5,"Improved",IF(L5=E5,"No change","Worse")),IF(L5<E5,"Improved",IF(L5=E5,"No change","Worse")))) -> Improved | N5: =IF(B5="","",IF(OR(J5="Implemented",J5="Cancelled"),"Closed",IF(AND(I5<>"",I5<TODAY()),"OVERDUE","On track"))) -> Closed
A6: A-002 | B6: 46063 | C6: Issue Resolution Time | E6: 15.5 | F6: Issues waiting for weekly meeting to be actioned | G6: Daily issue triage at pre-start (CI-003) | H6: M. Diallo | I6: 46096 | J6: Implemented | K6: 46091 | L6: 8.2 | M6: =IF(OR(C6="",E6="",L6=""),"",IF(INDEX(KPI_Targets!$F$5:$F$20,MATCH(C6,KPI_Targets!$B$5:$B$20,0))="Higher",IF(L6>E6,"Improved",IF(L6=E6,"No change","Worse")),IF(L6<E6,"Improved",IF(L6=E6,"No change","Worse")))) -> Improved | N6: =IF(B6="","",IF(OR(J6="Implemented",J6="Cancelled"),"Closed",IF(AND(I6<>"",I6<TODAY()),"OVERDUE","On track"))) -> Closed
A7: A-003 | B7: 46086 | C7: Change Request Approval Time | E7: 9.5 | F7: CRs sit with sponsor without deadline | G7: 48h review SLA + standard CR form (CI-002) | H7: B. Toure | I7: 46112 | J7: Implemented | K7: 46106 | L7: 6 | M7: =IF(OR(C7="",E7="",L7=""),"",IF(INDEX(KPI_Targets!$F$5:$F$20,MATCH(C7,KPI_Targets!$B$5:$B$20,0))="Higher",IF(L7>E7,"Improved",IF(L7=E7,"No change","Worse")),IF(L7<E7,"Improved",IF(L7=E7,"No change","Worse")))) -> Improved | N7: =IF(B7="","",IF(OR(J7="Implemented",J7="Cancelled"),"Closed",IF(AND(I7<>"",I7<TODAY()),"OVERDUE","On track"))) -> Closed
A8: A-004 | B8: 46120 | C8: Project Cost Variance (CV%) | D8: P05 | E8: -0.07 | F8: Steel price escalation not in budget | G8: Re-tender steel package; apply rise-and-fall | H8: I. Sylla | I8: 46157 | J8: Implemented | K8: 46154 | L8: -0.05 | M8: =IF(OR(C8="",E8="",L8=""),"",IF(INDEX(KPI_Targets!$F$5:$F$20,MATCH(C8,KPI_Targets!$B$5:$B$20,0))="Higher",IF(L8>E8,"Improved",IF(L8=E8,"No change","Worse")),IF(L8<E8,"Improved",IF(L8=E8,"No change","Worse")))) -> Improved | N8: =IF(B8="","",IF(OR(J8="Implemented",J8="Cancelled"),"Closed",IF(AND(I8<>"",I8<TODAY()),"OVERDUE","On track"))) -> Closed
A9: A-005 | B9: 46148 | C9: Project Quality Index | E9: 0.8 | F9: Concrete pours rejected – slump & cover | G9: Pre-pour QA checklist and supplier briefing | H9: S. Keita | I9: 46172 | J9: Implemented | K9: 46175 | L9: 0.9 | M9: =IF(OR(C9="",E9="",L9=""),"",IF(INDEX(KPI_Targets!$F$5:$F$20,MATCH(C9,KPI_Targets!$B$5:$B$20,0))="Higher",IF(L9>E9,"Improved",IF(L9=E9,"No change","Worse")),IF(L9<E9,"Improved",IF(L9=E9,"No change","Worse")))) -> Improved | N9: =IF(B9="","",IF(OR(J9="Implemented",J9="Cancelled"),"Closed",IF(AND(I9<>"",I9<TODAY()),"OVERDUE","On track"))) -> Closed
A10: A-006 | B10: 46177 | C10: Scope Change Frequency | E10: 1.1 | F10: Client adding scope informally on site | G10: Scope freeze gate + all requests via CR form | H10: K. Conde | I10: 46218 | J10: Implemented | K10: 46213 | L10: 0.6 | M10: =IF(OR(C10="",E10="",L10=""),"",IF(INDEX(KPI_Targets!$F$5:$F$20,MATCH(C10,KPI_Targets!$B$5:$B$20,0))="Higher",IF(L10>E10,"Improved",IF(L10=E10,"No change","Worse")),IF(L10<E10,"Improved",IF(L10=E10,"No change","Worse")))) -> Improved | N10: =IF(B10="","",IF(OR(J10="Implemented",J10="Cancelled"),"Closed",IF(AND(I10<>"",I10<TODAY()),"OVERDUE","On track"))) -> Closed
A11: A-007 | B11: 46239 | C11: Milestone Completion Rate | D11: P07 | E11: 0.75 | F11: Pump delivery late – milestones slipping | G11: Expedite with supplier, re-sequence install | H11: A. Camara | I11: 46280 | J11: Implemented | K11: 46285 | L11: 0.83 | M11: =IF(OR(C11="",E11="",L11=""),"",IF(INDEX(KPI_Targets!$F$5:$F$20,MATCH(C11,KPI_Targets!$B$5:$B$20,0))="Higher",IF(L11>E11,"Improved",IF(L11=E11,"No change","Worse")),IF(L11<E11,"Improved",IF(L11=E11,"No change","Worse")))) -> Improved | N11: =IF(B11="","",IF(OR(J11="Implemented",J11="Cancelled"),"Closed",IF(AND(I11<>"",I11<TODAY()),"OVERDUE","On track"))) -> Closed
A12: A-008 | B12: 46272 | C12: Team Productivity Index | E12: 0.91 | F12: Drill rig waiting on survey pickups | G12: Dedicated surveyor for D&B on day shift | H12: F. Bah | I12: 46310 | J12: In progress | M12: =IF(OR(C12="",E12="",L12=""),"",IF(INDEX(KPI_Targets!$F$5:$F$20,MATCH(C12,KPI_Targets!$B$5:$B$20,0))="Higher",IF(L12>E12,"Improved",IF(L12=E12,"No change","Worse")),IF(L12<E12,"Improved",IF(L12=E12,"No change","Worse")))) | N12: =IF(B12="","",IF(OR(J12="Implemented",J12="Cancelled"),"Closed",IF(AND(I12<>"",I12<TODAY()),"OVERDUE","On track"))) -> OVERDUE
A13: A-009 | B13: 46301 | C13: Project Cost Variance (CV%) | D13: P07 | E13: -0.06 | F13: Overtime on dewatering install | G13: Review crew size and roster | H13: A. Camara | I13: 46315 | J13: Open | M13: =IF(OR(C13="",E13="",L13=""),"",IF(INDEX(KPI_Targets!$F$5:$F$20,MATCH(C13,KPI_Targets!$B$5:$B$20,0))="Higher",IF(L13>E13,"Improved",IF(L13=E13,"No change","Worse")),IF(L13<E13,"Improved",IF(L13=E13,"No change","Worse")))) | N13: =IF(B13="","",IF(OR(J13="Implemented",J13="Cancelled"),"Closed",IF(AND(I13<>"",I13<TODAY()),"OVERDUE","On track"))) -> OVERDUE
A14: A-010 | B14: 46303 | C14: Resource Utilization Rate | E14: 0.78 | F14: Maintenance team low booked hours | G14: Assign planned work orders to idle hours | H14: S. Keita | I14: 46341 | J14: Open | M14: =IF(OR(C14="",E14="",L14=""),"",IF(INDEX(KPI_Targets!$F$5:$F$20,MATCH(C14,KPI_Targets!$B$5:$B$20,0))="Higher",IF(L14>E14,"Improved",IF(L14=E14,"No change","Worse")),IF(L14<E14,"Improved",IF(L14=E14,"No change","Worse")))) | N14: =IF(B14="","",IF(OR(J14="Implemented",J14="Cancelled"),"Closed",IF(AND(I14<>"",I14<TODAY()),"OVERDUE","On track"))) -> On track
M15: =IF(OR(C15="",E15="",L15=""),"",IF(INDEX(KPI_Targets!$F$5:$F$20,MATCH(C15,KPI_Targets!$B$5:$B$20,0))="Higher",IF(L15>E15,"Improved",IF(L15=E15,"No change","Worse")),IF(L15<E15,"Improved",IF(L15=E15,"No change","Worse")))) | N15: =IF(B15="","",IF(OR(J15="Implemented",J15="Cancelled"),"Closed",IF(AND(I15<>"",I15<TODAY()),"OVERDUE","On track")))
M16: =IF(OR(C16="",E16="",L16=""),"",IF(INDEX(KPI_Targets!$F$5:$F$20,MATCH(C16,KPI_Targets!$B$5:$B$20,0))="Higher",IF(L16>E16,"Improved",IF(L16=E16,"No change","Worse")),IF(L16<E16,"Improved",IF(L16=E16,"No change","Worse")))) | N16: =IF(B16="","",IF(OR(J16="Implemented",J16="Cancelled"),"Closed",IF(AND(I16<>"",I16<TODAY()),"OVERDUE","On track")))
M17: =IF(OR(C17="",E17="",L17=""),"",IF(INDEX(KPI_Targets!$F$5:$F$20,MATCH(C17,KPI_Targets!$B$5:$B$20,0))="Higher",IF(L17>E17,"Improved",IF(L17=E17,"No change","Worse")),IF(L17<E17,"Improved",IF(L17=E17,"No change","Worse")))) | N17: =IF(B17="","",IF(OR(J17="Implemented",J17="Cancelled"),"Closed",IF(AND(I17<>"",I17<TODAY()),"OVERDUE","On track")))
M18: =IF(OR(C18="",E18="",L18=""),"",IF(INDEX(KPI_Targets!$F$5:$F$20,MATCH(C18,KPI_Targets!$B$5:$B$20,0))="Higher",IF(L18>E18,"Improved",IF(L18=E18,"No change","Worse")),IF(L18<E18,"Improved",IF(L18=E18,"No change","Worse")))) | N18: =IF(B18="","",IF(OR(J18="Implemented",J18="Cancelled"),"Closed",IF(AND(I18<>"",I18<TODAY()),"OVERDUE","On track")))
M19: =IF(OR(C19="",E19="",L19=""),"",IF(INDEX(KPI_Targets!$F$5:$F$20,MATCH(C19,KPI_Targets!$B$5:$B$20,0))="Higher",IF(L19>E19,"Improved",IF(L19=E19,"No change","Worse")),IF(L19<E19,"Improved",IF(L19=E19,"No change","Worse")))) | N19: =IF(B19="","",IF(OR(J19="Implemented",J19="Cancelled"),"Closed",IF(AND(I19<>"",I19<TODAY()),"OVERDUE","On track")))
M20: =IF(OR(C20="",E20="",L20=""),"",IF(INDEX(KPI_Targets!$F$5:$F$20,MATCH(C20,KPI_Targets!$B$5:$B$20,0))="Higher",IF(L20>E20,"Improved",IF(L20=E20,"No change","Worse")),IF(L20<E20,"Improved",IF(L20=E20,"No change","Worse")))) | N20: =IF(B20="","",IF(OR(J20="Implemented",J20="Cancelled"),"Closed",IF(AND(I20<>"",I20<TODAY()),"OVERDUE","On track")))
M21: =IF(OR(C21="",E21="",L21=""),"",IF(INDEX(KPI_Targets!$F$5:$F$20,MATCH(C21,KPI_Targets!$B$5:$B$20,0))="Higher",IF(L21>E21,"Improved",IF(L21=E21,"No change","Worse")),IF(L21<E21,"Improved",IF(L21=E21,"No change","Worse")))) | N21: =IF(B21="","",IF(OR(J21="Implemented",J21="Cancelled"),"Closed",IF(AND(I21<>"",I21<TODAY()),"OVERDUE","On track")))
M22: =IF(OR(C22="",E22="",L22=""),"",IF(INDEX(KPI_Targets!$F$5:$F$20,MATCH(C22,KPI_Targets!$B$5:$B$20,0))="Higher",IF(L22>E22,"Improved",IF(L22=E22,"No change","Worse")),IF(L22<E22,"Improved",IF(L22=E22,"No change","Worse")))) | N22: =IF(B22="","",IF(OR(J22="Implemented",J22="Cancelled"),"Closed",IF(AND(I22<>"",I22<TODAY()),"OVERDUE","On track")))
M23: =IF(OR(C23="",E23="",L23=""),"",IF(INDEX(KPI_Targets!$F$5:$F$20,MATCH(C23,KPI_Targets!$B$5:$B$20,0))="Higher",IF(L23>E23,"Improved",IF(L23=E23,"No change","Worse")),IF(L23<E23,"Improved",IF(L23=E23,"No change","Worse")))) | N23: =IF(B23="","",IF(OR(J23="Implemented",J23="Cancelled"),"Closed",IF(AND(I23<>"",I23<TODAY()),"OVERDUE","On track")))
M24: =IF(OR(C24="",E24="",L24=""),"",IF(INDEX(KPI_Targets!$F$5:$F$20,MATCH(C24,KPI_Targets!$B$5:$B$20,0))="Higher",IF(L24>E24,"Improved",IF(L24=E24,"No change","Worse")),IF(L24<E24,"Improved",IF(L24=E24,"No change","Worse")))) | N24: =IF(B24="","",IF(OR(J24="Implemented",J24="Cancelled"),"Closed",IF(AND(I24<>"",I24<TODAY()),"OVERDUE","On track")))
M25: =IF(OR(C25="",E25="",L25=""),"",IF(INDEX(KPI_Targets!$F$5:$F$20,MATCH(C25,KPI_Targets!$B$5:$B$20,0))="Higher",IF(L25>E25,"Improved",IF(L25=E25,"No change","Worse")),IF(L25<E25,"Improved",IF(L25=E25,"No change","Worse")))) | N25: =IF(B25="","",IF(OR(J25="Implemented",J25="Cancelled"),"Closed",IF(AND(I25<>"",I25<TODAY()),"OVERDUE","On track")))
M26: =IF(OR(C26="",E26="",L26=""),"",IF(INDEX(KPI_Targets!$F$5:$F$20,MATCH(C26,KPI_Targets!$B$5:$B$20,0))="Higher",IF(L26>E26,"Improved",IF(L26=E26,"No change","Worse")),IF(L26<E26,"Improved",IF(L26=E26,"No change","Worse")))) | N26: =IF(B26="","",IF(OR(J26="Implemented",J26="Cancelled"),"Closed",IF(AND(I26<>"",I26<TODAY()),"OVERDUE","On track")))
... M504: =IF(OR(C504="",E504="",L504=""),"",IF(INDEX(KPI_Targets!$F$5:$F$20,MATCH(C504,KPI_Targets!$B$5:$B$20,0))="Higher",IF(L504>E504,"Improved",IF(L504=E504,"No change","Worse")),IF(L504<E504,"Improved",IF(L504=E504,"No change","Worse")))) | N504: =IF(B504="","",IF(OR(J504="Implemented",J504="Cancelled"),"Closed",IF(AND(I504<>"",I504<TODAY()),"OVERDUE","On track")))

Sheet Projects
A1: Project Register
A2: One row per project. Status, baseline vs actual finish and final cost drive On-Time Delivery and Project Success Rate.
A4: Project ID | B4: Project name | C4: Area / client | D4: Project manager | E4: Sponsor | F4: Start date | G4: Baseline finish | H4: Forecast / actual finish | I4: Status | J4: Budget at completion (BAC) | K4: Forecast / final cost (EAC) | L4: Scope fully delivered? | M4: Deliverables accepted? | N4: On time? | O4: Within budget? | P4: Successful? | Q4: Days late (+) / early (−) | R4: Cost variance at completion | S4: Remarks
A5: P01 | B5: Pit 2 Stage 3 Pushback | C5: Mining | D5: A. Camara | E5: B. Toure | F5: 45962 | G5: 46203 | H5: 46224 | I5: Completed | J5: 4800000 | K5: 5100000 | L5: Yes | M5: Yes | N5: =IF(OR(A5="",I5<>"Completed"),"",IF(H5<=G5,"Yes","No")) -> No | O5: =IF(OR(A5="",I5<>"Completed"),"",IF(K5<=J5*(1+Settings!$B$7),"Yes","No")) -> No | P5: =IF(OR(A5="",I5<>"Completed"),"",IF(AND(N5="Yes",O5="Yes",L5="Yes"),"Yes","No")) -> No | Q5: =IF(OR(G5="",H5=""),"",H5-G5) -> 21 | R5: =IF(OR(J5="",K5=""),"",J5-K5) -> -300000
A6: P02 | B6: Main Haul Road Upgrade | C6: Infrastructure | D6: M. Diallo | E6: B. Toure | F6: 46032 | G6: 46142 | H6: 46137 | I6: Completed | J6: 1250000 | K6: 1210000 | L6: Yes | M6: Yes | N6: =IF(OR(A6="",I6<>"Completed"),"",IF(H6<=G6,"Yes","No")) -> Yes | O6: =IF(OR(A6="",I6<>"Completed"),"",IF(K6<=J6*(1+Settings!$B$7),"Yes","No")) -> Yes | P6: =IF(OR(A6="",I6<>"Completed"),"",IF(AND(N6="Yes",O6="Yes",L6="Yes"),"Yes","No")) -> Yes | Q6: =IF(OR(G6="",H6=""),"",H6-G6) -> -5 | R6: =IF(OR(J6="",K6=""),"",J6-K6) -> 40000
A7: P03 | B7: Haul Truck Mid-life Rebuilds | C7: Maintenance | D7: S. Keita | E7: O. Traore | F7: 46054 | G7: 46265 | H7: 46262 | I7: Completed | J7: 2100000 | K7: 2180000 | L7: Yes | M7: Yes | N7: =IF(OR(A7="",I7<>"Completed"),"",IF(H7<=G7,"Yes","No")) -> Yes | O7: =IF(OR(A7="",I7<>"Completed"),"",IF(K7<=J7*(1+Settings!$B$7),"Yes","No")) -> Yes | P7: =IF(OR(A7="",I7<>"Completed"),"",IF(AND(N7="Yes",O7="Yes",L7="Yes"),"Yes","No")) -> Yes | Q7: =IF(OR(G7="",H7=""),"",H7-G7) -> -3 | R7: =IF(OR(J7="",K7=""),"",J7-K7) -> -80000
A8: P04 | B8: Blast Fragmentation Optimisation | C8: Drill & Blast | D8: F. Bah | E8: B. Toure | F8: 46037 | G8: 46173 | H8: 46193 | I8: Completed | J8: 350000 | K8: 335000 | L8: No | M8: Yes | N8: =IF(OR(A8="",I8<>"Completed"),"",IF(H8<=G8,"Yes","No")) -> No | O8: =IF(OR(A8="",I8<>"Completed"),"",IF(K8<=J8*(1+Settings!$B$7),"Yes","No")) -> Yes | P8: =IF(OR(A8="",I8<>"Completed"),"",IF(AND(N8="Yes",O8="Yes",L8="Yes"),"Yes","No")) -> No | Q8: =IF(OR(G8="",H8=""),"",H8-G8) -> 20 | R8: =IF(OR(J8="",K8=""),"",J8-K8) -> 15000
A9: P05 | B9: Workshop Extension | C9: Infrastructure | D9: I. Sylla | E9: O. Traore | F9: 46082 | G9: 46356 | H9: 46376 | I9: Active | J9: 1600000 | K9: 1720000 | N9: =IF(OR(A9="",I9<>"Completed"),"",IF(H9<=G9,"Yes","No")) | O9: =IF(OR(A9="",I9<>"Completed"),"",IF(K9<=J9*(1+Settings!$B$7),"Yes","No")) | P9: =IF(OR(A9="",I9<>"Completed"),"",IF(AND(N9="Yes",O9="Yes",L9="Yes"),"Yes","No")) | Q9: =IF(OR(G9="",H9=""),"",H9-G9) -> 20 | R9: =IF(OR(J9="",K9=""),"",J9-K9) -> -120000
A10: P06 | B10: ERP Maintenance Module Roll-out | C10: Systems | D10: K. Conde | E10: O. Traore | F10: 46113 | G10: 46371 | H10: 46371 | I10: Active | J10: 420000 | K10: 410000 | N10: =IF(OR(A10="",I10<>"Completed"),"",IF(H10<=G10,"Yes","No")) | O10: =IF(OR(A10="",I10<>"Completed"),"",IF(K10<=J10*(1+Settings!$B$7),"Yes","No")) | P10: =IF(OR(A10="",I10<>"Completed"),"",IF(AND(N10="Yes",O10="Yes",L10="Yes"),"Yes","No")) | Q10: =IF(OR(G10="",H10=""),"",H10-G10) -> 0 | R10: =IF(OR(J10="",K10=""),"",J10-K10) -> 10000
A11: P07 | B11: Pit Dewatering System Upgrade | C11: Mining | D11: A. Camara | E11: B. Toure | F11: 46143 | G11: 46326 | H11: 46340 | I11: Active | J11: 900000 | K11: 960000 | N11: =IF(OR(A11="",I11<>"Completed"),"",IF(H11<=G11,"Yes","No")) | O11: =IF(OR(A11="",I11<>"Completed"),"",IF(K11<=J11*(1+Settings!$B$7),"Yes","No")) | P11: =IF(OR(A11="",I11<>"Completed"),"",IF(AND(N11="Yes",O11="Yes",L11="Yes"),"Yes","No")) | Q11: =IF(OR(G11="",H11=""),"",H11-G11) -> 14 | R11: =IF(OR(J11="",K11=""),"",J11-K11) -> -60000
A12: P08 | B12: Camp Accommodation Expansion | C12: Infrastructure | D12: M. Diallo | E12: O. Traore | F12: 46068 | G12: 46295 | H12: 46295 | I12: Completed | J12: 1900000 | K12: 1880000 | L12: Yes | M12: No | N12: =IF(OR(A12="",I12<>"Completed"),"",IF(H12<=G12,"Yes","No")) -> Yes | O12: =IF(OR(A12="",I12<>"Completed"),"",IF(K12<=J12*(1+Settings!$B$7),"Yes","No")) -> Yes | P12: =IF(OR(A12="",I12<>"Completed"),"",IF(AND(N12="Yes",O12="Yes",L12="Yes"),"Yes","No")) -> Yes | Q12: =IF(OR(G12="",H12=""),"",H12-G12) -> 0 | R12: =IF(OR(J12="",K12=""),"",J12-K12) -> 20000
N13: =IF(OR(A13="",I13<>"Completed"),"",IF(H13<=G13,"Yes","No")) | O13: =IF(OR(A13="",I13<>"Completed"),"",IF(K13<=J13*(1+Settings!$B$7),"Yes","No")) | P13: =IF(OR(A13="",I13<>"Completed"),"",IF(AND(N13="Yes",O13="Yes",L13="Yes"),"Yes","No")) | Q13: =IF(OR(G13="",H13=""),"",H13-G13) | R13: =IF(OR(J13="",K13=""),"",J13-K13)
N14: =IF(OR(A14="",I14<>"Completed"),"",IF(H14<=G14,"Yes","No")) | O14: =IF(OR(A14="",I14<>"Completed"),"",IF(K14<=J14*(1+Settings!$B$7),"Yes","No")) | P14: =IF(OR(A14="",I14<>"Completed"),"",IF(AND(N14="Yes",O14="Yes",L14="Yes"),"Yes","No")) | Q14: =IF(OR(G14="",H14=""),"",H14-G14) | R14: =IF(OR(J14="",K14=""),"",J14-K14)
N15: =IF(OR(A15="",I15<>"Completed"),"",IF(H15<=G15,"Yes","No")) | O15: =IF(OR(A15="",I15<>"Completed"),"",IF(K15<=J15*(1+Settings!$B$7),"Yes","No")) | P15: =IF(OR(A15="",I15<>"Completed"),"",IF(AND(N15="Yes",O15="Yes",L15="Yes"),"Yes","No")) | Q15: =IF(OR(G15="",H15=""),"",H15-G15) | R15: =IF(OR(J15="",K15=""),"",J15-K15)
N16: =IF(OR(A16="",I16<>"Completed"),"",IF(H16<=G16,"Yes","No")) | O16: =IF(OR(A16="",I16<>"Completed"),"",IF(K16<=J16*(1+Settings!$B$7),"Yes","No")) | P16: =IF(OR(A16="",I16<>"Completed"),"",IF(AND(N16="Yes",O16="Yes",L16="Yes"),"Yes","No")) | Q16: =IF(OR(G16="",H16=""),"",H16-G16) | R16: =IF(OR(J16="",K16=""),"",J16-K16)
N17: =IF(OR(A17="",I17<>"Completed"),"",IF(H17<=G17,"Yes","No")) | O17: =IF(OR(A17="",I17<>"Completed"),"",IF(K17<=J17*(1+Settings!$B$7),"Yes","No")) | P17: =IF(OR(A17="",I17<>"Completed"),"",IF(AND(N17="Yes",O17="Yes",L17="Yes"),"Yes","No")) | Q17: =IF(OR(G17="",H17=""),"",H17-G17) | R17: =IF(OR(J17="",K17=""),"",J17-K17)
N18: =IF(OR(A18="",I18<>"Completed"),"",IF(H18<=G18,"Yes","No")) | O18: =IF(OR(A18="",I18<>"Completed"),"",IF(K18<=J18*(1+Settings!$B$7),"Yes","No")) | P18: =IF(OR(A18="",I18<>"Completed"),"",IF(AND(N18="Yes",O18="Yes",L18="Yes"),"Yes","No")) | Q18: =IF(OR(G18="",H18=""),"",H18-G18) | R18: =IF(OR(J18="",K18=""),"",J18-K18)
N19: =IF(OR(A19="",I19<>"Completed"),"",IF(H19<=G19,"Yes","No")) | O19: =IF(OR(A19="",I19<>"Completed"),"",IF(K19<=J19*(1+Settings!$B$7),"Yes","No")) | P19: =IF(OR(A19="",I19<>"Completed"),"",IF(AND(N19="Yes",O19="Yes",L19="Yes"),"Yes","No")) | Q19: =IF(OR(G19="",H19=""),"",H19-G19) | R19: =IF(OR(J19="",K19=""),"",J19-K19)
N20: =IF(OR(A20="",I20<>"Completed"),"",IF(H20<=G20,"Yes","No")) | O20: =IF(OR(A20="",I20<>"Completed"),"",IF(K20<=J20*(1+Settings!$B$7),"Yes","No")) | P20: =IF(OR(A20="",I20<>"Completed"),"",IF(AND(N20="Yes",O20="Yes",L20="Yes"),"Yes","No")) | Q20: =IF(OR(G20="",H20=""),"",H20-G20) | R20: =IF(OR(J20="",K20=""),"",J20-K20)
N21: =IF(OR(A21="",I21<>"Completed"),"",IF(H21<=G21,"Yes","No")) | O21: =IF(OR(A21="",I21<>"Completed"),"",IF(K21<=J21*(1+Settings!$B$7),"Yes","No")) | P21: =IF(OR(A21="",I21<>"Completed"),"",IF(AND(N21="Yes",O21="Yes",L21="Yes"),"Yes","No")) | Q21: =IF(OR(G21="",H21=""),"",H21-G21) | R21: =IF(OR(J21="",K21=""),"",J21-K21)
N22: =IF(OR(A22="",I22<>"Completed"),"",IF(H22<=G22,"Yes","No")) | O22: =IF(OR(A22="",I22<>"Completed"),"",IF(K22<=J22*(1+Settings!$B$7),"Yes","No")) | P22: =IF(OR(A22="",I22<>"Completed"),"",IF(AND(N22="Yes",O22="Yes",L22="Yes"),"Yes","No")) | Q22: =IF(OR(G22="",H22=""),"",H22-G22) | R22: =IF(OR(J22="",K22=""),"",J22-K22)
N23: =IF(OR(A23="",I23<>"Completed"),"",IF(H23<=G23,"Yes","No")) | O23: =IF(OR(A23="",I23<>"Completed"),"",IF(K23<=J23*(1+Settings!$B$7),"Yes","No")) | P23: =IF(OR(A23="",I23<>"Completed"),"",IF(AND(N23="Yes",O23="Yes",L23="Yes"),"Yes","No")) | Q23: =IF(OR(G23="",H23=""),"",H23-G23) | R23: =IF(OR(J23="",K23=""),"",J23-K23)
N24: =IF(OR(A24="",I24<>"Completed"),"",IF(H24<=G24,"Yes","No")) | O24: =IF(OR(A24="",I24<>"Completed"),"",IF(K24<=J24*(1+Settings!$B$7),"Yes","No")) | P24: =IF(OR(A24="",I24<>"Completed"),"",IF(AND(N24="Yes",O24="Yes",L24="Yes"),"Yes","No")) | Q24: =IF(OR(G24="",H24=""),"",H24-G24) | R24: =IF(OR(J24="",K24=""),"",J24-K24)
... N104: =IF(OR(A104="",I104<>"Completed"),"",IF(H104<=G104,"Yes","No")) | O104: =IF(OR(A104="",I104<>"Completed"),"",IF(K104<=J104*(1+Settings!$B$7),"Yes","No")) | P104: =IF(OR(A104="",I104<>"Completed"),"",IF(AND(N104="Yes",O104="Yes",L104="Yes"),"Yes","No")) | Q104: =IF(OR(G104="",H104=""),"",H104-G104) | R104: =IF(OR(J104="",K104=""),"",J104-K104)

Sheet Cost_Schedule
A1: Cost & Schedule (Earned Value) – monthly per project
A2: Enter one row per project per month. Month = 1st of the month. Values in your currency. PV = budgeted cost of work planned, EV = budgeted cost of work done, AC = actual cost.
A4: Month | B4: Project ID | C4: Project name | D4: Approved budget (period) | E4: Planned value (PV) | F4: Earned value (EV) | G4: Actual cost (AC) | H4: Schedule var. SV = EV−PV | I4: Cost var. CV = EV−AC | J4: SPI = EV/PV | K4: CPI = EV/AC | L4: Budget used = AC/Budget | M4: Comment
A5: 46023 | B5: P01 | C5: =IF(B5="","",IFERROR(INDEX(Projects!$B$5:$B$104,MATCH(B5,Projects!$A$5:$A$104,0)),"?")) -> Pit 2 Stage 3 Pushback | D5: 600000 | E5: 579700 | F5: 527800 | G5: 564500 | H5: =IF(OR(E5="",F5=""),"",F5-E5) -> -51900 | I5: =IF(OR(F5="",G5=""),"",F5-G5) -> -36700 | J5: =IF(OR(E5="",E5=0,F5=""),"",F5/E5) -> 0.91047093 | K5: =IF(OR(G5="",G5=0,F5=""),"",F5/G5) -> 0.93498671 | L5: =IF(OR(D5="",D5=0,G5=""),"",G5/D5) -> 0.94083333
A6: 46023 | B6: P02 | C6: =IF(B6="","",IFERROR(INDEX(Projects!$B$5:$B$104,MATCH(B6,Projects!$A$5:$A$104,0)),"?")) -> Main Haul Road Upgrade | D6: 312000 | E6: 297500 | F6: 304100 | G6: 292600 | H6: =IF(OR(E6="",F6=""),"",F6-E6) -> 6600 | I6: =IF(OR(F6="",G6=""),"",F6-G6) -> 11500 | J6: =IF(OR(E6="",E6=0,F6=""),"",F6/E6) -> 1.0221849 | K6: =IF(OR(G6="",G6=0,F6=""),"",F6/G6) -> 1.0393028 | L6: =IF(OR(D6="",D6=0,G6=""),"",G6/D6) -> 0.93782051
A7: 46023 | B7: P04 | C7: =IF(B7="","",IFERROR(INDEX(Projects!$B$5:$B$104,MATCH(B7,Projects!$A$5:$A$104,0)),"?")) -> Blast Fragmentation Optimisation | D7: 70000 | E7: 66700 | F7: 61400 | G7: 57900 | H7: =IF(OR(E7="",F7=""),"",F7-E7) -> -5300 | I7: =IF(OR(F7="",G7=""),"",F7-G7) -> 3500 | J7: =IF(OR(E7="",E7=0,F7=""),"",F7/E7) -> 0.92053973 | K7: =IF(OR(G7="",G7=0,F7=""),"",F7/G7) -> 1.0604491 | L7: =IF(OR(D7="",D7=0,G7=""),"",G7/D7) -> 0.82714286
A8: 46054 | B8: P01 | C8: =IF(B8="","",IFERROR(INDEX(Projects!$B$5:$B$104,MATCH(B8,Projects!$A$5:$A$104,0)),"?")) -> Pit 2 Stage 3 Pushback | D8: 600000 | E8: 583000 | F8: 528200 | G8: 546100 | H8: =IF(OR(E8="",F8=""),"",F8-E8) -> -54800 | I8: =IF(OR(F8="",G8=""),"",F8-G8) -> -17900 | J8: =IF(OR(E8="",E8=0,F8=""),"",F8/E8) -> 0.90600343 | K8: =IF(OR(G8="",G8=0,F8=""),"",F8/G8) -> 0.96722212 | L8: =IF(OR(D8="",D8=0,G8=""),"",G8/D8) -> 0.91016667
A9: 46054 | B9: P02 | C9: =IF(B9="","",IFERROR(INDEX(Projects!$B$5:$B$104,MATCH(B9,Projects!$A$5:$A$104,0)),"?")) -> Main Haul Road Upgrade | D9: 312000 | E9: 303000 | F9: 315100 | G9: 298700 | H9: =IF(OR(E9="",F9=""),"",F9-E9) -> 12100 | I9: =IF(OR(F9="",G9=""),"",F9-G9) -> 16400 | J9: =IF(OR(E9="",E9=0,F9=""),"",F9/E9) -> 1.039934 | K9: =IF(OR(G9="",G9=0,F9=""),"",F9/G9) -> 1.0549046 | L9: =IF(OR(D9="",D9=0,G9=""),"",G9/D9) -> 0.95737179
A10: 46054 | B10: P03 | C10: =IF(B10="","",IFERROR(INDEX(Projects!$B$5:$B$104,MATCH(B10,Projects!$A$5:$A$104,0)),"?")) -> Haul Truck Mid-life Rebuilds | D10: 300000 | E10: 288300 | F10: 284700 | G10: 301100 | H10: =IF(OR(E10="",F10=""),"",F10-E10) -> -3600 | I10: =IF(OR(F10="",G10=""),"",F10-G10) -> -16400 | J10: =IF(OR(E10="",E10=0,F10=""),"",F10/E10) -> 0.98751301 | K10: =IF(OR(G10="",G10=0,F10=""),"",F10/G10) -> 0.94553305 | L10: =IF(OR(D10="",D10=0,G10=""),"",G10/D10) -> 1.0036667
A11: 46054 | B11: P04 | C11: =IF(B11="","",IFERROR(INDEX(Projects!$B$5:$B$104,MATCH(B11,Projects!$A$5:$A$104,0)),"?")) -> Blast Fragmentation Optimisation | D11: 70000 | E11: 68500 | F11: 62600 | G11: 62500 | H11: =IF(OR(E11="",F11=""),"",F11-E11) -> -5900 | I11: =IF(OR(F11="",G11=""),"",F11-G11) -> 100 | J11: =IF(OR(E11="",E11=0,F11=""),"",F11/E11) -> 0.91386861 | K11: =IF(OR(G11="",G11=0,F11=""),"",F11/G11) -> 1.0016 | L11: =IF(OR(D11="",D11=0,G11=""),"",G11/D11) -> 0.89285714
A12: 46054 | B12: P08 | C12: =IF(B12="","",IFERROR(INDEX(Projects!$B$5:$B$104,MATCH(B12,Projects!$A$5:$A$104,0)),"?")) -> Camp Accommodation Expansion | D12: 238000 | E12: 226700 | F12: 231600 | G12: 226400 | H12: =IF(OR(E12="",F12=""),"",F12-E12) -> 4900 | I12: =IF(OR(F12="",G12=""),"",F12-G12) -> 5200 | J12: =IF(OR(E12="",E12=0,F12=""),"",F12/E12) -> 1.0216145 | K12: =IF(OR(G12="",G12=0,F12=""),"",F12/G12) -> 1.0229682 | L12: =IF(OR(D12="",D12=0,G12=""),"",G12/D12) -> 0.9512605
A13: 46082 | B13: P01 | C13: =IF(B13="","",IFERROR(INDEX(Projects!$B$5:$B$104,MATCH(B13,Projects!$A$5:$A$104,0)),"?")) -> Pit 2 Stage 3 Pushback | D13: 600000 | E13: 574300 | F13: 521900 | G13: 546900 | H13: =IF(OR(E13="",F13=""),"",F13-E13) -> -52400 | I13: =IF(OR(F13="",G13=""),"",F13-G13) -> -25000 | J13: =IF(OR(E13="",E13=0,F13=""),"",F13/E13) -> 0.90875849 | K13: =IF(OR(G13="",G13=0,F13=""),"",F13/G13) -> 0.9542878 | L13: =IF(OR(D13="",D13=0,G13=""),"",G13/D13) -> 0.9115
A14: 46082 | B14: P02 | C14: =IF(B14="","",IFERROR(INDEX(Projects!$B$5:$B$104,MATCH(B14,Projects!$A$5:$A$104,0)),"?")) -> Main Haul Road Upgrade | D14: 312000 | E14: 309100 | F14: 309200 | G14: 301400 | H14: =IF(OR(E14="",F14=""),"",F14-E14) -> 100 | I14: =IF(OR(F14="",G14=""),"",F14-G14) -> 7800 | J14: =IF(OR(E14="",E14=0,F14=""),"",F14/E14) -> 1.0003235 | K14: =IF(OR(G14="",G14=0,F14=""),"",F14/G14) -> 1.0258792 | L14: =IF(OR(D14="",D14=0,G14=""),"",G14/D14) -> 0.96602564
A15: 46082 | B15: P03 | C15: =IF(B15="","",IFERROR(INDEX(Projects!$B$5:$B$104,MATCH(B15,Projects!$A$5:$A$104,0)),"?")) -> Haul Truck Mid-life Rebuilds | D15: 300000 | E15: 294600 | F15: 286500 | G15: 295900 | H15: =IF(OR(E15="",F15=""),"",F15-E15) -> -8100 | I15: =IF(OR(F15="",G15=""),"",F15-G15) -> -9400 | J15: =IF(OR(E15="",E15=0,F15=""),"",F15/E15) -> 0.97250509 | K15: =IF(OR(G15="",G15=0,F15=""),"",F15/G15) -> 0.96823251 | L15: =IF(OR(D15="",D15=0,G15=""),"",G15/D15) -> 0.98633333
A16: 46082 | B16: P04 | C16: =IF(B16="","",IFERROR(INDEX(Projects!$B$5:$B$104,MATCH(B16,Projects!$A$5:$A$104,0)),"?")) -> Blast Fragmentation Optimisation | D16: 70000 | E16: 66700 | F16: 59700 | G16: 56900 | H16: =IF(OR(E16="",F16=""),"",F16-E16) -> -7000 | I16: =IF(OR(F16="",G16=""),"",F16-G16) -> 2800 | J16: =IF(OR(E16="",E16=0,F16=""),"",F16/E16) -> 0.89505247 | K16: =IF(OR(G16="",G16=0,F16=""),"",F16/G16) -> 1.0492091 | L16: =IF(OR(D16="",D16=0,G16=""),"",G16/D16) -> 0.81285714
... A57: 46296 | B57: P07 | C57: =IF(B57="","",IFERROR(INDEX(Projects!$B$5:$B$104,MATCH(B57,Projects!$A$5:$A$104,0)),"?")) -> Pit Dewatering System Upgrade | D57: 150000 | E57: 146600 | F57: 133900 | G57: 142200 | H57: =IF(OR(E57="",F57=""),"",F57-E57) -> -12700 | I57: =IF(OR(F57="",G57=""),"",F57-G57) -> -8300 | J57: =IF(OR(E57="",E57=0,F57=""),"",F57/E57) -> 0.91336971 | K57: =IF(OR(G57="",G57=0,F57=""),"",F57/G57) -> 0.9416315 | L57: =IF(OR(D57="",D57=0,G57=""),"",G57/D57) -> 0.948
C58: =IF(B58="","",IFERROR(INDEX(Projects!$B$5:$B$104,MATCH(B58,Projects!$A$5:$A$104,0)),"?")) | H58: =IF(OR(E58="",F58=""),"",F58-E58) | I58: =IF(OR(F58="",G58=""),"",F58-G58) | J58: =IF(OR(E58="",E58=0,F58=""),"",F58/E58) | K58: =IF(OR(G58="",G58=0,F58=""),"",F58/G58) | L58: =IF(OR(D58="",D58=0,G58=""),"",G58/D58)
C59: =IF(B59="","",IFERROR(INDEX(Projects!$B$5:$B$104,MATCH(B59,Projects!$A$5:$A$104,0)),"?")) | H59: =IF(OR(E59="",F59=""),"",F59-E59) | I59: =IF(OR(F59="",G59=""),"",F59-G59) | J59: =IF(OR(E59="",E59=0,F59=""),"",F59/E59) | K59: =IF(OR(G59="",G59=0,F59=""),"",F59/G59) | L59: =IF(OR(D59="",D59=0,G59=""),"",G59/D59)
C60: =IF(B60="","",IFERROR(INDEX(Projects!$B$5:$B$104,MATCH(B60,Projects!$A$5:$A$104,0)),"?")) | H60: =IF(OR(E60="",F60=""),"",F60-E60) | I60: =IF(OR(F60="",G60=""),"",F60-G60) | J60: =IF(OR(E60="",E60=0,F60=""),"",F60/E60) | K60: =IF(OR(G60="",G60=0,F60=""),"",F60/G60) | L60: =IF(OR(D60="",D60=0,G60=""),"",G60/D60)
C61: =IF(B61="","",IFERROR(INDEX(Projects!$B$5:$B$104,MATCH(B61,Projects!$A$5:$A$104,0)),"?")) | H61: =IF(OR(E61="",F61=""),"",F61-E61) | I61: =IF(OR(F61="",G61=""),"",F61-G61) | J61: =IF(OR(E61="",E61=0,F61=""),"",F61/E61) | K61: =IF(OR(G61="",G61=0,F61=""),"",F61/G61) | L61: =IF(OR(D61="",D61=0,G61=""),"",G61/D61)
C62: =IF(B62="","",IFERROR(INDEX(Projects!$B$5:$B$104,MATCH(B62,Projects!$A$5:$A$104,0)),"?")) | H62: =IF(OR(E62="",F62=""),"",F62-E62) | I62: =IF(OR(F62="",G62=""),"",F62-G62) | J62: =IF(OR(E62="",E62=0,F62=""),"",F62/E62) | K62: =IF(OR(G62="",G62=0,F62=""),"",F62/G62) | L62: =IF(OR(D62="",D62=0,G62=""),"",G62/D62)
C63: =IF(B63="","",IFERROR(INDEX(Projects!$B$5:$B$104,MATCH(B63,Projects!$A$5:$A$104,0)),"?")) | H63: =IF(OR(E63="",F63=""),"",F63-E63) | I63: =IF(OR(F63="",G63=""),"",F63-G63) | J63: =IF(OR(E63="",E63=0,F63=""),"",F63/E63) | K63: =IF(OR(G63="",G63=0,F63=""),"",F63/G63) | L63: =IF(OR(D63="",D63=0,G63=""),"",G63/D63)
C64: =IF(B64="","",IFERROR(INDEX(Projects!$B$5:$B$104,MATCH(B64,Projects!$A$5:$A$104,0)),"?")) | H64: =IF(OR(E64="",F64=""),"",F64-E64) | I64: =IF(OR(F64="",G64=""),"",F64-G64) | J64: =IF(OR(E64="",E64=0,F64=""),"",F64/E64) | K64: =IF(OR(G64="",G64=0,F64=""),"",F64/G64) | L64: =IF(OR(D64="",D64=0,G64=""),"",G64/D64)
C65: =IF(B65="","",IFERROR(INDEX(Projects!$B$5:$B$104,MATCH(B65,Projects!$A$5:$A$104,0)),"?")) | H65: =IF(OR(E65="",F65=""),"",F65-E65) | I65: =IF(OR(F65="",G65=""),"",F65-G65) | J65: =IF(OR(E65="",E65=0,F65=""),"",F65/E65) | K65: =IF(OR(G65="",G65=0,F65=""),"",F65/G65) | L65: =IF(OR(D65="",D65=0,G65=""),"",G65/D65)
C66: =IF(B66="","",IFERROR(INDEX(Projects!$B$5:$B$104,MATCH(B66,Projects!$A$5:$A$104,0)),"?")) | H66: =IF(OR(E66="",F66=""),"",F66-E66) | I66: =IF(OR(F66="",G66=""),"",F66-G66) | J66: =IF(OR(E66="",E66=0,F66=""),"",F66/E66) | K66: =IF(OR(G66="",G66=0,F66=""),"",F66/G66) | L66: =IF(OR(D66="",D66=0,G66=""),"",G66/D66)
C67: =IF(B67="","",IFERROR(INDEX(Projects!$B$5:$B$104,MATCH(B67,Projects!$A$5:$A$104,0)),"?")) | H67: =IF(OR(E67="",F67=""),"",F67-E67) | I67: =IF(OR(F67="",G67=""),"",F67-G67) | J67: =IF(OR(E67="",E67=0,F67=""),"",F67/E67) | K67: =IF(OR(G67="",G67=0,F67=""),"",F67/G67) | L67: =IF(OR(D67="",D67=0,G67=""),"",G67/D67)
C68: =IF(B68="","",IFERROR(INDEX(Projects!$B$5:$B$104,MATCH(B68,Projects!$A$5:$A$104,0)),"?")) | H68: =IF(OR(E68="",F68=""),"",F68-E68) | I68: =IF(OR(F68="",G68=""),"",F68-G68) | J68: =IF(OR(E68="",E68=0,F68=""),"",F68/E68) | K68: =IF(OR(G68="",G68=0,F68=""),"",F68/G68) | L68: =IF(OR(D68="",D68=0,G68=""),"",G68/D68)
C69: =IF(B69="","",IFERROR(INDEX(Projects!$B$5:$B$104,MATCH(B69,Projects!$A$5:$A$104,0)),"?")) | H69: =IF(OR(E69="",F69=""),"",F69-E69) | I69: =IF(OR(F69="",G69=""),"",F69-G69) | J69: =IF(OR(E69="",E69=0,F69=""),"",F69/E69) | K69: =IF(OR(G69="",G69=0,F69=""),"",F69/G69) | L69: =IF(OR(D69="",D69=0,G69=""),"",G69/D69)
... C504: =IF(B504="","",IFERROR(INDEX(Projects!$B$5:$B$104,MATCH(B504,Projects!$A$5:$A$104,0)),"?")) | H504: =IF(OR(E504="",F504=""),"",F504-E504) | I504: =IF(OR(F504="",G504=""),"",F504-G504) | J504: =IF(OR(E504="",E504=0,F504=""),"",F504/E504) | K504: =IF(OR(G504="",G504=0,F504=""),"",F504/G504) | L504: =IF(OR(D504="",D504=0,G504=""),"",G504/D504)

Sheet Change_Log
A1: Change Request Log
A2: Every change request (scope, schedule, cost…). Scope CRs drive Scope Change Frequency; submitted→decision days drive CR Approval Time.
A4: CR ID | B4: Project ID | C4: Date submitted | D4: Description of change | E4: Change type | F4: Requested by | G4: Cost impact | H4: Schedule impact (days) | I4: Decision | J4: Decision date | K4: Approval time (days) | L4: Implemented? | M4: Implementation date | N4: Remarks
A5: CR-001 | B5: P06 | C5: 46076 | D5: Upgrade concrete spec | E5: Quality | F5: K. Conde | G5: 60000 | H5: 3 | I5: Rejected | J5: 46083 | K5: =IF(OR(C5="",J5=""),"",J5-C5) -> 7
A6: CR-002 | B6: P04 | C6: 46321 | D6: Fuel price escalation | E6: Cost | F6: B. Toure | G6: 40000 | H6: -2 | I6: Rejected | J6: 46326 | K6: =IF(OR(C6="",J6=""),"",J6-C6) -> 5
A7: CR-003 | B7: P08 | C7: 46023 | D7: Additional steel cost | E7: Cost | F7: K. Conde | G7: 40000 | H7: 0 | I7: Approved | J7: 46036 | K7: =IF(OR(C7="",J7=""),"",J7-C7) -> 13 | L7: Yes | M7: 46050
A8: CR-004 | B8: P04 | C8: 46116 | D8: Add reporting dashboard to ERP | E8: Scope | F8: K. Conde | G8: 60000 | H8: 0 | I8: Approved | J8: 46125 | K8: =IF(OR(C8="",J8=""),"",J8-C8) -> 9 | L8: Yes | M8: 46128
A9: CR-005 | B9: P04 | C9: 46066 | D9: Fuel price escalation | E9: Cost | F9: O. Traore | G9: -8000 | H9: 10 | I9: Approved | J9: 46070 | K9: =IF(OR(C9="",J9=""),"",J9-C9) -> 4 | L9: Yes | M9: 46083
A10: CR-006 | B10: P03 | C10: 46077 | D10: Extra drainage culverts | E10: Scope | F10: B. Toure | G10: 60000 | H10: 7 | I10: Approved | J10: 46088 | K10: =IF(OR(C10="",J10=""),"",J10-C10) -> 11 | L10: No
A11: CR-007 | B11: P01 | C11: 46099 | D11: Delay due to rainy season | E11: Schedule | F11: O. Traore | G11: 15000 | H11: 3 | I11: Approved | J11: 46112 | K11: =IF(OR(C11="",J11=""),"",J11-C11) -> 13 | L11: Yes | M11: 46131
A12: CR-008 | B12: P04 | C12: 46031 | D12: Additional bay in workshop | E12: Scope | F12: O. Traore | G12: 15000 | H12: 0 | I12: Rejected | J12: 46038 | K12: =IF(OR(C12="",J12=""),"",J12-C12) -> 7
A13: CR-009 | B13: P07 | C13: 46188 | D13: Fuel price escalation | E13: Cost | F13: A. Camara | G13: -8000 | H13: 3 | I13: Rejected | J13: 46192 | K13: =IF(OR(C13="",J13=""),"",J13-C13) -> 4
A14: CR-010 | B14: P03 | C14: 46296 | D14: Additional steel cost | E14: Cost | F14: M. Diallo | G14: 25000 | H14: 0 | I14: Pending | K14: =IF(OR(C14="",J14=""),"",J14-C14)
A15: CR-011 | B15: P08 | C15: 46195 | D15: Delay due to rainy season | E15: Schedule | F15: F. Bah | G15: 15000 | H15: 7 | I15: Rejected | J15: 46198 | K15: =IF(OR(C15="",J15=""),"",J15-C15) -> 3
A16: CR-012 | B16: P08 | C16: 46047 | D16: Add ramp widening at bench 4 | E16: Scope | F16: B. Toure | G16: 40000 | H16: 14 | I16: Approved | J16: 46061 | K16: =IF(OR(C16="",J16=""),"",J16-C16) -> 14 | L16: No
A17: CR-013 | B17: P05 | C17: 46285 | D17: Resequence works around blasting | E17: Schedule | F17: F. Bah | G17: -8000 | H17: 3 | I17: Approved | J17: 46294 | K17: =IF(OR(C17="",J17=""),"",J17-C17) -> 9 | L17: Yes | M17: 46304
A18: CR-014 | B18: P06 | C18: 46207 | D18: Additional bay in workshop | E18: Scope | F18: M. Diallo | G18: 15000 | H18: -2 | I18: Approved | J18: 46212 | K18: =IF(OR(C18="",J18=""),"",J18-C18) -> 5 | L18: Yes | M18: 46221
A19: CR-015 | B19: P03 | C19: 46178 | D19: Add ramp widening at bench 4 | E19: Scope | F19: O. Traore | G19: -8000 | H19: 3 | I19: Rejected | J19: 46183 | K19: =IF(OR(C19="",J19=""),"",J19-C19) -> 5
A20: CR-016 | B20: P07 | C20: 46118 | D20: Additional steel cost | E20: Cost | F20: A. Camara | G20: 40000 | H20: 14 | I20: Approved | J20: 46123 | K20: =IF(OR(C20="",J20=""),"",J20-C20) -> 5 | L20: Yes | M20: 46128
A21: CR-017 | B21: P07 | C21: 46249 | D21: Fuel price escalation | E21: Cost | F21: F. Bah | G21: 0 | H21: 0 | I21: Approved | J21: 46255 | K21: =IF(OR(C21="",J21=""),"",J21-C21) -> 6 | L21: Yes | M21: 46260
A22: CR-018 | B22: P03 | C22: 46151 | D22: Additional bay in workshop | E22: Scope | F22: O. Traore | G22: 15000 | H22: 14 | I22: Approved | J22: 46155 | K22: =IF(OR(C22="",J22=""),"",J22-C22) -> 4 | L22: No
A23: CR-019 | B23: P06 | C23: 46284 | D23: Resequence works around blasting | E23: Schedule | F23: M. Diallo | G23: 40000 | H23: 0 | I23: Approved | J23: 46286 | K23: =IF(OR(C23="",J23=""),"",J23-C23) -> 2 | L23: Yes | M23: 46294
A24: CR-020 | B24: P04 | C24: 46079 | D24: Extend pushback to east wall | E24: Scope | F24: O. Traore | G24: 40000 | H24: 14 | I24: Approved | J24: 46082 | K24: =IF(OR(C24="",J24=""),"",J24-C24) -> 3 | L24: Yes | M24: 46095
A25: CR-021 | B25: P04 | C25: 46083 | D25: Resequence works around blasting | E25: Schedule | F25: A. Camara | G25: 15000 | H25: 3 | I25: Rejected | J25: 46087 | K25: =IF(OR(C25="",J25=""),"",J25-C25) -> 4
A26: CR-022 | B26: P04 | C26: 46163 | D26: Additional bay in workshop | E26: Scope | F26: A. Camara | G26: 0 | H26: 0 | I26: Approved | J26: 46167 | K26: =IF(OR(C26="",J26=""),"",J26-C26) -> 4 | L26: Yes | M26: 46170
A27: CR-023 | B27: P08 | C27: 46283 | D27: Add second excavator crew | E27: Resource | F27: O. Traore | G27: 25000 | H27: 7 | I27: Approved | J27: 46292 | K27: =IF(OR(C27="",J27=""),"",J27-C27) -> 9 | L27: Yes | M27: 46308
A28: CR-024 | B28: P03 | C28: 46120 | D28: Extra drainage culverts | E28: Scope | F28: A. Camara | G28: 0 | H28: -2 | I28: Approved | J28: 46127 | K28: =IF(OR(C28="",J28=""),"",J28-C28) -> 7 | L28: No
A29: CR-025 | B29: P02 | C29: 46156 | D29: Additional bay in workshop | E29: Scope | F29: F. Bah | G29: 60000 | H29: 7 | I29: Approved | J29: 46164 | K29: =IF(OR(C29="",J29=""),"",J29-C29) -> 8 | L29: No
A30: CR-026 | B30: P05 | C30: 46037 | D30: Extend pushback to east wall | E30: Scope | F30: K. Conde | G30: 15000 | H30: 0 | I30: Approved | J30: 46043 | K30: =IF(OR(C30="",J30=""),"",J30-C30) -> 6 | L30: Yes | M30: 46056
K31: =IF(OR(C31="",J31=""),"",J31-C31)
K32: =IF(OR(C32="",J32=""),"",J32-C32)
K33: =IF(OR(C33="",J33=""),"",J33-C33)
K34: =IF(OR(C34="",J34=""),"",J34-C34)
K35: =IF(OR(C35="",J35=""),"",J35-C35)
K36: =IF(OR(C36="",J36=""),"",J36-C36)
K37: =IF(OR(C37="",J37=""),"",J37-C37)
K38: =IF(OR(C38="",J38=""),"",J38-C38)
K39: =IF(OR(C39="",J39=""),"",J39-C39)
K40: =IF(OR(C40="",J40=""),"",J40-C40)
K41: =IF(OR(C41="",J41=""),"",J41-C41)
K42: =IF(OR(C42="",J42=""),"",J42-C42)
... K504: =IF(OR(C504="",J504=""),"",J504-C504)

Sheet Risk_Log
A1: Risk Register
A2: Score = Probability × Impact (1–5 each). Closing a risk: enter Closure date and whether it Materialised. Residual score shows the reduction achieved.
A4: Risk ID | B4: Project ID | C4: Date identified | D4: Risk description | E4: Category | F4: Probability (1-5) | G4: Impact (1-5) | H4: Inherent score | I4: Rating | J4: Mitigation action | K4: Owner | L4: Status | M4: Closure date | N4: Materialised? | O4: Residual P (1-5) | P4: Residual I (1-5) | Q4: Residual score | R4: Reduction %
A5: R-001 | B5: P01 | C5: 46149 | D5: Fuel price increase | E5: Commercial | F5: 3 | G5: 2 | H5: =IF(OR(F5="",G5=""),"",F5*G5) -> 6 | I5: =IF(H5="","",IF(H5>=15,"High",IF(H5>=8,"Medium","Low"))) -> Low | J5: Rise-and-fall clause in contract | K5: M. Diallo | L5: Closed | M5: 46169 | N5: No | O5: 2 | P5: 1 | Q5: =IF(OR(O5="",P5=""),"",O5*P5) -> 2 | R5: =IF(OR(H5="",Q5=""),"",1-Q5/H5) -> 0.66666667
A6: R-002 | B6: P03 | C6: 46145 | D6: Late delivery of rebuild kits | E6: Supply chain | F6: 5 | G6: 2 | H6: =IF(OR(F6="",G6=""),"",F6*G6) -> 10 | I6: =IF(H6="","",IF(H6>=15,"High",IF(H6>=8,"Medium","Low"))) -> Medium | J6: Order 8 weeks early, second supplier | K6: O. Traore | L6: Closed | M6: 46179 | N6: No | O6: 4 | P6: 1 | Q6: =IF(OR(O6="",P6=""),"",O6*P6) -> 4 | R6: =IF(OR(H6="",Q6=""),"",1-Q6/H6) -> 0.6
A7: R-003 | B7: P01 | C7: 46197 | D7: ERP data migration errors | E7: Technical | F7: 3 | G7: 4 | H7: =IF(OR(F7="",G7=""),"",F7*G7) -> 12 | I7: =IF(H7="","",IF(H7>=15,"High",IF(H7>=8,"Medium","Low"))) -> Medium | J7: Trial migration and reconciliation | K7: O. Traore | L7: Open | O7: 1 | P7: 4 | Q7: =IF(OR(O7="",P7=""),"",O7*P7) -> 4 | R7: =IF(OR(H7="",Q7=""),"",1-Q7/H7) -> 0.66666667
A8: R-004 | B8: P01 | C8: 46270 | D8: Pit wall instability on east wall | E8: Technical | F8: 3 | G8: 2 | H8: =IF(OR(F8="",G8=""),"",F8*G8) -> 6 | I8: =IF(H8="","",IF(H8>=15,"High",IF(H8>=8,"Medium","Low"))) -> Low | J8: Geotech monitoring radar + reduced bench height | K8: A. Camara | L8: Closed | M8: 46293 | N8: No | O8: 1 | P8: 1 | Q8: =IF(OR(O8="",P8=""),"",O8*P8) -> 1 | R8: =IF(OR(H8="",Q8=""),"",1-Q8/H8) -> 0.83333333
A9: R-005 | B9: P02 | C9: 46287 | D9: Flyrock incident near haul road | E9: Safety | F9: 5 | G9: 4 | H9: =IF(OR(F9="",G9=""),"",F9*G9) -> 20 | I9: =IF(H9="","",IF(H9>=15,"High",IF(H9>=8,"Medium","Low"))) -> High | J9: Blast exclusion zone review, stemming QA | K9: B. Toure | L9: Closed | M9: 46315 | N9: No | O9: 2 | P9: 2 | Q9: =IF(OR(O9="",P9=""),"",O9*P9) -> 4 | R9: =IF(OR(H9="",Q9=""),"",1-Q9/H9) -> 0.8
A10: R-006 | B10: P02 | C10: 46145 | D10: Community road blockage | E10: Community | F10: 3 | G10: 3 | H10: =IF(OR(F10="",G10=""),"",F10*G10) -> 9 | I10: =IF(H10="","",IF(H10>=15,"High",IF(H10>=8,"Medium","Low"))) -> Medium | J10: Weekly liaison meetings with village committee | K10: B. Toure | L10: Occurred | M10: 46201 | N10: Yes | O10: 1 | P10: 2 | Q10: =IF(OR(O10="",P10=""),"",O10*P10) -> 2 | R10: =IF(OR(H10="",Q10=""),"",1-Q10/H10) -> 0.77777778
A11: R-007 | B11: P03 | C11: 46167 | D11: Pit wall instability on east wall | E11: Technical | F11: 3 | G11: 2 | H11: =IF(OR(F11="",G11=""),"",F11*G11) -> 6 | I11: =IF(H11="","",IF(H11>=15,"High",IF(H11>=8,"Medium","Low"))) -> Low | J11: Geotech monitoring radar + reduced bench height | K11: A. Camara | L11: Mitigated | M11: 46203 | N11: No | O11: 1 | P11: 1 | Q11: =IF(OR(O11="",P11=""),"",O11*P11) -> 1 | R11: =IF(OR(H11="",Q11=""),"",1-Q11/H11) -> 0.83333333
A12: R-008 | B12: P05 | C12: 46236 | D12: ERP data migration errors | E12: Technical | F12: 4 | G12: 2 | H12: =IF(OR(F12="",G12=""),"",F12*G12) -> 8 | I12: =IF(H12="","",IF(H12>=15,"High",IF(H12>=8,"Medium","Low"))) -> Medium | J12: Trial migration and reconciliation | K12: I. Sylla | L12: Open | O12: 1 | P12: 1 | Q12: =IF(OR(O12="",P12=""),"",O12*P12) -> 1 | R12: =IF(OR(H12="",Q12=""),"",1-Q12/H12) -> 0.875
A13: R-009 | B13: P08 | C13: 46249 | D13: ERP data migration errors | E13: Technical | F13: 2 | G13: 3 | H13: =IF(OR(F13="",G13=""),"",F13*G13) -> 6 | I13: =IF(H13="","",IF(H13>=15,"High",IF(H13>=8,"Medium","Low"))) -> Low | J13: Trial migration and reconciliation | K13: M. Diallo | L13: Occurred | M13: 46269 | N13: Yes | O13: 1 | P13: 2 | Q13: =IF(OR(O13="",P13=""),"",O13*P13) -> 2 | R13: =IF(OR(H13="",Q13=""),"",1-Q13/H13) -> 0.66666667
A14: R-010 | B14: P02 | C14: 46280 | D14: Community road blockage | E14: Community | F14: 5 | G14: 3 | H14: =IF(OR(F14="",G14=""),"",F14*G14) -> 15 | I14: =IF(H14="","",IF(H14>=15,"High",IF(H14>=8,"Medium","Low"))) -> High | J14: Weekly liaison meetings with village committee | K14: S. Keita | L14: Open | O14: 4 | P14: 3 | Q14: =IF(OR(O14="",P14=""),"",O14*P14) -> 12 | R14: =IF(OR(H14="",Q14=""),"",1-Q14/H14) -> 0.2
A15: R-011 | B15: P04 | C15: 46274 | D15: Fuel price increase | E15: Commercial | F15: 3 | G15: 4 | H15: =IF(OR(F15="",G15=""),"",F15*G15) -> 12 | I15: =IF(H15="","",IF(H15>=15,"High",IF(H15>=8,"Medium","Low"))) -> Medium | J15: Rise-and-fall clause in contract | K15: B. Toure | L15: Open | O15: 1 | P15: 3 | Q15: =IF(OR(O15="",P15=""),"",O15*P15) -> 3 | R15: =IF(OR(H15="",Q15=""),"",1-Q15/H15) -> 0.75
A16: R-012 | B16: P07 | C16: 46247 | D16: Pit wall instability on east wall | E16: Technical | F16: 3 | G16: 2 | H16: =IF(OR(F16="",G16=""),"",F16*G16) -> 6 | I16: =IF(H16="","",IF(H16>=15,"High",IF(H16>=8,"Medium","Low"))) -> Low | J16: Geotech monitoring radar + reduced bench height | K16: I. Sylla | L16: Open | O16: 1 | P16: 1 | Q16: =IF(OR(O16="",P16=""),"",O16*P16) -> 1 | R16: =IF(OR(H16="",Q16=""),"",1-Q16/H16) -> 0.83333333
A17: R-013 | B17: P04 | C17: 46095 | D17: Fuel price increase | E17: Commercial | F17: 5 | G17: 4 | H17: =IF(OR(F17="",G17=""),"",F17*G17) -> 20 | I17: =IF(H17="","",IF(H17>=15,"High",IF(H17>=8,"Medium","Low"))) -> High | J17: Rise-and-fall clause in contract | K17: A. Camara | L17: Mitigated | M17: 46131 | N17: No | O17: 3 | P17: 4 | Q17: =IF(OR(O17="",P17=""),"",O17*P17) -> 12 | R17: =IF(OR(H17="",Q17=""),"",1-Q17/H17) -> 0.4
A18: R-014 | B18: P01 | C18: 46151 | D18: Fuel price increase | E18: Commercial | F18: 2 | G18: 5 | H18: =IF(OR(F18="",G18=""),"",F18*G18) -> 10 | I18: =IF(H18="","",IF(H18>=15,"High",IF(H18>=8,"Medium","Low"))) -> Medium | J18: Rise-and-fall clause in contract | K18: I. Sylla | L18: Mitigated | M18: 46221 | N18: No | O18: 1 | P18: 4 | Q18: =IF(OR(O18="",P18=""),"",O18*P18) -> 4 | R18: =IF(OR(H18="",Q18=""),"",1-Q18/H18) -> 0.6
A19: R-015 | B19: P06 | C19: 46055 | D19: Community road blockage | E19: Community | F19: 3 | G19: 3 | H19: =IF(OR(F19="",G19=""),"",F19*G19) -> 9 | I19: =IF(H19="","",IF(H19>=15,"High",IF(H19>=8,"Medium","Low"))) -> Medium | J19: Weekly liaison meetings with village committee | K19: F. Bah | L19: Open | O19: 1 | P19: 1 | Q19: =IF(OR(O19="",P19=""),"",O19*P19) -> 1 | R19: =IF(OR(H19="",Q19=""),"",1-Q19/H19) -> 0.88888889
A20: R-016 | B20: P07 | C20: 46187 | D20: Pit wall instability on east wall | E20: Technical | F20: 5 | G20: 3 | H20: =IF(OR(F20="",G20=""),"",F20*G20) -> 15 | I20: =IF(H20="","",IF(H20>=15,"High",IF(H20>=8,"Medium","Low"))) -> High | J20: Geotech monitoring radar + reduced bench height | K20: B. Toure | L20: Open | O20: 4 | P20: 1 | Q20: =IF(OR(O20="",P20=""),"",O20*P20) -> 4 | R20: =IF(OR(H20="",Q20=""),"",1-Q20/H20) -> 0.73333333
A21: R-017 | B21: P03 | C21: 46320 | D21: Late delivery of rebuild kits | E21: Supply chain | F21: 4 | G21: 5 | H21: =IF(OR(F21="",G21=""),"",F21*G21) -> 20 | I21: =IF(H21="","",IF(H21>=15,"High",IF(H21>=8,"Medium","Low"))) -> High | J21: Order 8 weeks early, second supplier | K21: B. Toure | L21: Open | O21: 1 | P21: 5 | Q21: =IF(OR(O21="",P21=""),"",O21*P21) -> 5 | R21: =IF(OR(H21="",Q21=""),"",1-Q21/H21) -> 0.75
A22: R-018 | B22: P07 | C22: 46214 | D22: Community road blockage | E22: Community | F22: 4 | G22: 4 | H22: =IF(OR(F22="",G22=""),"",F22*G22) -> 16 | I22: =IF(H22="","",IF(H22>=15,"High",IF(H22>=8,"Medium","Low"))) -> High | J22: Weekly liaison meetings with village committee | K22: F. Bah | L22: Open | O22: 1 | P22: 3 | Q22: =IF(OR(O22="",P22=""),"",O22*P22) -> 3 | R22: =IF(OR(H22="",Q22=""),"",1-Q22/H22) -> 0.8125
A23: R-019 | B23: P08 | C23: 46158 | D23: Key engineer resignation | E23: Schedule | F23: 2 | G23: 3 | H23: =IF(OR(F23="",G23=""),"",F23*G23) -> 6 | I23: =IF(H23="","",IF(H23>=15,"High",IF(H23>=8,"Medium","Low"))) -> Low | J23: Cross-training and handover notes | K23: K. Conde | L23: Mitigated | M23: 46177 | N23: No | O23: 1 | P23: 3 | Q23: =IF(OR(O23="",P23=""),"",O23*P23) -> 3 | R23: =IF(OR(H23="",Q23=""),"",1-Q23/H23) -> 0.5
A24: R-020 | B24: P05 | C24: 46248 | D24: Late delivery of rebuild kits | E24: Supply chain | F24: 3 | G24: 3 | H24: =IF(OR(F24="",G24=""),"",F24*G24) -> 9 | I24: =IF(H24="","",IF(H24>=15,"High",IF(H24>=8,"Medium","Low"))) -> Medium | J24: Order 8 weeks early, second supplier | K24: F. Bah | L24: Mitigated | M24: 46284 | N24: No | O24: 2 | P24: 2 | Q24: =IF(OR(O24="",P24=""),"",O24*P24) -> 4 | R24: =IF(OR(H24="",Q24=""),"",1-Q24/H24) -> 0.55555556
A25: R-021 | B25: P05 | C25: 46046 | D25: Key engineer resignation | E25: Schedule | F25: 5 | G25: 5 | H25: =IF(OR(F25="",G25=""),"",F25*G25) -> 25 | I25: =IF(H25="","",IF(H25>=15,"High",IF(H25>=8,"Medium","Low"))) -> High | J25: Cross-training and handover notes | K25: K. Conde | L25: Open | O25: 4 | P25: 4 | Q25: =IF(OR(O25="",P25=""),"",O25*P25) -> 16 | R25: =IF(OR(H25="",Q25=""),"",1-Q25/H25) -> 0.36
A26: R-022 | B26: P04 | C26: 46038 | D26: Community road blockage | E26: Community | F26: 4 | G26: 3 | H26: =IF(OR(F26="",G26=""),"",F26*G26) -> 12 | I26: =IF(H26="","",IF(H26>=15,"High",IF(H26>=8,"Medium","Low"))) -> Medium | J26: Weekly liaison meetings with village committee | K26: M. Diallo | L26: Open | O26: 1 | P26: 1 | Q26: =IF(OR(O26="",P26=""),"",O26*P26) -> 1 | R26: =IF(OR(H26="",Q26=""),"",1-Q26/H26) -> 0.91666667
A27: R-023 | B27: P01 | C27: 46150 | D27: Key engineer resignation | E27: Schedule | F27: 5 | G27: 5 | H27: =IF(OR(F27="",G27=""),"",F27*G27) -> 25 | I27: =IF(H27="","",IF(H27>=15,"High",IF(H27>=8,"Medium","Low"))) -> High | J27: Cross-training and handover notes | K27: O. Traore | L27: Occurred | M27: 46184 | N27: Yes | O27: 4 | P27: 5 | Q27: =IF(OR(O27="",P27=""),"",O27*P27) -> 20 | R27: =IF(OR(H27="",Q27=""),"",1-Q27/H27) -> 0.2
A28: R-024 | B28: P02 | C28: 46253 | D28: ERP data migration errors | E28: Technical | F28: 2 | G28: 2 | H28: =IF(OR(F28="",G28=""),"",F28*G28) -> 4 | I28: =IF(H28="","",IF(H28>=15,"High",IF(H28>=8,"Medium","Low"))) -> Low | J28: Trial migration and reconciliation | K28: F. Bah | L28: Mitigated | M28: 46320 | N28: No | O28: 1 | P28: 2 | Q28: =IF(OR(O28="",P28=""),"",O28*P28) -> 2 | R28: =IF(OR(H28="",Q28=""),"",1-Q28/H28) -> 0.5
A29: R-025 | B29: P01 | C29: 46086 | D29: Heavy rain flooding pit floor | E29: Environmental | F29: 5 | G29: 2 | H29: =IF(OR(F29="",G29=""),"",F29*G29) -> 10 | I29: =IF(H29="","",IF(H29>=15,"High",IF(H29>=8,"Medium","Low"))) -> Medium | J29: Upgrade pumps, sump preparation before season | K29: I. Sylla | L29: Closed | M29: 46103 | N29: No | O29: 4 | P29: 1 | Q29: =IF(OR(O29="",P29=""),"",O29*P29) -> 4 | R29: =IF(OR(H29="",Q29=""),"",1-Q29/H29) -> 0.6
A30: R-026 | B30: P04 | C30: 46102 | D30: Community road blockage | E30: Community | F30: 5 | G30: 2 | H30: =IF(OR(F30="",G30=""),"",F30*G30) -> 10 | I30: =IF(H30="","",IF(H30>=15,"High",IF(H30>=8,"Medium","Low"))) -> Medium | J30: Weekly liaison meetings with village committee | K30: A. Camara | L30: Closed | M30: 46136 | N30: No | O30: 3 | P30: 1 | Q30: =IF(OR(O30="",P30=""),"",O30*P30) -> 3 | R30: =IF(OR(H30="",Q30=""),"",1-Q30/H30) -> 0.7
A31: R-027 | B31: P08 | C31: 46040 | D31: Community road blockage | E31: Community | F31: 5 | G31: 4 | H31: =IF(OR(F31="",G31=""),"",F31*G31) -> 20 | I31: =IF(H31="","",IF(H31>=15,"High",IF(H31>=8,"Medium","Low"))) -> High | J31: Weekly liaison meetings with village committee | K31: F. Bah | L31: Open | O31: 2 | P31: 4 | Q31: =IF(OR(O31="",P31=""),"",O31*P31) -> 8 | R31: =IF(OR(H31="",Q31=""),"",1-Q31/H31) -> 0.6
A32: R-028 | B32: P04 | C32: 46273 | D32: Pit wall instability on east wall | E32: Technical | F32: 5 | G32: 4 | H32: =IF(OR(F32="",G32=""),"",F32*G32) -> 20 | I32: =IF(H32="","",IF(H32>=15,"High",IF(H32>=8,"Medium","Low"))) -> High | J32: Geotech monitoring radar + reduced bench height | K32: O. Traore | L32: Mitigated | M32: 46300 | N32: No | O32: 4 | P32: 3 | Q32: =IF(OR(O32="",P32=""),"",O32*P32) -> 12 | R32: =IF(OR(H32="",Q32=""),"",1-Q32/H32) -> 0.4
H33: =IF(OR(F33="",G33=""),"",F33*G33) | I33: =IF(H33="","",IF(H33>=15,"High",IF(H33>=8,"Medium","Low"))) | Q33: =IF(OR(O33="",P33=""),"",O33*P33) | R33: =IF(OR(H33="",Q33=""),"",1-Q33/H33)
H34: =IF(OR(F34="",G34=""),"",F34*G34) | I34: =IF(H34="","",IF(H34>=15,"High",IF(H34>=8,"Medium","Low"))) | Q34: =IF(OR(O34="",P34=""),"",O34*P34) | R34: =IF(OR(H34="",Q34=""),"",1-Q34/H34)
H35: =IF(OR(F35="",G35=""),"",F35*G35) | I35: =IF(H35="","",IF(H35>=15,"High",IF(H35>=8,"Medium","Low"))) | Q35: =IF(OR(O35="",P35=""),"",O35*P35) | R35: =IF(OR(H35="",Q35=""),"",1-Q35/H35)
H36: =IF(OR(F36="",G36=""),"",F36*G36) | I36: =IF(H36="","",IF(H36>=15,"High",IF(H36>=8,"Medium","Low"))) | Q36: =IF(OR(O36="",P36=""),"",O36*P36) | R36: =IF(OR(H36="",Q36=""),"",1-Q36/H36)
H37: =IF(OR(F37="",G37=""),"",F37*G37) | I37: =IF(H37="","",IF(H37>=15,"High",IF(H37>=8,"Medium","Low"))) | Q37: =IF(OR(O37="",P37=""),"",O37*P37) | R37: =IF(OR(H37="",Q37=""),"",1-Q37/H37)
H38: =IF(OR(F38="",G38=""),"",F38*G38) | I38: =IF(H38="","",IF(H38>=15,"High",IF(H38>=8,"Medium","Low"))) | Q38: =IF(OR(O38="",P38=""),"",O38*P38) | R38: =IF(OR(H38="",Q38=""),"",1-Q38/H38)
H39: =IF(OR(F39="",G39=""),"",F39*G39) | I39: =IF(H39="","",IF(H39>=15,"High",IF(H39>=8,"Medium","Low"))) | Q39: =IF(OR(O39="",P39=""),"",O39*P39) | R39: =IF(OR(H39="",Q39=""),"",1-Q39/H39)
H40: =IF(OR(F40="",G40=""),"",F40*G40) | I40: =IF(H40="","",IF(H40>=15,"High",IF(H40>=8,"Medium","Low"))) | Q40: =IF(OR(O40="",P40=""),"",O40*P40) | R40: =IF(OR(H40="",Q40=""),"",1-Q40/H40)
H41: =IF(OR(F41="",G41=""),"",F41*G41) | I41: =IF(H41="","",IF(H41>=15,"High",IF(H41>=8,"Medium","Low"))) | Q41: =IF(OR(O41="",P41=""),"",O41*P41) | R41: =IF(OR(H41="",Q41=""),"",1-Q41/H41)
H42: =IF(OR(F42="",G42=""),"",F42*G42) | I42: =IF(H42="","",IF(H42>=15,"High",IF(H42>=8,"Medium","Low"))) | Q42: =IF(OR(O42="",P42=""),"",O42*P42) | R42: =IF(OR(H42="",Q42=""),"",1-Q42/H42)
H43: =IF(OR(F43="",G43=""),"",F43*G43) | I43: =IF(H43="","",IF(H43>=15,"High",IF(H43>=8,"Medium","Low"))) | Q43: =IF(OR(O43="",P43=""),"",O43*P43) | R43: =IF(OR(H43="",Q43=""),"",1-Q43/H43)
H44: =IF(OR(F44="",G44=""),"",F44*G44) | I44: =IF(H44="","",IF(H44>=15,"High",IF(H44>=8,"Medium","Low"))) | Q44: =IF(OR(O44="",P44=""),"",O44*P44) | R44: =IF(OR(H44="",Q44=""),"",1-Q44/H44)
... H504: =IF(OR(F504="",G504=""),"",F504*G504) | I504: =IF(H504="","",IF(H504>=15,"High",IF(H504>=8,"Medium","Low"))) | Q504: =IF(OR(O504="",P504=""),"",O504*P504) | R504: =IF(OR(H504="",Q504=""),"",1-Q504/H504)

Sheet Issue_Log
A1: Issue Log
A2: Issues = problems happening now (risks that occurred, defects, blockers). Resolution days feed Issue Resolution Time.
A4: Issue ID | B4: Project ID | C4: Date raised | D4: Issue description | E4: Priority | F4: Owner | G4: Status | H4: Date resolved | I4: Days to resolve | J4: Days open (if open) | K4: Root cause | L4: Remarks
A5: I-001 | B5: P06 | C5: 46181 | D5: Dust complaint from village | E5: Low | F5: K. Conde | G5: Resolved | H5: 46182 | I5: =IF(OR(C5="",H5=""),"",H5-C5) -> 1 | J5: =IF(OR(C5="",H5<>""),"",TODAY()-C5) | K5: Water cart breakdown
A6: I-002 | B6: P05 | C6: 46210 | D6: Excavator breakdown – no spare boom cylinder | E6: Critical | F6: F. Bah | G6: Resolved | H6: 46223 | I6: =IF(OR(C6="",H6=""),"",H6-C6) -> 13 | J6: =IF(OR(C6="",H6<>""),"",TODAY()-C6) | K6: Spares stock-out
A7: I-003 | B7: P04 | C7: 46241 | D7: ERP user access not granted | E7: High | F7: B. Toure | G7: Resolved | H7: 46254 | I7: =IF(OR(C7="",H7=""),"",H7-C7) -> 13 | J7: =IF(OR(C7="",H7<>""),"",TODAY()-C7) | K7: IT approval workflow
A8: I-004 | B8: P08 | C8: 46121 | D8: ERP user access not granted | E8: High | F8: F. Bah | G8: Resolved | H8: 46123 | I8: =IF(OR(C8="",H8=""),"",H8-C8) -> 2 | J8: =IF(OR(C8="",H8<>""),"",TODAY()-C8) | K8: IT approval workflow
A9: I-005 | B9: P03 | C9: 46248 | D9: Excavator breakdown – no spare boom cylinder | E9: Low | F9: A. Camara | G9: Resolved | H9: 46258 | I9: =IF(OR(C9="",H9=""),"",H9-C9) -> 10 | J9: =IF(OR(C9="",H9<>""),"",TODAY()-C9) | K9: Spares stock-out
A10: I-006 | B10: P01 | C10: 46113 | D10: Concrete batch failed slump test | E10: Critical | F10: S. Keita | G10: Resolved | H10: 46120 | I10: =IF(OR(C10="",H10=""),"",H10-C10) -> 7 | J10: =IF(OR(C10="",H10<>""),"",TODAY()-C10) | K10: Supplier QC
A11: I-007 | B11: P02 | C11: 46218 | D11: Pump discharge line leaking | E11: Critical | F11: S. Keita | G11: Resolved | H11: 46230 | I11: =IF(OR(C11="",H11=""),"",H11-C11) -> 12 | J11: =IF(OR(C11="",H11<>""),"",TODAY()-C11) | K11: Poor installation
A12: I-008 | B12: P08 | C12: 46180 | D12: Concrete batch failed slump test | E12: Critical | F12: I. Sylla | G12: Resolved | H12: 46191 | I12: =IF(OR(C12="",H12=""),"",H12-C12) -> 11 | J12: =IF(OR(C12="",H12<>""),"",TODAY()-C12) | K12: Supplier QC
A13: I-009 | B13: P03 | C13: 46215 | D13: Pump discharge line leaking | E13: Critical | F13: A. Camara | G13: Resolved | H13: 46223 | I13: =IF(OR(C13="",H13=""),"",H13-C13) -> 8 | J13: =IF(OR(C13="",H13<>""),"",TODAY()-C13) | K13: Poor installation
A14: I-010 | B14: P07 | C14: 46062 | D14: Survey pickup missing for bench 3 | E14: Critical | F14: F. Bah | G14: Resolved | H14: 46074 | I14: =IF(OR(C14="",H14=""),"",H14-C14) -> 12 | J14: =IF(OR(C14="",H14<>""),"",TODAY()-C14) | K14: Surveyor rostered off
A15: I-011 | B15: P07 | C15: 46215 | D15: ERP user access not granted | E15: Critical | F15: A. Camara | G15: Resolved | H15: 46229 | I15: =IF(OR(C15="",H15=""),"",H15-C15) -> 14 | J15: =IF(OR(C15="",H15<>""),"",TODAY()-C15) | K15: IT approval workflow
A16: I-012 | B16: P08 | C16: 46241 | D16: Pump discharge line leaking | E16: High | F16: K. Conde | G16: Resolved | H16: 46250 | I16: =IF(OR(C16="",H16=""),"",H16-C16) -> 9 | J16: =IF(OR(C16="",H16<>""),"",TODAY()-C16) | K16: Poor installation
... A33: I-029 | B33: P02 | C33: 46175 | D33: ERP user access not granted | E33: Critical | F33: F. Bah | G33: Resolved | H33: 46179 | I33: =IF(OR(C33="",H33=""),"",H33-C33) -> 4 | J33: =IF(OR(C33="",H33<>""),"",TODAY()-C33) | K33: IT approval workflow
A34: I-030 | B34: P03 | C34: 46314 | D34: Blast delayed – explosives truck late | E34: Low | F34: I. Sylla | G34: In progress | I34: =IF(OR(C34="",H34=""),"",H34-C34) | J34: =IF(OR(C34="",H34<>""),"",TODAY()-C34) -> 10 | K34: Logistics
A35: I-031 | B35: P01 | C35: 46026 | D35: Pump discharge line leaking | E35: Medium | F35: K. Conde | G35: Resolved | H35: 46033 | I35: =IF(OR(C35="",H35=""),"",H35-C35) -> 7 | J35: =IF(OR(C35="",H35<>""),"",TODAY()-C35) | K35: Poor installation
A36: I-032 | B36: P01 | C36: 46083 | D36: Blast delayed – explosives truck late | E36: High | F36: A. Camara | G36: Resolved | H36: 46092 | I36: =IF(OR(C36="",H36=""),"",H36-C36) -> 9 | J36: =IF(OR(C36="",H36<>""),"",TODAY()-C36) | K36: Logistics
A37: I-033 | B37: P05 | C37: 46187 | D37: Pump discharge line leaking | E37: Critical | F37: F. Bah | G37: Resolved | H37: 46190 | I37: =IF(OR(C37="",H37=""),"",H37-C37) -> 3 | J37: =IF(OR(C37="",H37<>""),"",TODAY()-C37) | K37: Poor installation
A38: I-034 | B38: P08 | C38: 46048 | D38: Dust complaint from village | E38: Critical | F38: O. Traore | G38: Resolved | H38: 46066 | I38: =IF(OR(C38="",H38=""),"",H38-C38) -> 18 | J38: =IF(OR(C38="",H38<>""),"",TODAY()-C38) | K38: Water cart breakdown
A39: I-035 | B39: P03 | C39: 46079 | D39: Contractor invoice disputed | E39: Critical | F39: S. Keita | G39: Resolved | H39: 46097 | I39: =IF(OR(C39="",H39=""),"",H39-C39) -> 18 | J39: =IF(OR(C39="",H39<>""),"",TODAY()-C39) | K39: Unclear rates
A40: I-036 | B40: P05 | C40: 46226 | D40: ERP user access not granted | E40: Medium | F40: O. Traore | G40: Resolved | H40: 46233 | I40: =IF(OR(C40="",H40=""),"",H40-C40) -> 7 | J40: =IF(OR(C40="",H40<>""),"",TODAY()-C40) | K40: IT approval workflow
A41: I-037 | B41: P07 | C41: 46032 | D41: Pump discharge line leaking | E41: Critical | F41: K. Conde | G41: Resolved | H41: 46046 | I41: =IF(OR(C41="",H41=""),"",H41-C41) -> 14 | J41: =IF(OR(C41="",H41<>""),"",TODAY()-C41) | K41: Poor installation
A42: I-038 | B42: P01 | C42: 46125 | D42: Contractor invoice disputed | E42: Low | F42: S. Keita | G42: Resolved | H42: 46129 | I42: =IF(OR(C42="",H42=""),"",H42-C42) -> 4 | J42: =IF(OR(C42="",H42<>""),"",TODAY()-C42) | K42: Unclear rates
A43: I-039 | B43: P06 | C43: 46207 | D43: Survey pickup missing for bench 3 | E43: Low | F43: S. Keita | G43: Resolved | H43: 46214 | I43: =IF(OR(C43="",H43=""),"",H43-C43) -> 7 | J43: =IF(OR(C43="",H43<>""),"",TODAY()-C43) | K43: Surveyor rostered off
A44: I-040 | B44: P03 | C44: 46082 | D44: Excavator breakdown – no spare boom cylinder | E44: Low | F44: M. Diallo | G44: Resolved | H44: 46100 | I44: =IF(OR(C44="",H44=""),"",H44-C44) -> 18 | J44: =IF(OR(C44="",H44<>""),"",TODAY()-C44) | K44: Spares stock-out
I45: =IF(OR(C45="",H45=""),"",H45-C45) | J45: =IF(OR(C45="",H45<>""),"",TODAY()-C45)
I46: =IF(OR(C46="",H46=""),"",H46-C46) | J46: =IF(OR(C46="",H46<>""),"",TODAY()-C46)
I47: =IF(OR(C47="",H47=""),"",H47-C47) | J47: =IF(OR(C47="",H47<>""),"",TODAY()-C47)
I48: =IF(OR(C48="",H48=""),"",H48-C48) | J48: =IF(OR(C48="",H48<>""),"",TODAY()-C48)
I49: =IF(OR(C49="",H49=""),"",H49-C49) | J49: =IF(OR(C49="",H49<>""),"",TODAY()-C49)
I50: =IF(OR(C50="",H50=""),"",H50-C50) | J50: =IF(OR(C50="",H50<>""),"",TODAY()-C50)
I51: =IF(OR(C51="",H51=""),"",H51-C51) | J51: =IF(OR(C51="",H51<>""),"",TODAY()-C51)
I52: =IF(OR(C52="",H52=""),"",H52-C52) | J52: =IF(OR(C52="",H52<>""),"",TODAY()-C52)
I53: =IF(OR(C53="",H53=""),"",H53-C53) | J53: =IF(OR(C53="",H53<>""),"",TODAY()-C53)
I54: =IF(OR(C54="",H54=""),"",H54-C54) | J54: =IF(OR(C54="",H54<>""),"",TODAY()-C54)
I55: =IF(OR(C55="",H55=""),"",H55-C55) | J55: =IF(OR(C55="",H55<>""),"",TODAY()-C55)
I56: =IF(OR(C56="",H56=""),"",H56-C56) | J56: =IF(OR(C56="",H56<>""),"",TODAY()-C56)
... I504: =IF(OR(C504="",H504=""),"",H504-C504) | J504: =IF(OR(C504="",H504<>""),"",TODAY()-C504)

Sheet Stakeholder_Survey
A1: Stakeholder Satisfaction Survey
A2: Score each criterion 1 (very poor) to 5 (excellent). Overall = average of the four criteria.
A4: Survey date | B4: Project ID | C4: Stakeholder name | D4: Stakeholder group | E4: Communication | F4: Delivery vs plan | G4: Quality of outputs | H4: Responsiveness | I4: Overall score | J4: Comments
A5: 46045 | B5: P06 | C5: Stakeholder 1 | D5: Subcontractor | E5: 4 | F5: 4 | G5: 4 | H5: 4 | I5: =IF(COUNT(E5:H5)=0,"",AVERAGE(E5:H5)) -> 4
A6: 46060 | B6: P02 | C6: Stakeholder 2 | D6: Internal – Management | E6: 2 | F6: 4 | G6: 4 | H6: 3 | I6: =IF(COUNT(E6:H6)=0,"",AVERAGE(E6:H6)) -> 3.25
A7: 46090 | B7: P01 | C7: Stakeholder 3 | D7: Internal – Management | E7: 3 | F7: 4 | G7: 3 | H7: 3 | I7: =IF(COUNT(E7:H7)=0,"",AVERAGE(E7:H7)) -> 3.25
A8: 46136 | B8: P03 | C8: Stakeholder 4 | D8: Client – Owner's team | E8: 3 | F8: 3 | G8: 4 | H8: 4 | I8: =IF(COUNT(E8:H8)=0,"",AVERAGE(E8:H8)) -> 3.5
A9: 46165 | B9: P04 | C9: Stakeholder 5 | D9: Client – Mine Manager | E9: 3 | F9: 4 | G9: 4 | H9: 4 | I9: =IF(COUNT(E9:H9)=0,"",AVERAGE(E9:H9)) -> 3.75
A10: 46185 | B10: P04 | C10: Stakeholder 6 | D10: Client – Mine Manager | E10: 5 | F10: 3 | G10: 3 | H10: 3 | I10: =IF(COUNT(E10:H10)=0,"",AVERAGE(E10:H10)) -> 3.5
A11: 46218 | B11: P02 | C11: Stakeholder 7 | D11: Internal – Management | E11: 3 | F11: 3 | G11: 4 | H11: 4 | I11: =IF(COUNT(E11:H11)=0,"",AVERAGE(E11:H11)) -> 3.5
A12: 46252 | B12: P05 | C12: Stakeholder 8 | D12: Subcontractor | E12: 4 | F12: 5 | G12: 3 | H12: 4 | I12: =IF(COUNT(E12:H12)=0,"",AVERAGE(E12:H12)) -> 4
A13: 46275 | B13: P01 | C13: Stakeholder 9 | D13: Client – Mine Manager | E13: 4 | F13: 4 | G13: 4 | H13: 5 | I13: =IF(COUNT(E13:H13)=0,"",AVERAGE(E13:H13)) -> 4.25
A14: 46314 | B14: P03 | C14: Stakeholder 10 | D14: Internal – Management | E14: 4 | F14: 4 | G14: 4 | H14: 5 | I14: =IF(COUNT(E14:H14)=0,"",AVERAGE(E14:H14)) -> 4.25
A15: 46041 | B15: P01 | C15: Stakeholder 11 | D15: Client – Mine Manager | E15: 3 | F15: 3 | G15: 3 | H15: 2 | I15: =IF(COUNT(E15:H15)=0,"",AVERAGE(E15:H15)) -> 2.75
A16: 46074 | B16: P02 | C16: Stakeholder 12 | D16: Client – Mine Manager | E16: 4 | F16: 2 | G16: 3 | H16: 3 | I16: =IF(COUNT(E16:H16)=0,"",AVERAGE(E16:H16)) -> 3
... A40: 46184 | B40: P03 | C40: Stakeholder 36 | D40: Community | E40: 4 | F40: 4 | G40: 3 | H40: 3 | I40: =IF(COUNT(E40:H40)=0,"",AVERAGE(E40:H40)) -> 3.5
I41: =IF(COUNT(E41:H41)=0,"",AVERAGE(E41:H41))
I42: =IF(COUNT(E42:H42)=0,"",AVERAGE(E42:H42))
I43: =IF(COUNT(E43:H43)=0,"",AVERAGE(E43:H43))
I44: =IF(COUNT(E44:H44)=0,"",AVERAGE(E44:H44))
I45: =IF(COUNT(E45:H45)=0,"",AVERAGE(E45:H45))
I46: =IF(COUNT(E46:H46)=0,"",AVERAGE(E46:H46))
I47: =IF(COUNT(E47:H47)=0,"",AVERAGE(E47:H47))
I48: =IF(COUNT(E48:H48)=0,"",AVERAGE(E48:H48))
I49: =IF(COUNT(E49:H49)=0,"",AVERAGE(E49:H49))
I50: =IF(COUNT(E50:H50)=0,"",AVERAGE(E50:H50))
I51: =IF(COUNT(E51:H51)=0,"",AVERAGE(E51:H51))
I52: =IF(COUNT(E52:H52)=0,"",AVERAGE(E52:H52))
... I504: =IF(COUNT(E504:H504)=0,"",AVERAGE(E504:H504))

Sheet Resources
A1: Resource Utilisation & Team Productivity – monthly per team
A2: Available = paid/rostered hours. Allocated = hours booked to project work. Output unit is team-specific (e.g. m drilled, t moved).
A4: Month | B4: Team / resource | C4: Discipline | D4: Available hours | E4: Allocated project hours | F4: Utilisation | G4: Output unit | H4: Planned output | I4: Actual output | J4: Productivity (actual/plan) | K4: Remarks
A5: 46023 | B5: Drill & Blast crew | C5: Drill & Blast | D5: 2080 | E5: 1726 | F5: =IF(OR(D5="",D5=0,E5=""),"",E5/D5) -> 0.82980769 | G5: m drilled | H5: 9000 | I5: 8743 | J5: =IF(OR(H5="",H5=0,I5=""),"",I5/H5) -> 0.97144444
A6: 46023 | B6: Load & Haul crew | C6: Mining | D6: 1760 | E6: 1589 | F6: =IF(OR(D6="",D6=0,E6=""),"",E6/D6) -> 0.90284091 | G6: kt moved | H6: 900 | I6: 857 | J6: =IF(OR(H6="",H6=0,I6=""),"",I6/H6) -> 0.95222222
A7: 46023 | B7: Maintenance team | C7: Maintenance | D7: 1840 | E7: 1561 | F7: =IF(OR(D7="",D7=0,E7=""),"",E7/D7) -> 0.84836957 | G7: work orders | H7: 160 | I7: 148 | J7: =IF(OR(H7="",H7=0,I7=""),"",I7/H7) -> 0.925
A8: 46023 | B8: Projects & Engineering | C8: Engineering | D8: 1840 | E8: 1498 | F8: =IF(OR(D8="",D8=0,E8=""),"",E8/D8) -> 0.81413043 | G8: deliverables | H8: 24 | I8: 24 | J8: =IF(OR(H8="",H8=0,I8=""),"",I8/H8) -> 1
A9: 46054 | B9: Drill & Blast crew | C9: Drill & Blast | D9: 1840 | E9: 1412 | F9: =IF(OR(D9="",D9=0,E9=""),"",E9/D9) -> 0.7673913 | G9: m drilled | H9: 9000 | I9: 7791 | J9: =IF(OR(H9="",H9=0,I9=""),"",I9/H9) -> 0.86566667
A10: 46054 | B10: Load & Haul crew | C10: Mining | D10: 1760 | E10: 1510 | F10: =IF(OR(D10="",D10=0,E10=""),"",E10/D10) -> 0.85795455 | G10: kt moved | H10: 900 | I10: 805 | J10: =IF(OR(H10="",H10=0,I10=""),"",I10/H10) -> 0.89444444
A11: 46054 | B11: Maintenance team | C11: Maintenance | D11: 1840 | E11: 1607 | F11: =IF(OR(D11="",D11=0,E11=""),"",E11/D11) -> 0.87336957 | G11: work orders | H11: 160 | I11: 139 | J11: =IF(OR(H11="",H11=0,I11=""),"",I11/H11) -> 0.86875
A12: 46054 | B12: Projects & Engineering | C12: Engineering | D12: 1840 | E12: 1604 | F12: =IF(OR(D12="",D12=0,E12=""),"",E12/D12) -> 0.87173913 | G12: deliverables | H12: 24 | I12: 24 | J12: =IF(OR(H12="",H12=0,I12=""),"",I12/H12) -> 1
A13: 46082 | B13: Drill & Blast crew | C13: Drill & Blast | D13: 1760 | E13: 1549 | F13: =IF(OR(D13="",D13=0,E13=""),"",E13/D13) -> 0.88011364 | G13: m drilled | H13: 9000 | I13: 7864 | J13: =IF(OR(H13="",H13=0,I13=""),"",I13/H13) -> 0.87377778
A14: 46082 | B14: Load & Haul crew | C14: Mining | D14: 1920 | E14: 1494 | F14: =IF(OR(D14="",D14=0,E14=""),"",E14/D14) -> 0.778125 | G14: kt moved | H14: 900 | I14: 954 | J14: =IF(OR(H14="",H14=0,I14=""),"",I14/H14) -> 1.06
A15: 46082 | B15: Maintenance team | C15: Maintenance | D15: 1760 | E15: 1597 | F15: =IF(OR(D15="",D15=0,E15=""),"",E15/D15) -> 0.90738636 | G15: work orders | H15: 160 | I15: 163 | J15: =IF(OR(H15="",H15=0,I15=""),"",I15/H15) -> 1.01875
A16: 46082 | B16: Projects & Engineering | C16: Engineering | D16: 2080 | E16: 1582 | F16: =IF(OR(D16="",D16=0,E16=""),"",E16/D16) -> 0.76057692 | G16: deliverables | H16: 24 | I16: 22 | J16: =IF(OR(H16="",H16=0,I16=""),"",I16/H16) -> 0.91666667
... A44: 46296 | B44: Projects & Engineering | C44: Engineering | D44: 1840 | E44: 1665 | F44: =IF(OR(D44="",D44=0,E44=""),"",E44/D44) -> 0.9048913 | G44: deliverables | H44: 24 | I44: 23 | J44: =IF(OR(H44="",H44=0,I44=""),"",I44/H44) -> 0.95833333
F45: =IF(OR(D45="",D45=0,E45=""),"",E45/D45) | J45: =IF(OR(H45="",H45=0,I45=""),"",I45/H45)
F46: =IF(OR(D46="",D46=0,E46=""),"",E46/D46) | J46: =IF(OR(H46="",H46=0,I46=""),"",I46/H46)
F47: =IF(OR(D47="",D47=0,E47=""),"",E47/D47) | J47: =IF(OR(H47="",H47=0,I47=""),"",I47/H47)
F48: =IF(OR(D48="",D48=0,E48=""),"",E48/D48) | J48: =IF(OR(H48="",H48=0,I48=""),"",I48/H48)
F49: =IF(OR(D49="",D49=0,E49=""),"",E49/D49) | J49: =IF(OR(H49="",H49=0,I49=""),"",I49/H49)
F50: =IF(OR(D50="",D50=0,E50=""),"",E50/D50) | J50: =IF(OR(H50="",H50=0,I50=""),"",I50/H50)
F51: =IF(OR(D51="",D51=0,E51=""),"",E51/D51) | J51: =IF(OR(H51="",H51=0,I51=""),"",I51/H51)
F52: =IF(OR(D52="",D52=0,E52=""),"",E52/D52) | J52: =IF(OR(H52="",H52=0,I52=""),"",I52/H52)
F53: =IF(OR(D53="",D53=0,E53=""),"",E53/D53) | J53: =IF(OR(H53="",H53=0,I53=""),"",I53/H53)
F54: =IF(OR(D54="",D54=0,E54=""),"",E54/D54) | J54: =IF(OR(H54="",H54=0,I54=""),"",I54/H54)
F55: =IF(OR(D55="",D55=0,E55=""),"",E55/D55) | J55: =IF(OR(H55="",H55=0,I55=""),"",I55/H55)
F56: =IF(OR(D56="",D56=0,E56=""),"",E56/D56) | J56: =IF(OR(H56="",H56=0,I56=""),"",I56/H56)
... F504: =IF(OR(D504="",D504=0,E504=""),"",E504/D504) | J504: =IF(OR(H504="",H504=0,I504=""),"",I504/H504)

Sheet Milestones
A1: Milestone Tracker
A2: Keep the BASELINE due date fixed. Enter the actual completion date when done. On time? compares the two.
A4: Milestone ID | B4: Project ID | C4: Milestone | D4: Owner | E4: Baseline due date | F4: Actual / forecast completion | G4: Status | H4: On time? | I4: Days late (+) / early (−) | J4: Remarks
A5: M-001 | B5: P03 | C5: Go-live | D5: B. Toure | E5: 46042 | F5: 46045 | G5: Completed | H5: =IF(E5="","",IF(G5<>"Completed",IF(E5<TODAY(),"Overdue",""),IF(F5<=E5,"Yes","No"))) -> No | I5: =IF(OR(E5="",F5=""),"",F5-E5) -> 3
A6: M-002 | B6: P04 | C6: Procurement complete | D6: K. Conde | E6: 46078 | F6: 46079 | G6: Completed | H6: =IF(E6="","",IF(G6<>"Completed",IF(E6<TODAY(),"Overdue",""),IF(F6<=E6,"Yes","No"))) -> No | I6: =IF(OR(E6="",F6=""),"",F6-E6) -> 1
A7: M-003 | B7: P04 | C7: Commissioning | D7: I. Sylla | E7: 46098 | F7: 46098 | G7: Completed | H7: =IF(E7="","",IF(G7<>"Completed",IF(E7<TODAY(),"Overdue",""),IF(F7<=E7,"Yes","No"))) -> Yes | I7: =IF(OR(E7="",F7=""),"",F7-E7) -> 0
A8: M-004 | B8: P03 | C8: Procurement complete | D8: F. Bah | E8: 46139 | F8: 46139 | G8: Completed | H8: =IF(E8="","",IF(G8<>"Completed",IF(E8<TODAY(),"Overdue",""),IF(F8<=E8,"Yes","No"))) -> Yes | I8: =IF(OR(E8="",F8=""),"",F8-E8) -> 0
A9: M-005 | B9: P06 | C9: Procurement complete | D9: F. Bah | E9: 46168 | F9: 46171 | G9: Completed | H9: =IF(E9="","",IF(G9<>"Completed",IF(E9<TODAY(),"Overdue",""),IF(F9<=E9,"Yes","No"))) -> No | I9: =IF(OR(E9="",F9=""),"",F9-E9) -> 3
A10: M-006 | B10: P05 | C10: Mobilisation complete | D10: S. Keita | E10: 46186 | F10: 46186 | G10: Completed | H10: =IF(E10="","",IF(G10<>"Completed",IF(E10<TODAY(),"Overdue",""),IF(F10<=E10,"Yes","No"))) -> Yes | I10: =IF(OR(E10="",F10=""),"",F10-E10) -> 0
A11: M-007 | B11: P04 | C11: Trial blast completed | D11: S. Keita | E11: 46227 | F11: 46225 | G11: Completed | H11: =IF(E11="","",IF(G11<>"Completed",IF(E11<TODAY(),"Overdue",""),IF(F11<=E11,"Yes","No"))) -> Yes | I11: =IF(OR(E11="",F11=""),"",F11-E11) -> -2
A12: M-008 | B12: P05 | C12: Trial blast completed | D12: I. Sylla | E12: 46241 | F12: 46242 | G12: Completed | H12: =IF(E12="","",IF(G12<>"Completed",IF(E12<TODAY(),"Overdue",""),IF(F12<=E12,"Yes","No"))) -> No | I12: =IF(OR(E12="",F12=""),"",F12-E12) -> 1
A13: M-009 | B13: P02 | C13: Commissioning | D13: F. Bah | E13: 46274 | F13: 46272 | G13: Completed | H13: =IF(E13="","",IF(G13<>"Completed",IF(E13<TODAY(),"Overdue",""),IF(F13<=E13,"Yes","No"))) -> Yes | I13: =IF(OR(E13="",F13=""),"",F13-E13) -> -2
A14: M-010 | B14: P07 | C14: Trial blast completed | D14: F. Bah | E14: 46310 | F14: 46305 | G14: Completed | H14: =IF(E14="","",IF(G14<>"Completed",IF(E14<TODAY(),"Overdue",""),IF(F14<=E14,"Yes","No"))) -> Yes | I14: =IF(OR(E14="",F14=""),"",F14-E14) -> -5
A15: M-011 | B15: P08 | C15: Design approved | D15: S. Keita | E15: 46041 | F15: 46042 | G15: Completed | H15: =IF(E15="","",IF(G15<>"Completed",IF(E15<TODAY(),"Overdue",""),IF(F15<=E15,"Yes","No"))) -> No | I15: =IF(OR(E15="",F15=""),"",F15-E15) -> 1
A16: M-012 | B16: P07 | C16: Design approved | D16: F. Bah | E16: 46064 | F16: 46064 | G16: Completed | H16: =IF(E16="","",IF(G16<>"Completed",IF(E16<TODAY(),"Overdue",""),IF(F16<=E16,"Yes","No"))) -> Yes | I16: =IF(OR(E16="",F16=""),"",F16-E16) -> 0
... A23: M-019 | B23: P05 | C23: 50% construction | D23: S. Keita | E23: 46271 | F23: 46266 | G23: Completed | H23: =IF(E23="","",IF(G23<>"Completed",IF(E23<TODAY(),"Overdue",""),IF(F23<=E23,"Yes","No"))) -> Yes | I23: =IF(OR(E23="",F23=""),"",F23-E23) -> -5
A24: M-020 | B24: P04 | C24: Handover | D24: M. Diallo | E24: 46320 | G24: In progress | H24: =IF(E24="","",IF(G24<>"Completed",IF(E24<TODAY(),"Overdue",""),IF(F24<=E24,"Yes","No"))) -> Overdue | I24: =IF(OR(E24="",F24=""),"",F24-E24)
A25: M-021 | B25: P04 | C25: Go-live | D25: A. Camara | E25: 46043 | F25: 46053 | G25: Completed | H25: =IF(E25="","",IF(G25<>"Completed",IF(E25<TODAY(),"Overdue",""),IF(F25<=E25,"Yes","No"))) -> No | I25: =IF(OR(E25="",F25=""),"",F25-E25) -> 10
A26: M-022 | B26: P06 | C26: Trial blast completed | D26: B. Toure | E26: 46076 | F26: 46079 | G26: Completed | H26: =IF(E26="","",IF(G26<>"Completed",IF(E26<TODAY(),"Overdue",""),IF(F26<=E26,"Yes","No"))) -> No | I26: =IF(OR(E26="",F26=""),"",F26-E26) -> 3
A27: M-023 | B27: P07 | C27: Mobilisation complete | D27: K. Conde | E27: 46090 | F27: 46090 | G27: Completed | H27: =IF(E27="","",IF(G27<>"Completed",IF(E27<TODAY(),"Overdue",""),IF(F27<=E27,"Yes","No"))) -> Yes | I27: =IF(OR(E27="",F27=""),"",F27-E27) -> 0
A28: M-024 | B28: P05 | C28: Commissioning | D28: O. Traore | E28: 46135 | F28: 46130 | G28: Completed | H28: =IF(E28="","",IF(G28<>"Completed",IF(E28<TODAY(),"Overdue",""),IF(F28<=E28,"Yes","No"))) -> Yes | I28: =IF(OR(E28="",F28=""),"",F28-E28) -> -5
A29: M-025 | B29: P01 | C29: Mobilisation complete | D29: O. Traore | E29: 46157 | F29: 46152 | G29: Completed | H29: =IF(E29="","",IF(G29<>"Completed",IF(E29<TODAY(),"Overdue",""),IF(F29<=E29,"Yes","No"))) -> Yes | I29: =IF(OR(E29="",F29=""),"",F29-E29) -> -5
A30: M-026 | B30: P05 | C30: Mobilisation complete | D30: F. Bah | E30: 46189 | F30: 46192 | G30: Completed | H30: =IF(E30="","",IF(G30<>"Completed",IF(E30<TODAY(),"Overdue",""),IF(F30<=E30,"Yes","No"))) -> No | I30: =IF(OR(E30="",F30=""),"",F30-E30) -> 3
A31: M-027 | B31: P04 | C31: Trial blast completed | D31: B. Toure | E31: 46215 | F31: 46221 | G31: Completed | H31: =IF(E31="","",IF(G31<>"Completed",IF(E31<TODAY(),"Overdue",""),IF(F31<=E31,"Yes","No"))) -> No | I31: =IF(OR(E31="",F31=""),"",F31-E31) -> 6
A32: M-028 | B32: P03 | C32: Mobilisation complete | D32: F. Bah | E32: 46243 | F32: 46243 | G32: Completed | H32: =IF(E32="","",IF(G32<>"Completed",IF(E32<TODAY(),"Overdue",""),IF(F32<=E32,"Yes","No"))) -> Yes | I32: =IF(OR(E32="",F32=""),"",F32-E32) -> 0
A33: M-029 | B33: P04 | C33: Procurement complete | D33: K. Conde | E33: 46283 | F33: 46282 | G33: Completed | H33: =IF(E33="","",IF(G33<>"Completed",IF(E33<TODAY(),"Overdue",""),IF(F33<=E33,"Yes","No"))) -> Yes | I33: =IF(OR(E33="",F33=""),"",F33-E33) -> -1
A34: M-030 | B34: P07 | C34: Go-live | D34: I. Sylla | E34: 46319 | G34: In progress | H34: =IF(E34="","",IF(G34<>"Completed",IF(E34<TODAY(),"Overdue",""),IF(F34<=E34,"Yes","No"))) -> Overdue | I34: =IF(OR(E34="",F34=""),"",F34-E34)
A35: M-031 | B35: P03 | C35: Go-live | D35: K. Conde | E35: 46049 | F35: 46048 | G35: Completed | H35: =IF(E35="","",IF(G35<>"Completed",IF(E35<TODAY(),"Overdue",""),IF(F35<=E35,"Yes","No"))) -> Yes | I35: =IF(OR(E35="",F35=""),"",F35-E35) -> -1
A36: M-032 | B36: P05 | C36: Trial blast completed | D36: I. Sylla | E36: 46081 | F36: 46081 | G36: Completed | H36: =IF(E36="","",IF(G36<>"Completed",IF(E36<TODAY(),"Overdue",""),IF(F36<=E36,"Yes","No"))) -> Yes | I36: =IF(OR(E36="",F36=""),"",F36-E36) -> 0
A37: M-033 | B37: P08 | C37: Design approved | D37: I. Sylla | E37: 46097 | F37: 46097 | G37: Completed | H37: =IF(E37="","",IF(G37<>"Completed",IF(E37<TODAY(),"Overdue",""),IF(F37<=E37,"Yes","No"))) -> Yes | I37: =IF(OR(E37="",F37=""),"",F37-E37) -> 0
A38: M-034 | B38: P05 | C38: Handover | D38: B. Toure | E38: 46126 | F38: 46126 | G38: Completed | H38: =IF(E38="","",IF(G38<>"Completed",IF(E38<TODAY(),"Overdue",""),IF(F38<=E38,"Yes","No"))) -> Yes | I38: =IF(OR(E38="",F38=""),"",F38-E38) -> 0
A39: M-035 | B39: P02 | C39: Handover | D39: S. Keita | E39: 46160 | F39: 46166 | G39: Completed | H39: =IF(E39="","",IF(G39<>"Completed",IF(E39<TODAY(),"Overdue",""),IF(F39<=E39,"Yes","No"))) -> No | I39: =IF(OR(E39="",F39=""),"",F39-E39) -> 6
A40: M-036 | B40: P01 | C40: Mobilisation complete | D40: K. Conde | E40: 46185 | F40: 46191 | G40: Completed | H40: =IF(E40="","",IF(G40<>"Completed",IF(E40<TODAY(),"Overdue",""),IF(F40<=E40,"Yes","No"))) -> No | I40: =IF(OR(E40="",F40=""),"",F40-E40) -> 6
A41: M-037 | B41: P06 | C41: Design approved | D41: A. Camara | E41: 46231 | F41: 46231 | G41: Completed | H41: =IF(E41="","",IF(G41<>"Completed",IF(E41<TODAY(),"Overdue",""),IF(F41<=E41,"Yes","No"))) -> Yes | I41: =IF(OR(E41="",F41=""),"",F41-E41) -> 0
A42: M-038 | B42: P05 | C42: Commissioning | D42: M. Diallo | E42: 46243 | F42: 46241 | G42: Completed | H42: =IF(E42="","",IF(G42<>"Completed",IF(E42<TODAY(),"Overdue",""),IF(F42<=E42,"Yes","No"))) -> Yes | I42: =IF(OR(E42="",F42=""),"",F42-E42) -> -2
A43: M-039 | B43: P04 | C43: Procurement complete | D43: B. Toure | E43: 46286 | F43: 46286 | G43: Completed | H43: =IF(E43="","",IF(G43<>"Completed",IF(E43<TODAY(),"Overdue",""),IF(F43<=E43,"Yes","No"))) -> Yes | I43: =IF(OR(E43="",F43=""),"",F43-E43) -> 0
A44: M-040 | B44: P04 | C44: Trial blast completed | D44: S. Keita | E44: 46309 | G44: In progress | H44: =IF(E44="","",IF(G44<>"Completed",IF(E44<TODAY(),"Overdue",""),IF(F44<=E44,"Yes","No"))) -> Overdue | I44: =IF(OR(E44="",F44=""),"",F44-E44)
A45: M-041 | B45: P02 | C45: Commissioning | D45: F. Bah | E45: 46044 | F45: 46044 | G45: Completed | H45: =IF(E45="","",IF(G45<>"Completed",IF(E45<TODAY(),"Overdue",""),IF(F45<=E45,"Yes","No"))) -> Yes | I45: =IF(OR(E45="",F45=""),"",F45-E45) -> 0
A46: M-042 | B46: P02 | C46: Go-live | D46: M. Diallo | E46: 46071 | F46: 46071 | G46: Completed | H46: =IF(E46="","",IF(G46<>"Completed",IF(E46<TODAY(),"Overdue",""),IF(F46<=E46,"Yes","No"))) -> Yes | I46: =IF(OR(E46="",F46=""),"",F46-E46) -> 0
A47: M-043 | B47: P05 | C47: Trial blast completed | D47: F. Bah | E47: 46101 | F47: 46099 | G47: Completed | H47: =IF(E47="","",IF(G47<>"Completed",IF(E47<TODAY(),"Overdue",""),IF(F47<=E47,"Yes","No"))) -> Yes | I47: =IF(OR(E47="",F47=""),"",F47-E47) -> -2
A48: M-044 | B48: P08 | C48: Design approved | D48: B. Toure | E48: 46119 | F48: 46129 | G48: Completed | H48: =IF(E48="","",IF(G48<>"Completed",IF(E48<TODAY(),"Overdue",""),IF(F48<=E48,"Yes","No"))) -> No | I48: =IF(OR(E48="",F48=""),"",F48-E48) -> 10
A49: M-045 | B49: P08 | C49: 50% construction | D49: B. Toure | E49: 46159 | F49: 46159 | G49: Completed | H49: =IF(E49="","",IF(G49<>"Completed",IF(E49<TODAY(),"Overdue",""),IF(F49<=E49,"Yes","No"))) -> Yes | I49: =IF(OR(E49="",F49=""),"",F49-E49) -> 0
A50: M-046 | B50: P01 | C50: Procurement complete | D50: K. Conde | E50: 46181 | F50: 46180 | G50: Completed | H50: =IF(E50="","",IF(G50<>"Completed",IF(E50<TODAY(),"Overdue",""),IF(F50<=E50,"Yes","No"))) -> Yes | I50: =IF(OR(E50="",F50=""),"",F50-E50) -> -1
H51: =IF(E51="","",IF(G51<>"Completed",IF(E51<TODAY(),"Overdue",""),IF(F51<=E51,"Yes","No"))) | I51: =IF(OR(E51="",F51=""),"",F51-E51)
H52: =IF(E52="","",IF(G52<>"Completed",IF(E52<TODAY(),"Overdue",""),IF(F52<=E52,"Yes","No"))) | I52: =IF(OR(E52="",F52=""),"",F52-E52)
H53: =IF(E53="","",IF(G53<>"Completed",IF(E53<TODAY(),"Overdue",""),IF(F53<=E53,"Yes","No"))) | I53: =IF(OR(E53="",F53=""),"",F53-E53)
H54: =IF(E54="","",IF(G54<>"Completed",IF(E54<TODAY(),"Overdue",""),IF(F54<=E54,"Yes","No"))) | I54: =IF(OR(E54="",F54=""),"",F54-E54)
H55: =IF(E55="","",IF(G55<>"Completed",IF(E55<TODAY(),"Overdue",""),IF(F55<=E55,"Yes","No"))) | I55: =IF(OR(E55="",F55=""),"",F55-E55)
H56: =IF(E56="","",IF(G56<>"Completed",IF(E56<TODAY(),"Overdue",""),IF(F56<=E56,"Yes","No"))) | I56: =IF(OR(E56="",F56=""),"",F56-E56)
H57: =IF(E57="","",IF(G57<>"Completed",IF(E57<TODAY(),"Overdue",""),IF(F57<=E57,"Yes","No"))) | I57: =IF(OR(E57="",F57=""),"",F57-E57)
H58: =IF(E58="","",IF(G58<>"Completed",IF(E58<TODAY(),"Overdue",""),IF(F58<=E58,"Yes","No"))) | I58: =IF(OR(E58="",F58=""),"",F58-E58)
H59: =IF(E59="","",IF(G59<>"Completed",IF(E59<TODAY(),"Overdue",""),IF(F59<=E59,"Yes","No"))) | I59: =IF(OR(E59="",F59=""),"",F59-E59)
H60: =IF(E60="","",IF(G60<>"Completed",IF(E60<TODAY(),"Overdue",""),IF(F60<=E60,"Yes","No"))) | I60: =IF(OR(E60="",F60=""),"",F60-E60)
H61: =IF(E61="","",IF(G61<>"Completed",IF(E61<TODAY(),"Overdue",""),IF(F61<=E61,"Yes","No"))) | I61: =IF(OR(E61="",F61=""),"",F61-E61)
H62: =IF(E62="","",IF(G62<>"Completed",IF(E62<TODAY(),"Overdue",""),IF(F62<=E62,"Yes","No"))) | I62: =IF(OR(E62="",F62=""),"",F62-E62)
... H504: =IF(E504="","",IF(G504<>"Completed",IF(E504<TODAY(),"Overdue",""),IF(F504<=E504,"Yes","No"))) | I504: =IF(OR(E504="",F504=""),"",F504-E504)

Sheet Quality_Log
A1: Quality – Deliverable Inspection Log
A2: One row per deliverable inspection. 'Accepted first time' = passed with no rework.
A4: Inspection ID | B4: Project ID | C4: Deliverable | D4: Inspection date | E4: Inspector | F4: Defects found | G4: Accepted first time? | H4: Rework hours | I4: Rework cost | J4: Defect description / root cause
A5: Q-001 | B5: P08 | C5: Road section compaction test | D5: 46038 | E5: K. Conde | F5: 0 | G5: Yes | H5: 0 | I5: 0
A6: Q-002 | B6: P02 | C6: Concrete foundation pour | D6: 46075 | E6: K. Conde | F6: 0 | G6: Yes | H6: 0 | I6: 0
A7: Q-003 | B7: P01 | C7: Bench survey as-built | D7: 46102 | E7: A. Camara | F7: 0 | G7: Yes | H7: 0 | I7: 0
A8: Q-004 | B8: P06 | C8: Blast design pack | D8: 46130 | E8: B. Toure | F8: 0 | G8: Yes | H8: 0 | I8: 0
A9: Q-005 | B9: P03 | C9: Bench survey as-built | D9: 46150 | E9: O. Traore | F9: 0 | G9: Yes | H9: 0 | I9: 0
A10: Q-006 | B10: P06 | C10: Blast design pack | D10: 46196 | E10: K. Conde | F10: 0 | G10: Yes | H10: 0 | I10: 0
A11: Q-007 | B11: P04 | C11: Road section compaction test | D11: 46218 | E11: K. Conde | F11: 0 | G11: Yes | H11: 0 | I11: 0
A12: Q-008 | B12: P01 | C12: Road section compaction test | D12: 46245 | E12: K. Conde | F12: 0 | G12: Yes | H12: 0 | I12: 0
A13: Q-009 | B13: P07 | C13: Pump station install | D13: 46283 | E13: I. Sylla | F13: 0 | G13: Yes | H13: 0 | I13: 0
A14: Q-010 | B14: P06 | C14: Rebuilt truck acceptance | D14: 46317 | E14: B. Toure | F14: 0 | G14: Yes | H14: 0 | I14: 0
A15: Q-011 | B15: P06 | C15: Rebuilt truck acceptance | D15: 46034 | E15: I. Sylla | F15: 0 | G15: Yes | H15: 0 | I15: 0
A16: Q-012 | B16: P02 | C16: Bench survey as-built | D16: 46067 | E16: O. Traore | F16: 0 | G16: Yes | H16: 0 | I16: 0
... A28: Q-024 | B28: P07 | C28: Bench survey as-built | D28: 46114 | E28: M. Diallo | F28: 0 | G28: Yes | H28: 0 | I28: 0
A29: Q-025 | B29: P02 | C29: Concrete foundation pour | D29: 46159 | E29: A. Camara | F29: 1 | G29: No | H29: 17 | I29: 765 | J29: Workmanship
A30: Q-026 | B30: P04 | C30: Accommodation block handover | D30: 46198 | E30: S. Keita | F30: 0 | G30: Yes | H30: 0 | I30: 0
A31: Q-027 | B31: P02 | C31: Road section compaction test | D31: 46225 | E31: B. Toure | F31: 3 | G31: No | H31: 13 | I31: 585 | J31: Wrong material spec
A32: Q-028 | B32: P05 | C32: Bench survey as-built | D32: 46258 | E32: A. Camara | F32: 0 | G32: Yes | H32: 0 | I32: 0
A33: Q-029 | B33: P01 | C33: Blast design pack | D33: 46279 | E33: I. Sylla | F33: 0 | G33: Yes | H33: 0 | I33: 0
A34: Q-030 | B34: P03 | C34: Accommodation block handover | D34: 46316 | E34: A. Camara | F34: 0 | G34: Yes | H34: 0 | I34: 0
A35: Q-031 | B35: P08 | C35: Accommodation block handover | D35: 46045 | E35: S. Keita | F35: 0 | G35: Yes | H35: 0 | I35: 0
A36: Q-032 | B36: P02 | C36: Pump station install | D36: 46075 | E36: S. Keita | F36: 0 | G36: Yes | H36: 0 | I36: 0
A37: Q-033 | B37: P07 | C37: Accommodation block handover | D37: 46095 | E37: B. Toure | F37: 0 | G37: Yes | H37: 0 | I37: 0
A38: Q-034 | B38: P05 | C38: Road section compaction test | D38: 46115 | E38: K. Conde | F38: 5 | G38: No | H38: 25 | I38: 1125 | J38: Out of tolerance
A39: Q-035 | B39: P05 | C39: ERP module UAT | D39: 46151 | E39: O. Traore | F39: 0 | G39: Yes | H39: 0 | I39: 0
A40: Q-036 | B40: P07 | C40: Rebuilt truck acceptance | D40: 46200 | E40: B. Toure | F40: 0 | G40: Yes | H40: 0 | I40: 0
A41: Q-037 | B41: P01 | C41: Pump station install | D41: 46213 | E41: I. Sylla | F41: 0 | G41: Yes | H41: 0 | I41: 0
A42: Q-038 | B42: P01 | C42: Road section compaction test | D42: 46240 | E42: S. Keita | F42: 0 | G42: Yes | H42: 0 | I42: 0
A43: Q-039 | B43: P08 | C43: Pump station install | D43: 46284 | E43: M. Diallo | F43: 0 | G43: Yes | H43: 0 | I43: 0
A44: Q-040 | B44: P08 | C44: ERP module UAT | D44: 46303 | E44: F. Bah | F44: 0 | G44: Yes | H44: 0 | I44: 0
A45: Q-041 | B45: P01 | C45: ERP module UAT | D45: 46038 | E45: F. Bah | F45: 0 | G45: Yes | H45: 0 | I45: 0
A46: Q-042 | B46: P07 | C46: Accommodation block handover | D46: 46072 | E46: M. Diallo | F46: 5 | G46: No | H46: 4 | I46: 180 | J46: Workmanship
A47: Q-043 | B47: P04 | C47: ERP module UAT | D47: 46101 | E47: I. Sylla | F47: 0 | G47: Yes | H47: 0 | I47: 0
A48: Q-044 | B48: P08 | C48: Rebuilt truck acceptance | D48: 46120 | E48: F. Bah | F48: 5 | G48: No | H48: 24 | I48: 1080 | J48: Missing documentation
A49: Q-045 | B49: P05 | C49: Pump station install | D49: 46162 | E49: K. Conde | F49: 0 | G49: Yes | H49: 0 | I49: 0
A50: Q-046 | B50: P03 | C50: Rebuilt truck acceptance | D50: 46176 | E50: B. Toure | F50: 0 | G50: Yes | H50: 0 | I50: 0
A51: Q-047 | B51: P02 | C51: Pump station install | D51: 46225 | E51: B. Toure | F51: 0 | G51: Yes | H51: 0 | I51: 0
A52: Q-048 | B52: P03 | C52: Pump station install | D52: 46255 | E52: A. Camara | F52: 0 | G52: Yes | H52: 0 | I52: 0

Sheet Benefits_Log
A1: Benefits Realisation Log
A2: Re-measure each benefit periodically (monthly/quarterly). Planned and realised values are CUMULATIVE to the measurement date, in the same unit.
A4: Benefit ID | B4: Project ID | C4: Benefit description | D4: Measure / unit | E4: Measurement date | F4: Planned value (cumulative) | G4: Realised value (cumulative) | H4: Realisation % | I4: Benefit owner | J4: Remarks
A5: B01 | B5: P02 | C5: Haul cycle time reduction – fuel saving | D5: USD saved | E5: 46140 | F5: 25000 | G5: 22915 | H5: =IF(OR(F5="",F5=0,G5=""),"",G5/F5) -> 0.9166 | I5: A. Camara
A6: B01 | B6: P02 | C6: Haul cycle time reduction – fuel saving | D6: USD saved | E6: 46170 | F6: 50000 | G6: 44281 | H6: =IF(OR(F6="",F6=0,G6=""),"",G6/F6) -> 0.88562 | I6: F. Bah
A7: B01 | B7: P02 | C7: Haul cycle time reduction – fuel saving | D7: USD saved | E7: 46201 | F7: 75000 | G7: 74724 | H7: =IF(OR(F7="",F7=0,G7=""),"",G7/F7) -> 0.99632 | I7: B. Toure
A8: B01 | B8: P02 | C8: Haul cycle time reduction – fuel saving | D8: USD saved | E8: 46231 | F8: 100000 | G8: 94646 | H8: =IF(OR(F8="",F8=0,G8=""),"",G8/F8) -> 0.94646 | I8: F. Bah
A9: B01 | B9: P02 | C9: Haul cycle time reduction – fuel saving | D9: USD saved | E9: 46262 | F9: 125000 | G9: 113288 | H9: =IF(OR(F9="",F9=0,G9=""),"",G9/F9) -> 0.906304 | I9: I. Sylla
A10: B01 | B10: P02 | C10: Haul cycle time reduction – fuel saving | D10: USD saved | E10: 46293 | F10: 150000 | G10: 138991 | H10: =IF(OR(F10="",F10=0,G10=""),"",G10/F10) -> 0.92660667 | I10: B. Toure
A11: B01 | B11: P02 | C11: Haul cycle time reduction – fuel saving | D11: USD saved | E11: 46323 | F11: 175000 | G11: 169532 | H11: =IF(OR(F11="",F11=0,G11=""),"",G11/F11) -> 0.96875429 | I11: S. Keita
A12: B02 | B12: P04 | C12: Reduced secondary breaking cost | D12: USD saved | E12: 46201 | F12: 18000 | G12: 13380 | H12: =IF(OR(F12="",F12=0,G12=""),"",G12/F12) -> 0.74333333 | I12: A. Camara
A13: B02 | B13: P04 | C13: Reduced secondary breaking cost | D13: USD saved | E13: 46231 | F13: 36000 | G13: 27071 | H13: =IF(OR(F13="",F13=0,G13=""),"",G13/F13) -> 0.75197222 | I13: S. Keita
A14: B02 | B14: P04 | C14: Reduced secondary breaking cost | D14: USD saved | E14: 46262 | F14: 54000 | G14: 40821 | H14: =IF(OR(F14="",F14=0,G14=""),"",G14/F14) -> 0.75594444 | I14: A. Camara
A15: B02 | B15: P04 | C15: Reduced secondary breaking cost | D15: USD saved | E15: 46293 | F15: 72000 | G15: 52040 | H15: =IF(OR(F15="",F15=0,G15=""),"",G15/F15) -> 0.72277778 | I15: K. Conde
A16: B02 | B16: P04 | C16: Reduced secondary breaking cost | D16: USD saved | E16: 46323 | F16: 90000 | G16: 72530 | H16: =IF(OR(F16="",F16=0,G16=""),"",G16/F16) -> 0.80588889 | I16: B. Toure
... A21: B04 | B21: P08 | C21: Reduced bussing cost (on-site beds) | D21: USD saved | E21: 46323 | F21: 24000 | G21: 24560 | H21: =IF(OR(F21="",F21=0,G21=""),"",G21/F21) -> 1.0233333 | I21: O. Traore
H22: =IF(OR(F22="",F22=0,G22=""),"",G22/F22)
H23: =IF(OR(F23="",F23=0,G23=""),"",G23/F23)
H24: =IF(OR(F24="",F24=0,G24=""),"",G24/F24)
H25: =IF(OR(F25="",F25=0,G25=""),"",G25/F25)
H26: =IF(OR(F26="",F26=0,G26=""),"",G26/F26)
H27: =IF(OR(F27="",F27=0,G27=""),"",G27/F27)
H28: =IF(OR(F28="",F28=0,G28=""),"",G28/F28)
H29: =IF(OR(F29="",F29=0,G29=""),"",G29/F29)
H30: =IF(OR(F30="",F30=0,G30=""),"",G30/F30)
H31: =IF(OR(F31="",F31=0,G31=""),"",G31/F31)
H32: =IF(OR(F32="",F32=0,G32=""),"",G32/F32)
H33: =IF(OR(F33="",F33=0,G33=""),"",G33/F33)
... H504: =IF(OR(F504="",F504=0,G504=""),"",G504/F504)

Sheet CI_Log
A1: Continuous Improvement Initiatives
A2: Improvements to HOW projects are delivered. Count implemented per month = KPI; 'Benefit verified' checks they actually worked.
A4: CI ID | B4: Date proposed | C4: Initiative | D4: KPI targeted | E4: Owner | F4: Status | G4: Implementation date | H4: Expected benefit | I4: Benefit verified? | J4: Verified result | K4: Remarks
A5: CI-001 | B5: 46025 | C5: Weekly look-ahead planning meeting | D5: Milestone Completion Rate | E5: K. Conde | F5: Implemented | G5: 46049 | H5: Milestones hit on time | I5: Yes | J5: See monthly KPI trend
A6: CI-002 | B6: 46026 | C6: Standard CR form with 48h review SLA | D6: Change Request Approval Time | E6: S. Keita | F6: Implemented | G6: 46059 | H6: CR decided within 5 days | I6: Yes | J6: See monthly KPI trend
A7: CI-003 | B7: 46054 | C7: Daily issue triage at pre-start | D7: Issue Resolution Time | E7: A. Camara | F7: Implemented | G7: 46072 | H7: Issues closed in < 7 days | I7: Yes | J7: See monthly KPI trend
A8: CI-004 | B8: 46096 | C8: EVM reporting template for all projects | D8: Project Schedule Variance (SV%) | E8: A. Camara | F8: Implemented | G8: 46123 | H8: Early schedule-slip detection | I8: Yes | J8: See monthly KPI trend
A9: CI-005 | B9: 46086 | C9: Pre-pour QA checklist | D9: Project Quality Index | E9: B. Toure | F9: Implemented | G9: 46121 | H9: Fewer concrete rejections | I9: No
A10: CI-006 | B10: 46113 | C10: Monthly stakeholder pulse survey | D10: Stakeholder Satisfaction | E10: K. Conde | F10: Implemented | G10: 46126 | H10: Earlier complaint detection | I10: Yes | J10: See monthly KPI trend
A11: CI-007 | B11: 46155 | C11: Critical spares min/max review | D11: Resource Utilization Rate | E11: I. Sylla | F11: Implemented | G11: 46165 | H11: Less idle crew time | I11: Yes | J11: See monthly KPI trend
A12: CI-008 | B12: 46183 | C12: Risk review in monthly meeting | D12: Risk Mitigation Effectiveness | E12: M. Diallo | F12: Implemented | G12: 46211 | H12: Fewer risks materialising | I12: Yes | J12: See monthly KPI trend
A13: CI-009 | B13: 46181 | C13: Post-project lessons-learned workshop | D13: Project Success Rate | E13: I. Sylla | F13: Implemented | G13: 46201 | H13: Repeat mistakes avoided | I13: Yes | J13: See monthly KPI trend
A14: CI-010 | B14: 46210 | C14: Scope freeze gate before execution | D14: Scope Change Frequency | E14: B. Toure | F14: Implemented | G14: 46223 | H14: Fewer scope changes | I14: Yes | J14: See monthly KPI trend
A15: CI-011 | B15: 46241 | C15: Blast design peer review | D15: Project Quality Index | E15: F. Bah | F15: Implemented | G15: 46256 | H15: Fewer redrills | I15: Yes | J15: See monthly KPI trend
A16: CI-012 | B16: 46247 | C16: Benefits owner sign-off at closure | D16: Benefits Realization | E16: A. Camara | F16: Approved | H16: Benefits tracked after handover
A17: CI-013 | B17: 46273 | C17: Shift handover app | D17: Team Productivity Index | E17: F. Bah | F17: Proposed | H17: Productivity +3%
A18: CI-014 | B18: 46308 | C18: Supplier performance scorecard | D18: Budget Utilization | E18: S. Keita | F18: Approved | H18: Lower overspend

Sheet Settings
A1: Settings & Lists
A2: Yellow cells are editable. Lists feed the drop-downs in every log.
D3: Project Status | E3: Yes/No | F3: Direction | G3: Priority | H3: Change Type | I3: CR Decision | J3: Risk Status | K3: Risk Category | L3: Issue Status | M3: Milestone Status | N3: Action Status | O3: CI Status | P3: Owners
A4: Organisation / portfolio name | B4: Mining Services – Project Portfolio | D4: Not started | E4: Yes | F4: Higher | G4: Critical | H4: Scope | I4: Pending | J4: Open | K4: Safety | L4: Open | M4: Not started | N4: Open | O4: Proposed | P4: A. Camara
A5: Reporting year start (1st of month) | B5: 46023 | D5: Active | E5: No | F5: Lower | G5: High | H5: Schedule | I5: Approved | J5: Mitigated | K5: Technical | L5: In progress | M5: In progress | N5: In progress | O5: Approved | P5: M. Diallo
A6: Current reporting month (1st of month) | B6: =DATE(YEAR(TODAY()),MONTH(TODAY()),1) -> 46296 | D6: On hold | G6: Medium | H6: Cost | I6: Rejected | J6: Closed | K6: Commercial | L6: Resolved | M6: Completed | N6: Implemented | O6: In progress | P6: S. Keita
A7: Budget tolerance for 'within budget' | B7: 0.05 | D7: Completed | G7: Low | H7: Quality | J7: Occurred | K7: Schedule | N7: Cancelled | O7: Implemented | P7: F. Bah
A8: Prepared by | B8: Project Controls | D8: Cancelled | H8: Resource | K8: Environmental | O8: Rejected | P8: I. Sylla
K9: Community | P9: K. Conde
K10: Supply chain | P10: O. Traore
P11: B. Toure
A13: Tip: add owners/categories below the existing items in a list column (Owners accepts up to row 30).
